Workbook

Sheet Показатели рентабельности
A3: Отрасль 1. Технологии и полупроводники. | H3: Отрасль 2. Потребительский discretionary, e-commerce и онлайн-сервисы. | P3: Отрасль 3. Коммуникационные сервисы, digital-реклама и подписки. | X3: Отрасль 4. Здравоохранение, биотехнологии и медицинские технологии. | AF3: Отрасль 5. Потребительские товары повседневного спроса.
A6: 1 | B6: ROE | H6: 1 | I6: ROE | P6: 1 | Q6: ROE | X6: 1 | Y6: ROE | AF6: 1 | AG6: ROE
B7: Тикер | C7: 2024 | D7: 2023 | E7: 2022 | I7: Тикер | J7: 2024 | K7: 2023 | L7: 2022 | Q7: Тикер | R7: 2024 | S7: 2023 | T7: 2022 | Y7: Тикер | Z7: 2024 | AA7: 2023 | AB7: 2022 | AG7: Тикер | AH7: 2024 | AI7: 2023 | AJ7: 2022
A8: 1 | B8: AAPL | C8: =ROE!D2 -> 1.5741251 | D8: =ROE!C2 -> 1.7194951 | E8: =ROE!B2 -> 1.9695887 | H8: 1 | I8: AMZN | J8: =ROE!D5 -> 0.24289682 | K8: =ROE!C5 -> 0.17489753 | L8: =ROE!B5 -> -0.018638346 | P8: 1 | Q8: GOOGL | R8: =ROE!D11 -> 0.32908492 | S8: =ROE!C11 -> 0.27355646 | T8: =ROE!B11 -> 0.23413392 | X8: 1 | Y8: AMGN | Z8: =ROE!D4 -> 0.6755306 | AA8: =ROE!C4 -> 1.3579298 | AB8: =ROE!B4 -> 1.789675 | AF8: 1 | AG8: COST | AH8: =ROE!D9 -> 0.3026705 | AI8: =ROE!C9 -> 0.27536105 | AJ8: =ROE!B9 -> 0.2831121
A9: 2 | B9: MSFT | C9: =ROE!D16 -> 0.37133347 | D9: =ROE!C16 -> 0.38823924 | E9: =ROE!B16 -> 0.43675469 | H9: 2 | I9: MELI | J9: =ROE!D14 -> 0.51495554 | K9: =ROE!C14 -> 0.40302164 | L9: =ROE!B14 -> 0.26382047 | P9: 2 | Q9: META | R9: =ROE!D15 -> 0.37140602 | S9: =ROE!C15 -> 0.280392 | T9: =ROE!B15 -> 0.18454734 | X9: 2 | Y9: REGN | Z9: =ROE!D20 -> 0.15951069 | AA9: =ROE!C20 -> 0.16257548 | AB9: =ROE!B20 -> 0.19142252 | AF9: 2 | AG9: PEP | AH9: =ROE!D19 -> 0.52419002 | AI9: =ROE!C19 -> 0.50903175 | AJ9: =ROE!B19 -> 0.51956382
A10: 3 | B10: ASML | C10: =ROE!D6 -> 0.47427433 | D10: =ROE!C6 -> 0.70421143 | E10: =ROE!B6 -> 0.63833023 | H10: 3 | I10: TSLA | J10: =ROE!D22 -> 0.10520336 | K10: =ROE!C22 -> 0.27947232 | L10: =ROE!B22 -> 0.28147369 | P10: 3 | Q10: NFLX | R10: =ROE!D17 -> 0.38434898 | S10: =ROE!C17 -> 0.2614721 | T10: =ROE!B17 -> 0.21619278 | X10: 3 | Y10: GILD | Z10: =ROE!D10 -> 0.022768778 | AA10: =ROE!C10 -> 0.25707349 | AB10: =ROE!B10 -> 0.21619586 | AF10: 3 | AG10: MDLZ | AH10: =ROE!D13 -> 0.16687174 | AI10: =ROE!C13 -> 0.1796251 | AJ10: =ROE!B13 -> 0.10106759
A11: 4 | B11: AMD | C11: =ROE!D3 -> 0.028926494 | D11: =ROE!C3 -> 0.015437176 | E11: =ROE!B3 -> 0.024109589 | H11: 4 | I11: PDD | J11: =ROE!D18 -> 0.44923963 | K11: =ROE!C18 -> 0.39360053 | L11: =ROE!B18 -> 0.26779161 | P11: 4 | Q11: TMUS | R11: =ROE!D21 -> 0.1793351 | S11: =ROE!C21 -> 0.12379159 | T11: =ROE!B21 -> 0.037182727 | X11: 4 | Y11: VRTX | Z11: =ROE!D23 -> -0.031515152 | AA11: =ROE!C23 -> 0.22986622 | AB11: =ROE!B23 -> 0.23877464 | AF11: 4 | AG11: KDP | AH11: =ROE!D12 -> 0.057733528 | AI11: =ROE!C12 -> 0.085862761 | AJ11: =ROE!B12 -> 0.057151954
P12: 5 | Q12: CHTR | R12: =ROE!D8 -> 0.38113448 | S12: =ROE!C8 -> 0.45107647 | T12: =ROE!B8 -> 0.5543371 | AF12: 5 | AG12: CCEP | AH12: =ROE!D7 -> 0.17224415 | AI12: =ROE!C7 -> 0.21643001 | AJ12: =ROE!B7 -> 0.20249765
A14: 2 | B14: ROA | H14: 2 | I14: ROA | P14: 2 | Q14: ROA | X14: 2 | Y14: ROA | AF14: 2 | AG14: ROA
C15: 2024 | D15: 2023 | E15: 2022 | J15: 2024 | K15: 2023 | L15: 2022 | R15: 2024 | S15: 2023 | T15: 2022 | Z15: 2024 | AA15: 2023 | AB15: 2022 | AH15: 2024 | AI15: 2023 | AJ15: 2022
A16: 1 | B16: AAPL | C16: =ROA!D2 -> 0.26126208 | D16: =ROA!C2 -> 0.27503126 | E16: =ROA!B2 -> 0.28292441 | H16: 1 | I16: AMZN | J16: =ROA!D5 -> 0.10279437 | K16: =ROA!C5 -> 0.061431821 | L16: =ROA!B5 -> -0.0058831793 | P16: 1 | Q16: GOOGL | R16: =ROA!D11 -> 0.23484017 | S16: =ROA!C11 -> 0.1922606 | T16: =ROA!B11 -> 0.16418809 | X16: 1 | Y16: AMGN | Z16: =ROA!D4 -> 0.043282026 | AA16: =ROA!C4 -> 0.082785395 | AB16: =ROA!B4 -> 0.10061271 | AF16: 1 | AG16: COST | AH16: =ROA!D9 -> 0.10613362 | AI16: =ROA!C9 -> 0.094502854 | AJ16: =ROA!B9 -> 0.091076271
A17: 2 | B17: MSFT | C17: =ROA!D16 -> 0.19074187 | D17: =ROA!C16 -> 0.18630152 | E17: =ROA!B16 -> 0.19936959 | H17: 2 | I17: MELI | J17: =ROA!D14 -> 0.089282377 | K17: =ROA!C14 -> 0.062970524 | L17: =ROA!B14 -> 0.035090274 | P17: 2 | Q17: META | R17: =ROA!D15 -> 0.24663965 | S17: =ROA!C15 -> 0.18826532 | T17: =ROA!B15 -> 0.12491453 | X17: 2 | Y17: REGN | Z17: =ROA!D20 -> 0.12458004 | AA17: =ROA!C20 -> 0.12693215 | AB17: =ROA!B20 -> 0.1485016 | AF17: 2 | AG17: PEP | AH17: =ROA!D19 -> 0.095798202 | AI17: =ROA!C19 -> 0.094186276 | AJ17: =ROA!B19 -> 0.096651372 | AL17: =ROE!AL4 | AM17: =ROE!AM4 | AN17: =ROE!AN4
A18: 3 | B18: ASML | C18: =ROA!D6 -> 0.17101859 | D18: =ROA!C6 -> 0.20559181 | E18: =ROA!B6 -> 0.15493493 | H18: 3 | I18: TSLA | J18: =ROA!D22 -> 0.062355699 | K18: =ROA!C22 -> 0.15875654 | L18: =ROA!B22 -> 0.1528213 | P18: 3 | Q18: NFLX | R18: =ROA!D17 -> 0.1702116 | S18: =ROA!C17 -> 0.11113059 | T18: =ROA!B17 -> 0.092436371 | X18: 3 | Y18: GILD | Z18: =ROA!D10 -> 0.0079260238 | AA18: =ROA!C10 -> 0.090425872 | AB18: =ROA!B10 -> 0.072691583 | AF18: 3 | AG18: MDLZ | AH18: =ROA!D13 -> 0.065924168 | AI18: =ROA!C13 -> 0.069574611 | AJ18: =ROA!B13 -> 0.038181026 | AL18: =ROE!AL18 | AM18: =ROE!AM18 | AN18: =ROE!AN18
A19: 4 | B19: AMD | C19: =ROA!D3 -> 0.02393681 | D19: =ROA!C3 -> 0.012608423 | E19: =ROA!B3 -> 0.019532406 | H19: 4 | I19: PDD | J19: =ROA!D18 -> 0.26358662 | K19: =ROA!C18 -> 0.20514949 | L19: =ROA!B18 -> 0.13300467 | P19: 4 | Q19: TMUS | R19: =ROA!D21 -> 0.054551534 | S19: =ROA!C21 -> 0.039697389 | T19: =ROA!B21 -> 0.01225525 | X19: 4 | Y19: VRTX | Z19: =ROA!D23 -> -0.02366592 | AA19: =ROA!C23 -> 0.17707938 | AB19: =ROA!B23 -> 0.18302123 | AF19: 4 | AG19: KDP | AH19: =ROA!D12 -> 0.027302008 | AI19: =ROA!C12 -> 0.041955621 | AJ19: =ROA!B12 -> 0.02770222 | AL19: =ROE!AL5 | AM19: =ROE!AM5 | AN19: =ROE!AN5
P20: 5 | Q20: CHTR | R20: =ROA!D8 -> 0.034204426 | S20: =ROA!C8 -> 0.031242716 | T20: =ROA!B8 -> 0.034977132 | AF20: 5 | AG20: CCEP | AH20: =ROA!D7 -> 0.046989429 | AI20: =ROA!C7 -> 0.056994553 | AJ20: =ROA!B7 -> 0.051444751 | AL20: =ROE!AL8 | AM20: =ROE!AM8 | AN20: =ROE!AN8
A22: 3 | B22: ROIC | H22: 3 | I22: ROIC | P22: 3 | Q22: ROIC | X22: 3 | Y22: ROIC | AF22: 3 | AG22: ROIC
B23: Тикер | C23: 2024 | D23: 2023 | E23: 2022 | I23: Тикер | J23: 2024 | K23: 2023 | L23: 2022 | Q23: Тикер | R23: 2024 | S23: 2023 | T23: 2022 | Y23: Тикер | Z23: 2024 | AA23: 2023 | AB23: 2022 | AG23: Тикер | AH23: 2024 | AI23: 2023 | AJ23: 2022
A24: 1 | B24: AAPL | C24: =ROIC!D2 -> 0.5717837 | D24: =ROIC!C2 -> 0.56268883 | E24: =ROIC!B2 -> 0.5861678 | H24: 1 | I24: AMZN | J24: =ROIC!D5 -> 0.16570278 | K24: =ROIC!C5 -> 0.12369397 | L24: =ROIC!B5 -> -0.013225153 | P24: 1 | Q24: GOOGL | R24: =ROIC!D11 -> 0.29866607 | S24: =ROIC!C11 -> 0.25083967 | T24: =ROIC!B11 -> 0.22405925 | X24: 1 | Y24: AMGN | Z24: =ROIC!D4 -> 0.1044278 | AA24: =ROIC!C4 -> 0.12951488 | AB24: =ROIC!B4 -> 0.18321436 | AF24: 1 | AG24: COST | AH24: =ROIC!D9 -> 0.25478739 | AI24: =ROIC!C9 -> 0.2034084 | AJ24: =ROIC!B9 -> 0.22185394
A25: 2 | B25: MSFT | C25: =ROIC!D16 -> 0.28283015 | D25: =ROIC!C16 -> 0.29178372 | E25: =ROIC!B16 -> 0.34453327 | H25: 2 | I25: MELI | J25: =ROIC!D14 -> 0.20521446 | K25: =ROIC!C14 -> 0.14717533 | L25: =ROIC!B14 -> 0.086535518 | P25: 2 | Q25: META | R25: =ROIC!D15 -> 0.29788184 | S25: =ROIC!C15 -> 0.23004941 | T25: =ROIC!B15 -> 0.17214404 | X25: 2 | Y25: REGN | Z25: =ROIC!D20 -> 0.14243277 | AA25: =ROIC!C20 -> 0.1438807 | AB25: =ROIC!B20 -> 0.17818489 | AF25: 2 | AG25: PEP | AH25: =ROIC!D19 -> 0.16627141 | AI25: =ROIC!C19 -> 0.15671696 | AJ25: =ROIC!B19 -> 0.17370179
A26: 3 | B26: ASML | C26: =ROIC!D6 -> 0.32352142 | D26: =ROIC!C6 -> 0.43000792 | E26: =ROIC!B6 -> 0.42366929 | H26: 3 | I26: TSLA | J26: =ROIC!D22 -> 0.091984028 | K26: =ROIC!C22 -> 0.22600685 | L26: =ROIC!B22 -> 0.27299493 | P26: 3 | Q26: NFLX | R26: =ROIC!D17 -> 0.2316083 | S26: =ROIC!C17 -> 0.17250553 | T26: =ROIC!B17 -> 0.14501834 | X26: 3 | Y26: GILD | Z26: =ROIC!D10 -> 0.025134907 | AA26: =ROIC!C10 -> 0.13350849 | AB26: =ROIC!B10 -> 0.11405849 | AF26: 3 | AG26: MDLZ | AH26: =ROIC!D13 -> 0.11595106 | AI26: =ROIC!C13 -> 0.099481211 | AJ26: =ROIC!B13 -> 0.0537239
A27: 4 | B27: AMD | C27: =ROIC!D3 -> 0.028375872 | D27: =ROIC!C3 -> 0.017452788 | E27: =ROIC!B3 -> 0.024521865 | H27: 4 | I27: PDD | J27: =ROIC!D18 -> 0.35282257 | K27: =ROIC!C18 -> 0.31103696 | L27: =ROIC!B18 -> 0.23821755 | P27: 4 | Q27: TMUS | R27: =ROIC!D21 -> 0.099766901 | S27: =ROIC!C21 -> 0.077567879 | T27: =ROIC!B21 -> 0.037845105 | X27: 4 | Y27: VRTX | Z27: =ROIC!D23 -> -0.036658612 | AA27: =ROIC!C23 -> 0.20796146 | AB27: =ROIC!B23 -> 0.24186624 | AF27: 4 | AG27: KDP | AH27: =ROIC!D12 -> 0.050113377 | AI27: =ROIC!C12 -> 0.066209749 | AJ27: =ROIC!B12 -> 0.054282691
P28: 5 | Q28: CHTR | R28: =ROIC!D8 -> 0.089201829 | S28: =ROIC!C8 -> 0.084576624 | T28: =ROIC!B8 -> 0.088268271 | AF28: 5 | AG28: CCEP | AH28: =ROIC!D7 -> 0.084998954 | AI28: =ROIC!C7 -> 0.095917116 | AJ28: =ROIC!B7 -> 0.088173681
A30: 4 | B30: Margin | H30: 4 | I30: Margin | P30: 4 | Q30: Margin | X30: 4 | Y30: Margin | AF30: 4 | AG30: Margin
B31: Тикер | C31: 2024 | D31: 2023 | E31: 2022 | I31: Тикер | J31: 2024 | K31: 2023 | L31: 2022 | Q31: Тикер | R31: 2024 | S31: 2023 | T31: 2022 | Y31: Тикер | Z31: 2024 | AA31: 2023 | AB31: 2022 | AG31: Тикер | AH31: 2024 | AI31: 2023 | AJ31: 2022
A32: 1 | B32: AAPL | C32: ='Net Profit Margin'!D2 -> 0.23971256 | D32: ='Net Profit Margin'!C2 -> 0.25306234 | E32: ='Net Profit Margin'!B2 -> 0.25309641 | H32: 1 | I32: AMZN | J32: ='Net Profit Margin'!D5 -> 0.092871172 | K32: ='Net Profit Margin'!C5 -> 0.052932836 | L32: ='Net Profit Margin'!B5 -> -0.005295895 | P32: 1 | Q32: GOOGL | R32: ='Net Profit Margin'!D11 -> 0.28603672 | S32: ='Net Profit Margin'!C11 -> 0.24006649 | T32: ='Net Profit Margin'!B11 -> 0.21203807 | X32: 1 | Y32: AMGN | Z32: ='Net Profit Margin'!D4 -> 0.12236716 | AA32: ='Net Profit Margin'!C4 -> 0.23827598 | AB32: ='Net Profit Margin'!B4 -> 0.2489078 | AF32: 1 | AG32: COST | AH32: ='Net Profit Margin'!D9 -> 0.028952302 | AI32: ='Net Profit Margin'!C9 -> 0.02596888 | AJ32: ='Net Profit Margin'!B9 -> 0.025749711
A33: 2 | B33: MSFT | C33: ='Net Profit Margin'!D16 -> 0.35955973 | D33: ='Net Profit Margin'!C16 -> 0.34146238 | E33: ='Net Profit Margin'!B16 -> 0.36686337 | H33: 2 | I33: MELI | J33: ='Net Profit Margin'!D14 -> 0.091976705 | K33: ='Net Profit Margin'!C14 -> 0.065333951 | L33: ='Net Profit Margin'!B14 -> 0.04471243 | P33: 2 | Q33: META | R33: ='Net Profit Margin'!D15 -> 0.37908584 | S33: ='Net Profit Margin'!C15 -> 0.28982521 | T33: ='Net Profit Margin'!B15 -> 0.19895548 | X33: 2 | Y33: REGN | Z33: ='Net Profit Margin'!D20 -> 0.31070272 | AA33: ='Net Profit Margin'!C20 -> 0.30140579 | AB33: ='Net Profit Margin'!B20 -> 0.35639823 | AF33: 2 | AG33: PEP | AH33: ='Net Profit Margin'!D19 -> 0.10427417 | AI33: ='Net Profit Margin'!C19 -> 0.09920084 | AJ33: ='Net Profit Margin'!B19 -> 0.10313455
A34: 3 | B34: ASML | C34: ='Net Profit Margin'!D6 -> 0.26789891 | D34: ='Net Profit Margin'!C6 -> 0.28444944 | E34: ='Net Profit Margin'!B6 -> 0.26562574 | H34: 3 | I34: TSLA | J34: ='Net Profit Margin'!D22 -> 0.072985976 | K34: ='Net Profit Margin'!C22 -> 0.15499158 | L34: ='Net Profit Margin'!B22 -> 0.15446466 | P34: 3 | Q34: NFLX | R34: ='Net Profit Margin'!D17 -> 0.22336962 | S34: ='Net Profit Margin'!C17 -> 0.16036362 | T34: ='Net Profit Margin'!B17 -> 0.14207958 | X34: 3 | Y34: GILD | Z34: ='Net Profit Margin'!D10 -> 0.01669333 | AA34: ='Net Profit Margin'!C10 -> 0.20891724 | AB34: ='Net Profit Margin'!B10 -> 0.16832228 | AF34: 3 | AG34: MDLZ | AH34: ='Net Profit Margin'!D13 -> 0.1265333 | AI34: ='Net Profit Margin'!C13 -> 0.1376888 | AJ34: ='Net Profit Margin'!B13 -> 0.086264923
A35: 4 | B35: AMD | C35: ='Net Profit Margin'!D3 -> 0.063641652 | D35: ='Net Profit Margin'!C3 -> 0.037654321 | E35: ='Net Profit Margin'!B3 -> 0.055929833 | H35: 4 | I35: PDD | J35: ='Net Profit Margin'!D18 -> 0.28548554 | K35: ='Net Profit Margin'!C18 -> 0.24239516 | L35: ='Net Profit Margin'!B18 -> 0.24156437 | P35: 4 | Q35: TMUS | R35: ='Net Profit Margin'!D21 -> 0.13929975 | S35: ='Net Profit Margin'!C21 -> 0.10587082 | T35: ='Net Profit Margin'!B21 -> 0.032549547 | X35: 4 | Y35: VRTX | Z35: ='Net Profit Margin'!D23 -> -0.0486021 | AA35: ='Net Profit Margin'!C23 -> 0.36675718 | AB35: ='Net Profit Margin'!B23 -> 0.37197532 | AF35: 4 | AG35: KDP | AH35: ='Net Profit Margin'!D12 -> 0.093870106 | AI35: ='Net Profit Margin'!C12 -> 0.1472256 | AJ35: ='Net Profit Margin'!B12 -> 0.10215551
P36: 5 | Q36: CHTR | R36: ='Net Profit Margin'!D8 -> 0.092275574 | S36: ='Net Profit Margin'!C8 -> 0.08345084 | T36: ='Net Profit Margin'!B8 -> 0.093572989 | AF36: 5 | AG36: CCEP | AH36: ='Net Profit Margin'!D7 -> 0.069380566 | AI36: ='Net Profit Margin'!C7 -> 0.091192219 | AJ36: ='Net Profit Margin'!B7 -> 0.087066975
A38: Выводы (показатели рентабельности): | H38: Выводы (показатели рентабельности): | P38: Выводы (показатели рентабельности): | X38: Выводы (показатели рентабельности): | AF38: Выводы (показатели рентабельности):
A40: По итогам анализа показателей рентабельности в группе компаний технологического и полупроводникового сектора для дальнейшего рассмотрения были отобраны Apple (AAPL) и ASML Holding (ASML). Apple занимает первое место по показателям ROE (157,41%), ROA (26,13%) и ROIC (57,18%) в 2024 году, что говорит о наиболее высокой эффективности использования собственного капитала, активов и инвестированного капитала среди рассматриваемых компаний. ASML, в свою очередь, демонстрирует высокие значения по всем четырём метрикам, занимая второе место по совокупности показателей и опережая Microsoft по ROE и ROIC. Кроме того, компания сохраняет высокий уровень рентабельности продаж (26,79%), что подтверждает её способность эффективно конвертировать выручку в прибыль. | H40: По итогам анализа показателей рентабельности в группе компаний технологического и полупроводникового сектора для дальнейшего рассмотрения были отобраны Apple (AAPL) и ASML Holding (ASML). Apple занимает первое место по показателям ROE (157,41%), ROA (26,13%) и ROIC (57,18%) в 2024 году, что говорит о наиболее высокой эффективности использования собственного капитала, активов и инвестированного капитала среди рассматриваемых компаний. ASML, в свою очередь, демонстрирует высокие значения по всем четырём метрикам, занимая второе место по совокупности показателей и опережая Microsoft по ROE и ROIC. Кроме того, компания сохраняет высокий уровень рентабельности продаж (26,79%), что подтверждает её способность эффективно конвертировать выручку в прибыль. | P40: По итогам анализа показателей рентабельности в данном блоке выбраны Alphabet/Google (GOOGL) и Meta (META). Alphabet лидирует по ROA (23.48%) и ROIC (29.87%) в 2024 году, что свидетельствует об эффективном использовании активов и инвестированного капитала. Meta показывает наибольшую Profit Margin в отрасли (37.91%) и высокий ROE (37.14%), демонстрируя выдающуюся способность генерировать прибыль. Обе компании показывают устойчивую положительную динамику по всем четырём метрикам на протяжении 2022–2024 годов. Netflix занимает среднюю позицию без явного лидерства ни по одному показателю. T-Mobile и Charter выбывают ввиду низкой рентабельности по всем метрикам и высоккой долговой нагрузки, при этом высокий ROE Charter носит технический характер и объясняется долговой нагрузкой, а не реальной эффективностью бизнеса. | X40: По итогам анализа показателей рентабельности в отрасли здравоохранения, биотехнологий и медицинских технологий были отобраны Regeneron Pharmaceuticals (REGN) и Amgen (AMGN). REGN занимает первое место по показателям ROA (12,46%) и показывает наиболее высокую рентабельность продаж в отрасли (31,07% в 2024 году) при стабильном уровне ROE и ROIC (15,95% и 14,24% соответсственно) на протяжении всего анализируемого периода 2022 - 2024 годов. Подобная ситуация указывает об устойчивой способности данной компании конвертировать выручку в прибыль, не влезая при этом в долги. AMGN, в свою же очередь, лидирует по показателю ROE (67,55% в 2024 году), что обусловено сочетанием высокой операционной эффективности и умеренного долга, характерного для крупных биофармацевтических компаний с диверсифицированным портфелем препаратов. Несмотря на снижение рентабельности по многим метрикам в 2022 году, AMGN сохраняет хороший ROIC и уверенную маржу на уровне 12,24%. | AF40: По итогам анализа показателей рентабельности в группе компаний сектора потребительских товаров повседневного спроса были выбраны Costco Wholesale Corporation (COST) и Pepsico, Inc. (PEP). PepsiCo занимает первое место по показателю ROE на протяжении всего рассматриваемого периода (52.42% в 2024 году), что почти вдвое выше ближайшего конкурента (COST). Высокий ROE при двузначной чистой марже (~10%) указывает на то, что Pepsico зарабатывает на операционной эффективности, а не наращивает показатель за счёт долговой нагрузки. ROA (~9.6%) и ROIC (~17%) остаются стабильно высокими на протяжении всех трёх лет, что подтверждает устойчивость бизнес-модели и способность Pepsico последовательно генерировать прибыль на вложенный капитал. Costco, несмотря на минимальную чистую маржу в группе (2.90% в 2024 году), фиксирует наивысшие значения ROA (10.61%) и ROIC (25.48%) и уступает PepsiCo только по ROE. Компания Costco намеренно держит минимальную торговую наценку, получая основную прибыль за счёт членских взносов покупателей, поэтому при скромной марже Costco показывает выдающуюся отдачу на активы и вложенный капитал (высокая оборачиваемость товаров компенсирует низкую рентабельность каждой продажи).
A41: AAPL | H41: PDD | P41: GOOGL | X41: AMGN | AF41: COST
A42: ASML | H42: MELI | P42: META | X42: REGN | AF42: PEP

Sheet Мультипликаторы
A2: Отрасль 1. Технологии и полупроводники. | H2: Отрасль 2. Потребительский discretionary, e-commerce и онлайн-сервисы. | P2: Отрасль 3. Коммуникационные сервисы, digital-реклама и подписки. | X2: Отрасль 4. Здравоохранение, биотехнологии и медицинские технологии. | AF2: Отрасль 5. Потребительские товары повседневного спроса.
A5: 1 | B5: P/E | H5: 1 | I5: P/E | P5: 1 | Q5: P/E | X5: 1 | Y5: P/E | AF5: 1 | AG5: P/E
B6: Тикер | C6: 2024 | D6: 2023 | E6: 2022 | I6: Тикер | J6: 2024 | K6: 2023 | L6: 2022 | Q6: Тикер | R6: 2024 | S6: 2023 | T6: 2022 | Y6: Тикер | Z6: 2024 | AA6: 2023 | AB6: 2022 | AG6: Тикер | AH6: 2024 | AI6: 2023 | AJ6: 2022
A7: 1 | B7: AAPL | C7: ='P E'!D2 -> 40.926022 | D7: ='P E'!C2 -> 31.056296 | E7: ='P E'!B2 -> 20.910247 | H7: 1 | I7: AMZN | J7: ='P E'!D5 -> 39.672694 | K7: ='P E'!C5 -> 52.393104 | L7: ='P E'!B5 -> -311.11111 | P7: 1 | Q7: GOOGL | R7: ='P E'!D11 -> 23.436426 | S7: ='P E'!C11 -> 23.887058 | T7: ='P E'!B11 -> 19.190079 | X7: 1 | Y7: AMGN | Z7: ='P E'!D4 -> 32.911062 | AA7: ='P E'!C4 -> 21.367546 | AB7: ='P E'!B4 -> 19.422877 | AF7: 1 | AG7: COST | AH7: ='P E'!D9 -> 54.888352 | AI7: ='P E'!C9 -> 45.97496 | AJ7: ='P E'!B9 -> 33.250009
A8: 2 | B8: MSFT | C8: ='P E'!D16 -> 35.301558 | D8: ='P E'!C16 -> 38.106717 | E8: ='P E'!B16 -> 24.163899 | H8: 2 | I8: MELI | J8: ='P E'!D14 -> 45.116475 | K8: ='P E'!C14 -> 80.757453 | L8: ='P E'!B14 -> 88.797481 | P8: 2 | Q8: META | R8: ='P E'!D15 -> 24.441331 | S8: ='P E'!C15 -> 23.618286 | T8: ='P E'!B15 -> 13.900232 | X8: 2 | Y8: REGN | Z8: ='P E'!D20 -> 18.427095 | AA8: ='P E'!C20 -> 25.053071 | AB8: ='P E'!B20 -> 18.722652 | AF8: 2 | AG8: PEP | AH8: ='P E'!D19 -> 20.852117 | AI8: ='P E'!C19 -> 23.90929 | AJ8: ='P E'!B19 -> 25.261886
A9: 3 | B9: ASML | C9: ='P E'!D6 -> 35.557236 | D9: ='P E'!C6 -> 35.997379 | E9: ='P E'!B6 -> 32.967321 | H9: 3 | I9: TSLA | J9: ='P E'!D22 -> 197.96078 | K9: ='P E'!C22 -> 57.651971 | L9: ='P E'!B22 -> 34.027624 | P9: 3 | Q9: NFLX | R9: ='P E'!D17 -> 44.94806 | S9: ='P E'!C17 -> 40.472153 | T9: ='P E'!B17 -> 29.636182 | X9: 3 | Y9: GILD | Z9: ='P E'!D10 -> 235.1328 | AA9: ='P E'!C10 -> 16.730058 | AB9: ='P E'!B10 -> 21.10331 | AF9: 3 | AG9: MDLZ | AH9: ='P E'!D13 -> 16.784746 | AI9: ='P E'!C13 -> 18.721225 | AJ9: ='P E'!B13 -> 31.101937
A10: 4 | B10: AMD | C10: ='P E'!D3 -> 120.79 | D10: ='P E'!C3 -> 278.13208 | E10: ='P E'!B3 -> 77.107139 | H10: 4 | I10: PDD | J10: ='P E'!D18 -> 1.2761842 | K10: ='P E'!C18 -> 3.5546647 | L10: ='P E'!B18 -> 3.7203469 | P10: 4 | Q10: TMUS | R10: ='P E'!D21 -> 22.270373 | S10: ='P E'!C21 -> 22.221057 | T10: ='P E'!B21 -> 64.990849 | X10: 4 | Y10: VRTX | Z10: ='P E'!D23 -> -193.60578 | AA10: ='P E'!C23 -> 29.293738 | AB10: ='P E'!B23 -> 22.525741 | AF10: 4 | AG10: KDP | AH10: ='P E'!D12 -> 29.185956 | AI10: ='P E'!C12 -> 19.981232 | AJ10: ='P E'!B12 -> 32.020773
P11: 5 | Q11: CHTR | R11: ='P E'!D8 -> 9.8018298 | S11: ='P E'!C8 -> 12.96032 | T11: ='P E'!B8 -> 11.03123 | AF11: 5 | AG11: CCEP | AH11: ='P E'!D7 -> 24.040782 | AI11: ='P E'!C7 -> 17.235252 | AJ11: ='P E'!B7 -> 15.274151
A13: 2 | B13: PEG | H13: 2 | I13: PEG | P13: 2 | Q13: PEG | X13: 2 | Y13: PEG | AF13: 2 | AG13: PEG
C14: 2024 | J14: 2024 | R14: 2024 | Z14: 2024 | AH14: 2024
A15: 1 | B15: AAPL | C15: =PEG!B2 -> -16650.045 | H15: 1 | I15: AMZN | J15: =PEG!B5 | P15: 1 | Q15: GOOGL | R15: =PEG!B11 -> 71.487486 | X15: 1 | Y15: AMGN | Z15: =PEG!B4 -> -156.8032 | AF15: 1 | AG15: COST | AH15: =PEG!B9 -> 447.63244
A16: 2 | B16: MSFT | C16: =PEG!B16 -> 333.657 | H16: 2 | I16: MELI | J16: =PEG!B14 -> 45.632679 | P16: 2 | Q16: META | R16: =PEG!B15 -> 36.664131 | X16: 2 | Y16: REGN | Z16: =PEG!B20 -> 11747.266 | AF16: 2 | AG16: PEP | AH16: =PEG!B19 -> 515.39136
A17: 3 | B17: ASML | C17: =PEG!B6 -> 377.4867 | H17: 3 | I17: TSLA | P17: 3 | Q17: NFLX | R17: =PEG!B17 -> 109.17035 | X17: 3 | Y17: GILD | Z17: =PEG!B10 -> -347.3687 | AF17: 3 | AG17: MDLZ | AH17: =PEG!B13 -> 52.297749
A18: 4 | B18: AMD | C18: =PEG!B3 -> 1326.0592 | H18: 4 | I18: PDD | J18: =PEG!B18 -> 1.4804417 | P18: 4 | Q18: TMUS | R18: =PEG!B21 -> 19.108264 | X18: 4 | Y18: VRTX | Z18: =PEG!B23 | AF18: 4 | AG18: KDP | AH18: =PEG!B12 -> 1488.3421
P19: 5 | Q19: CHTR | R19: =PEG!B8 -> 147.20553 | AF19: 5 | AG19: CCEP | AH19: =PEG!B7 -> -741.05925
A21: 3 | B21: P/S | H21: 3 | I21: P/S | P21: 3 | Q21: P/S | X21: 3 | Y21: P/S | AF21: 3 | AG21: P/S
B22: Тикер | C22: 2024 | D22: 2023 | E22: 2022 | I22: Тикер | J22: 2024 | K22: 2023 | L22: 2022 | Q22: Тикер | R22: 2024 | S22: 2023 | T22: 2022 | Y22: Тикер | Z22: 2024 | AA22: 2023 | AB22: 2022 | AG22: Тикер | AH22: 2024 | AI22: 2023 | AJ22: 2022
A23: 1 | B23: AAPL | C23: ='P S'!D2 -> 9.8047479 | D23: ='P S'!C2 -> 7.8539862 | E23: ='P S'!B2 -> 5.289538 | H23: 1 | I23: AMZN | J23: ='P S'!D5 -> 3.686883 | K23: ='P S'!C5 -> 2.7734797 | L23: ='P S'!B5 -> 1.6651835 | P23: 1 | Q23: GOOGL | R23: ='P S'!D11 -> 6.7007241 | S23: ='P S'!C11 -> 5.7339073 | T23: ='P S'!B11 -> 4.071269 | X23: 1 | Y23: AMGN | Z23: ='P S'!D4 -> 4.0271939 | AA23: ='P S'!C4 -> 5.0933589 | AB23: ='P S'!B4 -> 4.8341441 | AF23: 1 | AG23: COST | AH23: ='P S'!D9 -> 1.5887578 | AI23: ='P S'!C9 -> 1.1941915 | AJ23: ='P S'!B9 -> 0.85619381
A24: 2 | B24: MSFT | C24: ='P S'!D16 -> 12.692759 | D24: ='P S'!C16 -> 13.006249 | E24: ='P S'!B16 -> 8.8676525 | H24: 2 | I24: MELI | J24: ='P S'!D14 -> 4.1492001 | K24: ='P S'!C14 -> 5.3060422 | L24: ='P S'!B14 -> 4.0298938 | P24: 2 | Q24: META | R24: ='P S'!D15 -> 9.2668544 | S24: ='P S'!C15 -> 6.8443396 | T24: ='P S'!B15 -> 2.7667409 | X24: 2 | Y24: REGN | Z24: ='P S'!D20 -> 5.7257818 | AA24: ='P S'!C20 -> 7.5506612 | AB24: ='P S'!B20 -> 6.6720588 | AF24: 2 | AG24: PEP | AH24: ='P S'!D19 -> 2.1741329 | AI24: ='P S'!C19 -> 2.3714243 | AJ24: ='P S'!B19 -> 2.6037766
A25: 3 | B25: ASML | C25: ='P S'!D6 -> 9.5273348 | D25: ='P S'!C6 -> 10.599322 | E25: ='P S'!B6 -> 9.9584559 | H25: 3 | I25: TSLA | J25: ='P S'!D22 -> 13.2946 | K25: ='P S'!C22 -> 8.9425119 | L25: ='P S'!B22 -> 5.2546034 | P25: 3 | Q25: NFLX | R25: ='P S'!D17 -> 10.03878 | S25: ='P S'!C17 -> 6.489626 | T25: ='P S'!B17 -> 4.2092072 | X25: 3 | Y25: GILD | Z25: ='P S'!D10 -> 3.8997994 | AA25: ='P S'!C10 -> 3.4927298 | AB25: ='P S'!B10 -> 3.5534567 | AF25: 3 | AG25: MDLZ | AH25: ='P S'!D13 -> 2.1218672 | AI25: ='P S'!C13 -> 2.5779111 | AJ25: ='P S'!B13 -> 2.6806362
A26: 4 | B26: AMD | C26: ='P S'!D3 -> 7.6685372 | D26: ='P S'!C3 -> 10.561784 | E26: ='P S'!B3 -> 4.3114133 | H26: 4 | I26: PDD | J26: ='P S'!D18 -> 0.36426971 | K26: ='P S'!C18 -> 0.86254138 | L26: ='P S'!B18 -> 0.89966677 | P26: 4 | Q26: TMUS | R26: ='P S'!D21 -> 3.1006833 | S26: ='P S'!C21 -> 2.3528399 | T26: ='P S'!B21 -> 2.1122178 | X26: 4 | Y26: VRTX | Z26: ='P S'!D23 -> 9.4242641 | AA26: ='P S'!C23 -> 10.739964 | AB26: ='P S'!B23 -> 8.3781672 | AF26: 4 | AG26: KDP | AH26: ='P S'!D12 -> 2.731542 | AI26: ='P S'!C12 -> 2.9444734 | AJ26: ='P S'!B12 -> 3.2865541
P27: 5 | Q27: CHTR | R27: ='P S'!D8 -> 0.9045355 | S27: ='P S'!C8 -> 1.0816611 | T27: ='P S'!B8 -> 1.0321616 | AF27: 5 | AG27: CCEP | AH27: ='P S'!D7 -> 1.6701745 | AI27: ='P S'!C7 -> 1.5717209 | AJ27: ='P S'!B7 -> 1.3298741
A29: 4 | B29: EV/EBITDA | H29: 4 | I29: EV/EBITDA | X29: 4 | Y29: EV/EBITDA
B30: Тикер | C30: 2024 | D30: 2023 | E30: 2022 | I30: Тикер | J30: 2024 | K30: 2023 | L30: 2022 | P30: 4 | Q30: EV/EBITDA | Y30: Тикер | Z30: 2024 | AA30: 2023 | AB30: 2022 | AF30: 4 | AG30: EV/EBITDA
A31: 1 | B31: AAPL | C31: ='EV EBITDA'!D2 -> 29.040967 | D31: ='EV EBITDA'!C2 -> 24.570323 | E31: ='EV EBITDA'!B2 -> 16.811936 | H31: 1 | I31: AMZN | J31: ='EV EBITDA'!D5 -> 19.417689 | K31: ='EV EBITDA'!C5 -> 18.527309 | L31: ='EV EBITDA'!B5 -> 24.564716 | Q31: Тикер | R31: 2024 | S31: 2023 | T31: 2022 | X31: 1 | Y31: AMGN | Z31: ='EV EBITDA'!D4 -> 13.681561 | AA31: ='EV EBITDA'!C4 -> 13.326855 | AB31: ='EV EBITDA'!B4 -> 13.030255 | AG31: Тикер | AH31: 2024 | AI31: 2023 | AJ31: 2022
A32: 2 | B32: MSFT | C32: ='EV EBITDA'!D16 -> 23.758441 | D32: ='EV EBITDA'!C16 -> 26.455014 | E32: ='EV EBITDA'!B16 -> 18.012235 | H32: 2 | I32: MELI | J32: ='EV EBITDA'!D14 -> 28.134079 | K32: ='EV EBITDA'!C14 -> 36.843794 | L32: ='EV EBITDA'!B14 -> 35.619314 | P32: 1 | Q32: GOOGL | R32: ='EV EBITDA'!D11 -> 17.315997 | S32: ='EV EBITDA'!C11 -> 18.022085 | T32: ='EV EBITDA'!B11 -> 13.613216 | X32: 2 | Y32: REGN | Z32: ='EV EBITDA'!D20 -> 15.331657 | AA32: ='EV EBITDA'!C20 -> 21.097401 | AB32: ='EV EBITDA'!B20 -> 15.36501 | AF32: 1 | AG32: COST | AH32: ='EV EBITDA'!D9 -> 33.14072 | AI32: ='EV EBITDA'!C9 -> 26.53158 | AJ32: ='EV EBITDA'!B9 -> 19.514307
A33: 3 | B33: ASML | C33: ='EV EBITDA'!D6 -> 25.803253 | D33: ='EV EBITDA'!C6 -> 29.042534 | E33: ='EV EBITDA'!B6 -> 29.272089 | H33: 3 | I33: TSLA | J33: ='EV EBITDA'!D22 -> 88.131182 | K33: ='EV EBITDA'!C22 -> 58.027082 | L33: ='EV EBITDA'!B22 -> 23.64759 | P33: 2 | Q33: META | R33: ='EV EBITDA'!D15 -> 17.606448 | S33: ='EV EBITDA'!C15 -> 15.557256 | T33: ='EV EBITDA'!B15 -> 8.8760118 | X33: 3 | Y33: GILD | Z33: ='EV EBITDA'!D10 -> 29.06063 | AA33: ='EV EBITDA'!C10 -> 10.824205 | AB33: ='EV EBITDA'!B10 -> 13.190223 | AF33: 2 | AG33: PEP | AH33: ='EV EBITDA'!D19 -> 14.157422 | AI33: ='EV EBITDA'!C19 -> 15.987467 | AJ33: ='EV EBITDA'!B19 -> 17.391146
A34: 4 | B34: AMD | C34: ='EV EBITDA'!D3 -> 38.125993 | D34: ='EV EBITDA'!C3 -> 58.901816 | E34: ='EV EBITDA'!B3 -> 18.030659 | H34: 4 | I34: PDD | J34: ='EV EBITDA'!D18 -> 0.71163259 | K34: ='EV EBITDA'!C18 -> 2.2214207 | L34: ='EV EBITDA'!B18 -> 2.5523411 | P34: 3 | Q34: NFLX | R34: ='EV EBITDA'!D17 -> 15.173966 | S34: ='EV EBITDA'!C17 -> 10.520451 | T34: ='EV EBITDA'!B17 -> 6.9976203 | X34: 4 | Y34: VRTX | Z34: ='EV EBITDA'!D23 -> 207.75454 | AA34: ='EV EBITDA'!C23 -> 20.940274 | AB34: ='EV EBITDA'!B23 -> 14.703776 | AF34: 3 | AG34: MDLZ | AH34: ='EV EBITDA'!D13 -> 11.689253 | AI34: ='EV EBITDA'!C13 -> 14.516814 | AJ34: ='EV EBITDA'!B13 -> 22.245081
P35: 4 | Q35: TMUS | R35: ='EV EBITDA'!D21 -> 11.62717 | S35: ='EV EBITDA'!C21 -> 10.783198 | T35: ='EV EBITDA'!B21 -> 13.657868 | AF35: 4 | AG35: KDP | AH35: ='EV EBITDA'!D12 -> 16.846807 | AI35: ='EV EBITDA'!C12 -> 14.642947 | AJ35: ='EV EBITDA'!B12 -> 18.983368
H36: Выводы (мультипликаторы): | P36: 5 | Q36: CHTR | R36: ='EV EBITDA'!D8 -> 6.7805241 | S36: ='EV EBITDA'!C8 -> 7.5493908 | T36: ='EV EBITDA'!B8 -> 7.2997196 | X36: Выводы (мультипликаторы): | AF36: 5 | AG36: CCEP | AH36: ='EV EBITDA'!D7 -> 14.112191 | AI36: ='EV EBITDA'!C7 -> 12.271978 | AJ36: ='EV EBITDA'!B7 -> 11.43217
A37: Выводы (мультипликаторы):
A38: По мультипликаторам за 2022-2024 годы в выборку вошли Apple и ASML. Apple лидировала по P/E и EV/EBITDA в 2022-2023 годах, и даже с переходом на третьи места в 2024 году остается привлекательной по совокупности периода. ASML - самая стабильная в блоке, без резких колебаний удерживает вторые и третьи позиции по всем коэффициентам. Microsoft показала лучшие P/E и EV/EBITDA в 2024 году, но все три года проигрывает остальным по соотношению цены и выручки (P/S). AMD выбывает из-за критически высоких, худших в группе значений P/E и EV/EBITDA, несмотря на лидерство по оценке выручки (P/S). | P38: Выводы (мультипликаторы): | AF38: Выводы (мультипликаторы):
H40: По итогам анализа мультипликаторов лидерами по привлекательности рыночной оценки в данном блоке являются PDD Holdings (PDD) и Amazon (AMZN). PDD демонстрирует наименьшие значения P/E (1.28), P/S (0.36) и EV/EBITDA (0.71) в 2024 году - значительно ниже, чем у любого другого конкурента в отрасли; PEG (1.48) указывает на разумную оценку с учётом темпов роста. Столь низкие мультипликаторы при сильных фундаментальных показателях отчасти объясняются специфическим дисконтом за геополитический и регуляторный риск, характерным для китайских компаний на NASDAQ, однако не отражают слабости бизнеса. Amazon занимает второе место по совокупности мультипликаторов (P/E=39.67, P/S=3.69, EV/EBITDA=19.42 в 2024 году), что является адекватной оценкой для крупнейшего e-commerce-оператора с быстрорастущим облачным сегментом (AWS). MercadoLibre торгуется с заметной премией к Amazon (P/E=45.12, EV/EBITDA=28.13), что оправдывается высокими темпами роста, однако ограничивает запас прочности оценки. Tesla имеет наиболее высокие мультипликаторы в отрасли (P/E=197.96, P/S=13.29, EV/EBITDA=88.13) - оценка существенно расходится с текущим уровнем рентабельности и делает акцию крайне чувствительной к разочаровывающим операционным результатам. | P40: По итогам анализа мультипликаторов формальными лидерами по дешевизне оценки в данном блоке являются Charter Communications (CHTR) и T-Mobile (TMUS). CHTR демонстрирует наименьший P/E (9.80) и EV/EBITDA (6.78) в 2024 году, TMUS показывает низкий P/S (3.10) и умеренный P/E (22.27). Однако низкая оценка требует контекста: в случае CHTR она обусловлена критически высокой долговой нагрузкой и слабой операционной эффективностью, в случае TMUS - зрелостью телеком-бизнеса с ограниченным потенциалом роста. Alphabet/Google и Meta торгуются с более высокими мультипликаторами, что отражает справедливую премию за доминирующие позиции в digital-рекламе и стабильно высокую рентабельность. Netflix имеет наиболее высокий P/E (44.95) и P/S (10.04) в отрасли, что делает акцию наиболее чувствительной к негативным изменениям в результатах компании. | X40: По итогам анализа мультипликаторов в группе компаний сектора здравоохранения, биотехнологий и медицинских технологий наиболее привлекательную рыночную оценку демонстрируют Regeneron Pharmaceuticals (REGN) и Amgen (AMGN). REGN показывает наиболее разумные мультипликаторы в отрасли: P/E = 18,43, EV/EBITDA = 15,33 и P/S = 5,73 в 2024 году при PEG = 11 747, что объясняется временным замедлением темпов роста прибыли. Уровень P/E у REGN является наиболее низким среди компаний с положительной рентабельностью в группе и подтверждает сдержанную рыночную оценку с учетом сильных фундаментальных показателей. AMGN также торгуется с умеренными мультипликаторами: P/E = 32,91, а EV/EBITDA = 13,68 является наименьшим значение EV/EBITDA в группе за 2024 год, что указывает на наиболее привлекательную оценку по операционному денежному потоку. Показатель PEG у AMGN является отрицательным, что связано со снижением прибыли в отчетном периоде на фоне интеграционных расходов. GILD не был выбран из-за его чересчур высокого показателя P/E (235x) в 2024 году, вызванного разовым сжатием чистой прибыли (также у него высокий EV/EBITDA). VRTX также не был учтен из-за его отрицательных показателей рентабельности, что делает P/E нерасчетным, а EV/EBITDA достигает критических выоских значений (207,75x). | AF40: По итогам анализа мультипликаторов в группе компаний сектора потребительских товаров повседневного спроса были отобраны Mondelez International, Inc. (MDLZ) и Coca-Cola Europacific Partners (CCEP). Mondelez демонстрирует одни из наиболее низких значений P/E (16.78) и EV/EBITDA (11.69) в группе по итогам 2024 года. Показатель EV/EBITDA снизился с 22.25 в 2022 году до 11.69 в 2024 году при сохранении стабильных операционных результатов, что указывает на возможную недооцененность акций компании. Coca-Cola Europacific Partners выделяется достаточно низким значением P/S (1.67) и конкурентным уровнем EV/EBITDA (14.11) в 2024 году. В секторе с относительно устойчивым уровнем рентабельности низкий P/S при устойчивой выручке свидетельствует о сдержанной рыночной оценке компании. Последовательное улучшение мультипликаторов на протяжении всего анализируемого периода отражает рост доверия рынка к бизнес-модели компании. Costco исключается из-за переоценённости (P/E = 55, EV/EBITDA = 33), PepsiCo не выбираем из-за отсутствия лидирующих позиций по мультипликаторам, а KDP из-за высокой оценки при низкой рентабельности.
H41: PDD | P41: CHTR | X41: REGN | AF41: CCEP
H42: AMZN | P42: TMUS | X42: AMGN | AF42: MDLZ
A45: AAPL
A46: ASML

Sheet Показатели фин устойчивости
A2: Отрасль 1. Технологии и полупроводники. | H2: Отрасль 2. Потребительский discretionary, e-commerce и онлайн-сервисы. | P2: Отрасль 3. Коммуникационные сервисы, digital-реклама и подписки. | X2: Отрасль 4. Здравоохранение, биотехнологии и медицинские технологии. | AF2: Отрасль 5. Потребительские товары повседневного спроса.
A5: 1 | B5: ND/EBITDA | H5: 1 | I5: ND/EBITDA | P5: 1 | Q5: ND/EBITDA | X5: 1 | Y5: ND/EBITDA | AF5: 1 | AG5: ND/EBITDA
B6: Тикер | C6: 2024 | D6: 2023 | E6: 2022 | I6: Тикер | J6: 2024 | K6: 2023 | L6: 2022 | Q6: Тикер | R6: 2024 | S6: 2023 | T6: 2022 | Y6: Тикер | Z6: 2024 | AA6: 2023 | AB6: 2022 | AG6: Тикер | AH6: 2024 | AI6: 2023 | AJ6: 2022
A7: 1 | B7: AAPL | C7: ='Net Debt EBITDA'!D2 -> 0.56947446 | D7: ='Net Debt EBITDA'!C2 -> 0.64475441 | E7: ='Net Debt EBITDA'!B2 -> 0.83371508 | H7: 1 | I7: AMZN | J7: ='Net Debt EBITDA'!D5 -> 0.42095869 | K7: ='Net Debt EBITDA'!C5 -> 0.69600233 | L7: ='Net Debt EBITDA'!B5 -> 2.2483834 | P7: 1 | Q7: GOOGL | R7: ='Net Debt EBITDA'!D11 -> -0.0065881797 | S7: ='Net Debt EBITDA'!C11 -> 0.031366425 | T7: ='Net Debt EBITDA'!B11 -> 0.091592297 | X7: 1 | Y7: AMGN | Z7: ='Net Debt EBITDA'!D4 -> 3.6033243 | AA7: ='Net Debt EBITDA'!C4 -> 3.6260388 | AB7: ='Net Debt EBITDA'!B4 -> 2.5734243 | AF7: 1 | AG7: COST | AH7: ='Net Debt EBITDA'!D9 -> -0.14301004 | AI7: ='Net Debt EBITDA'!C9 -> -0.44908616 | AJ7: ='Net Debt EBITDA'!B9 -> -0.11759952
A8: 2 | B8: MSFT | C8: ='Net Debt EBITDA'!D16 -> 0.36698269 | D8: ='Net Debt EBITDA'!C16 -> 0.2402606 | E8: ='Net Debt EBITDA'!B16 -> 0.4722613 | H8: 2 | I8: MELI | J8: ='Net Debt EBITDA'!D14 -> 1.3114499 | K8: ='Net Debt EBITDA'!C14 -> 1.2336739 | L8: ='Net Debt EBITDA'!B14 -> 2.6585736 | P8: 2 | Q8: META | R8: ='Net Debt EBITDA'!D15 -> 0.059521617 | S8: ='Net Debt EBITDA'!C15 -> -0.078371605 | T8: ='Net Debt EBITDA'!B15 -> 0.31599894 | X8: 2 | Y8: REGN | Z8: ='Net Debt EBITDA'!D20 -> 0.040654381 | AA8: ='Net Debt EBITDA'!C20 -> -0.0057741887 | AB8: ='Net Debt EBITDA'!B20 -> -0.076906989 | AF8: 2 | AG8: PEP | AH8: ='Net Debt EBITDA'!D19 -> 2.1848321 | AI8: ='Net Debt EBITDA'!C19 -> 2.2184842 | AJ8: ='Net Debt EBITDA'!B19 -> 2.3184133
A9: 3 | B9: ASML | C9: ='Net Debt EBITDA'!D6 -> -0.79500375 | D9: ='Net Debt EBITDA'!C6 -> -0.23788091 | E9: ='Net Debt EBITDA'!B6 -> -0.42361806 | H9: 3 | I9: TSLA | J9: ='Net Debt EBITDA'!D22 -> -0.17106337 | K9: ='Net Debt EBITDA'!C22 -> -0.46127332 | L9: ='Net Debt EBITDA'!B22 -> -0.59494818 | P9: 3 | Q9: NFLX | R9: ='Net Debt EBITDA'!D17 -> 0.29557758 | S9: ='Net Debt EBITDA'!C17 -> 0.34527684 | T9: ='Net Debt EBITDA'!B17 -> 0.4527576 | X9: 3 | Y9: GILD | Z9: ='Net Debt EBITDA'!D10 -> 3.7708615 | AA9: ='Net Debt EBITDA'!C10 -> 1.8008765 | AB9: ='Net Debt EBITDA'!B10 -> 2.2388161 | AF9: 3 | AG9: MDLZ | AH9: ='Net Debt EBITDA'!D13 -> 2.1089084 | AI9: ='Net Debt EBITDA'!C13 -> 2.3721387 | AJ9: ='Net Debt EBITDA'!B13 -> 4.5190006
A10: 4 | B10: AMD | C10: ='Net Debt EBITDA'!D3 -> -0.30612245 | D10: ='Net Debt EBITDA'!C3 -> -0.22957295 | E10: ='Net Debt EBITDA'!B3 -> -0.35634261 | H10: 4 | I10: PDD | J10: ='Net Debt EBITDA'!D18 -> -0.34850123 | K10: ='Net Debt EBITDA'!C18 -> -0.67235222 | L10: ='Net Debt EBITDA'!B18 -> -0.443605 | P10: 4 | Q10: TMUS | R10: ='Net Debt EBITDA'!D21 -> 3.496392 | S10: ='Net Debt EBITDA'!C21 -> 3.9758029 | T10: ='Net Debt EBITDA'!B21 -> 5.3214126 | X10: 4 | Y10: VRTX | Z10: ='Net Debt EBITDA'!D23 -> -5.8097882 | AA10: ='Net Debt EBITDA'!C23 -> -2.0760662 | AB10: ='Net Debt EBITDA'!B23 -> -2.1653252 | AF10: 4 | AG10: KDP | AH10: ='Net Debt EBITDA'!D12 -> 4.4482555 | AI10: ='Net Debt EBITDA'!C12 -> 3.6639819 | AJ10: ='Net Debt EBITDA'!B12 -> 4.1807113
P11: 5 | Q11: CHTR | R11: ='Net Debt EBITDA'!D8 -> 4.4526257 | S11: ='Net Debt EBITDA'!C8 -> 4.7011766 | T11: ='Net Debt EBITDA'!B8 -> 4.6344821 | AF11: 5 | AG11: CCEP | AH11: ='Net Debt EBITDA'!D7 -> 3.1398264 | AI11: ='Net Debt EBITDA'!C7 -> 3.1602787 | AJ11: ='Net Debt EBITDA'!B7 -> 3.5843271
A13: 2 | B13: Current Ratio | H13: 2 | I13: Current Ratio | X13: 2 | Y13: Current Ratio
B14: Тикер | C14: 2024 | D14: 2023 | E14: 2022 | I14: Тикер | J14: 2024 | K14: 2023 | L14: 2022 | P14: 2 | Q14: Current Ratio | Y14: Тикер | Z14: 2024 | AA14: 2023 | AB14: 2022 | AF14: 2 | AG14: Current Ratio
A15: 1 | B15: AAPL | C15: ='Current Ratio'!D2 -> 0.86731258 | D15: ='Current Ratio'!C2 -> 0.98801167 | E15: ='Current Ratio'!B2 -> 0.87935603 | H15: 1 | I15: AMZN | J15: ='Current Ratio'!D5 -> 1.0637348 | K15: ='Current Ratio'!C5 -> 1.0450772 | L15: ='Current Ratio'!B5 -> 0.94464358 | Q15: Тикер | R15: 2024 | S15: 2023 | T15: 2022 | X15: 1 | Y15: AMGN | Z15: ='Current Ratio'!D4 -> 1.2567644 | AA15: ='Current Ratio'!C4 -> 1.6491953 | AB15: ='Current Ratio'!B4 -> 1.4142921 | AG15: Тикер | AH15: 2024 | AI15: 2023 | AJ15: 2022
A16: 2 | B16: MSFT | C16: ='Current Ratio'!D16 -> 1.2749549 | D16: ='Current Ratio'!C16 -> 1.7691673 | E16: ='Current Ratio'!B16 -> 1.784607 | H16: 2 | I16: MELI | J16: ='Current Ratio'!D14 -> 1.2131542 | K16: ='Current Ratio'!C14 -> 1.2660925 | L16: ='Current Ratio'!B14 -> 1.2792572 | P16: 1 | Q16: GOOGL | R16: ='Current Ratio'!D11 -> 1.8369314 | S16: ='Current Ratio'!C11 -> 2.0965849 | T16: ='Current Ratio'!B11 -> 2.3779942 | X16: 2 | Y16: REGN | Z16: ='Current Ratio'!D20 -> 4.7311056 | AA16: ='Current Ratio'!C20 -> 5.6900158 | AB16: ='Current Ratio'!B20 -> 5.0565371 | AF16: 1 | AG16: COST | AH16: ='Current Ratio'!D9 -> 0.96565531 | AI16: ='Current Ratio'!C9 -> 1.0683679 | AJ16: ='Current Ratio'!B9 -> 1.0218139
A17: 3 | B17: ASML | C17: ='Current Ratio'!D6 -> 1.5329304 | D17: ='Current Ratio'!C6 -> 1.4988848 | E17: ='Current Ratio'!B6 -> 1.2825519 | H17: 3 | I17: TSLA | J17: ='Current Ratio'!D22 -> 2.0249124 | K17: ='Current Ratio'!C22 -> 1.725894 | L17: ='Current Ratio'!B22 -> 1.5319555 | P17: 2 | Q17: META | R17: ='Current Ratio'!D15 -> 2.9778843 | S17: ='Current Ratio'!C15 -> 2.670995 | T17: ='Current Ratio'!B15 -> 2.2033967 | X17: 3 | Y17: GILD | Z17: ='Current Ratio'!D10 -> 1.5972176 | AA17: ='Current Ratio'!C10 -> 1.4259752 | AB17: ='Current Ratio'!B10 -> 1.2851931 | AF17: 2 | AG17: PEP | AH17: ='Current Ratio'!D19 -> 0.81893709 | AI17: ='Current Ratio'!C19 -> 0.85158151 | AJ17: ='Current Ratio'!B19 -> 0.80414411
A18: 4 | B18: AMD | C18: ='Current Ratio'!D3 -> 2.6162615 | D18: ='Current Ratio'!C3 -> 2.5068022 | E18: ='Current Ratio'!B3 -> 2.358141 | H18: 4 | I18: PDD | J18: ='Current Ratio'!D18 -> 2.2059332 | K18: ='Current Ratio'!C18 -> 1.9277223 | L18: ='Current Ratio'!B18 -> 1.8531854 | P18: 3 | Q18: NFLX | R18: ='Current Ratio'!D17 -> 1.2180281 | S18: ='Current Ratio'!C17 -> 1.1193454 | T18: ='Current Ratio'!B17 -> 1.1683903 | X18: 4 | Y18: VRTX | Z18: ='Current Ratio'!D23 -> 2.6921394 | AA18: ='Current Ratio'!C23 -> 3.9872019 | AB18: ='Current Ratio'!B23 -> 4.8265198 | AF18: 3 | AG18: MDLZ | AH18: ='Current Ratio'!D13 -> 0.6773748 | AI18: ='Current Ratio'!C13 -> 0.61552622 | AJ18: ='Current Ratio'!B13 -> 0.60313191
P19: 4 | Q19: TMUS | R19: ='Current Ratio'!D21 -> 0.91226331 | S19: ='Current Ratio'!C21 -> 0.90859136 | T19: ='Current Ratio'!B21 -> 0.77063293 | AF19: 4 | AG19: KDP | AH19: ='Current Ratio'!D12 -> 0.49425003 | AI19: ='Current Ratio'!C12 -> 0.37853297 | AJ19: ='Current Ratio'!B12 -> 0.47102526
P20: 5 | Q20: CHTR | R20: ='Current Ratio'!D8 -> 0.31388106 | S20: ='Current Ratio'!C8 -> 0.31269865 | T20: ='Current Ratio'!B8 -> 0.33294654 | AF20: 5 | AG20: CCEP | AH20: ='Current Ratio'!D7 -> 0.81457848 | AI20: ='Current Ratio'!C7 -> 0.90752954 | AJ20: ='Current Ratio'!B7 -> 0.89470805
A21: 3 | B21: Quick Ratio | H21: 3 | I21: Quick Ratio | X21: 3 | Y21: Quick Ratio
B22: Тикер | C22: 2024 | D22: 2023 | E22: 2022 | I22: Тикер | J22: 2024 | K22: 2023 | L22: 2022 | Y22: Тикер | Z22: 2024 | AA22: 2023 | AB22: 2022
A23: 1 | B23: AAPL | C23: ='Quick Ratio'!D2 -> 0.82600685 | D23: ='Quick Ratio'!C2 -> 0.94444215 | E23: ='Quick Ratio'!B2 -> 0.84723539 | H23: 1 | I23: AMZN | J23: ='Quick Ratio'!D5 -> 0.87305427 | K23: ='Quick Ratio'!C5 -> 0.84304832 | L23: ='Quick Ratio'!B5 -> 0.72323721 | P23: 3 | Q23: Quick Ratio | X23: 1 | Y23: AMGN | Z23: ='Quick Ratio'!D4 -> 0.95380752 | AA23: ='Quick Ratio'!C4 -> 1.1316877 | AB23: ='Quick Ratio'!B4 -> 1.1000191 | AF23: 3 | AG23: Quick Ratio
A24: 2 | B24: MSFT | C24: ='Quick Ratio'!D16 -> 1.2650097 | D24: ='Quick Ratio'!C16 -> 1.7451632 | E24: ='Quick Ratio'!B16 -> 1.7452515 | H24: 2 | I24: MELI | J24: ='Quick Ratio'!D14 -> 1.1953261 | K24: ='Quick Ratio'!C14 -> 1.2449614 | L24: ='Quick Ratio'!B14 -> 1.2615043 | Q24: Тикер | R24: 2024 | S24: 2023 | T24: 2022 | X24: 2 | Y24: REGN | Z24: ='Quick Ratio'!D20 -> 3.9483812 | AA24: ='Quick Ratio'!C20 -> 4.936233 | AB24: ='Quick Ratio'!B20 -> 4.2919174 | AG24: Тикер | AH24: 2024 | AI24: 2023 | AJ24: 2022
A25: 3 | B25: ASML | C25: ='Quick Ratio'!D6 -> 0.98975134 | D25: ='Quick Ratio'!C6 -> 0.95505293 | E25: ='Quick Ratio'!B6 -> 0.88220379 | H25: 3 | I25: TSLA | J25: ='Quick Ratio'!D22 -> 1.6079595 | K25: ='Quick Ratio'!C22 -> 1.2519132 | L25: ='Quick Ratio'!B22 -> 1.0512561 | P25: 1 | Q25: GOOGL | R25: ='Quick Ratio'!D11 -> 1.8069725 | S25: ='Quick Ratio'!C11 -> 2.0639499 | T25: ='Quick Ratio'!B11 -> 2.3394661 | X25: 3 | Y25: GILD | Z25: ='Quick Ratio'!D10 -> 1.4547651 | AA25: ='Quick Ratio'!C10 -> 1.2675532 | AB25: ='Quick Ratio'!B10 -> 1.1510945 | AF25: 1 | AG25: COST | AH25: ='Quick Ratio'!D9 -> 0.4398545 | AI25: ='Quick Ratio'!C9 -> 0.57255159 | AJ25: ='Quick Ratio'!B9 -> 0.46218514
A26: 4 | B26: AMD | C26: ='Quick Ratio'!D3 -> 1.8287323 | D26: ='Quick Ratio'!C3 -> 1.8563313 | E26: ='Quick Ratio'!B3 -> 1.7660543 | H26: 4 | I26: PDD | J26: ='Quick Ratio'!D18 -> 2.2059332 | K26: ='Quick Ratio'!C18 -> 1.9277223 | L26: ='Quick Ratio'!B18 -> 1.8531854 | P26: 2 | Q26: META | R26: ='Quick Ratio'!D15 -> 2.9778843 | S26: ='Quick Ratio'!C15 -> 2.670995 | T26: ='Quick Ratio'!B15 -> 2.2033967 | X26: 4 | Y26: VRTX | Z26: ='Quick Ratio'!D23 -> 2.3539808 | AA26: ='Quick Ratio'!C23 -> 3.7789367 | AB26: ='Quick Ratio'!B23 -> 4.6585464 | AF26: 2 | AG26: PEP | AH26: ='Quick Ratio'!D19 -> 0.65068493 | AI26: ='Quick Ratio'!C19 -> 0.68303473 | AJ26: ='Quick Ratio'!B19 -> 0.60918424
P27: 3 | Q27: NFLX | R27: ='Quick Ratio'!D17 -> 1.2180281 | S27: ='Quick Ratio'!C17 -> 1.1193454 | T27: ='Quick Ratio'!B17 -> 1.1683903 | AF27: 3 | AG27: MDLZ | AH27: ='Quick Ratio'!D13 -> 0.48161031 | AI27: ='Quick Ratio'!C13 -> 0.42539315 | AJ27: ='Quick Ratio'!B13 -> 0.40105194
P28: 4 | Q28: TMUS | R28: ='Quick Ratio'!D21 -> 0.83260632 | S28: ='Quick Ratio'!C21 -> 0.8284117 | T28: ='Quick Ratio'!B21 -> 0.69448711 | AF28: 4 | AG28: KDP | AH28: ='Quick Ratio'!D12 -> 0.33362186 | AI28: ='Quick Ratio'!C12 -> 0.25044863 | AJ28: ='Quick Ratio'!B12 -> 0.30832095
A29: 4 | B29: Cash Ratio | H29: 4 | I29: Cash Ratio | P29: 5 | Q29: CHTR | R29: ='Quick Ratio'!D8 -> 0.31388106 | S29: ='Quick Ratio'!C8 -> 0.31269865 | T29: ='Quick Ratio'!B8 -> 0.33294654 | X29: 4 | Y29: Cash Ratio | AF29: 5 | AG29: CCEP | AH29: ='Quick Ratio'!D7 -> 0.61725365 | AI29: ='Quick Ratio'!C7 -> 0.72121462 | AJ29: ='Quick Ratio'!B7 -> 0.70600301
B30: Тикер | C30: 2024 | D30: 2023 | E30: 2022 | I30: Тикер | J30: 2024 | K30: 2023 | L30: 2022 | Y30: Тикер | Z30: 2024 | AA30: 2023 | AB30: 2022
A31: 1 | B31: AAPL | C31: ='Cash Ratio'!D2 -> 0.1697526 | D31: ='Cash Ratio'!C2 -> 0.20621714 | E31: ='Cash Ratio'!B2 -> 0.1535634 | H31: 1 | I31: AMZN | J31: ='Cash Ratio'!D5 -> 0.43904899 | K31: ='Cash Ratio'!C5 -> 0.44499354 | L31: ='Cash Ratio'!B5 -> 0.34678525 | X31: 1 | Y31: AMGN | Z31: ='Cash Ratio'!D4 -> 0.51833413 | AA31: ='Cash Ratio'!C4 -> 0.59504132 | AB31: ='Cash Ratio'!B4 -> 0.48632626
A32: 2 | B32: MSFT | C32: ='Cash Ratio'!D16 -> 0.14618553 | D32: ='Cash Ratio'!C16 -> 0.33321491 | E32: ='Cash Ratio'!B16 -> 0.14651564 | H32: 2 | I32: MELI | J32: ='Cash Ratio'!D14 -> 0.15870626 | K32: ='Cash Ratio'!C14 -> 0.22693776 | L32: ='Cash Ratio'!B14 -> 0.22307872 | P32: 4 | Q32: Cash Ratio | X32: 2 | Y32: REGN | Z32: ='Cash Ratio'!D20 -> 0.63083437 | AA32: ='Cash Ratio'!C20 -> 0.79745282 | AB32: ='Cash Ratio'!B20 -> 0.98873078 | AF32: 4 | AG32: Cash Ratio
A33: 3 | B33: ASML | C33: ='Cash Ratio'!D6 -> 0.63516263 | D33: ='Cash Ratio'!C6 -> 0.43040425 | E33: ='Cash Ratio'!B6 -> 0.40416268 | H33: 3 | I33: TSLA | J33: ='Cash Ratio'!D22 -> 0.55997363 | K33: ='Cash Ratio'!C22 -> 0.5704049 | L33: ='Cash Ratio'!B22 -> 0.60852147 | Q33: Тикер | R33: 2024 | S33: 2023 | T33: 2022 | X33: 3 | Y33: GILD | Z33: ='Cash Ratio'!D10 -> 0.8323059 | AA33: ='Cash Ratio'!C10 -> 0.53945035 | AB33: ='Cash Ratio'!B10 -> 0.48158035 | AG33: Тикер | AH33: 2024 | AI33: 2023 | AJ33: 2022
A34: 4 | B34: AMD | C34: ='Cash Ratio'!D3 -> 0.52012086 | D34: ='Cash Ratio'!C3 -> 0.58798027 | E34: ='Cash Ratio'!B3 -> 0.75914586 | H34: 4 | I34: PDD | J34: ='Cash Ratio'!D18 -> 0.3065873 | K34: ='Cash Ratio'!C18 -> 0.39106682 | L34: ='Cash Ratio'!B18 -> 0.29366366 | P34: 1 | Q34: GOOGL | R34: ='Cash Ratio'!D11 -> 0.26330199 | S34: ='Cash Ratio'!C11 -> 0.29393502 | T34: ='Cash Ratio'!B11 -> 0.31571429 | X34: 4 | Y34: VRTX | Z34: ='Cash Ratio'!D23 -> 1.2819391 | AA34: ='Cash Ratio'!C23 -> 2.923014 | AB34: ='Cash Ratio'!B23 -> 3.8306408 | AF34: 1 | AG34: COST | AH34: ='Cash Ratio'!D9 -> 0.27932551 | AI34: ='Cash Ratio'!C9 -> 0.4079445 | AJ34: ='Cash Ratio'!B9 -> 0.31886368
P35: 2 | Q35: META | R35: ='Cash Ratio'!D15 -> 1.3063758 | S35: ='Cash Ratio'!C15 -> 1.3098248 | T35: ='Cash Ratio'!B15 -> 0.54321764 | AF35: 2 | AG35: PEP | AH35: ='Cash Ratio'!D19 -> 0.26969178 | AI35: ='Cash Ratio'!C19 -> 0.30685373 | AJ35: ='Cash Ratio'!B19 -> 0.18495427
A36: Вывод | P36: 3 | Q36: NFLX | R36: ='Cash Ratio'!D17 -> 0.72565716 | S36: ='Cash Ratio'!C17 -> 0.80320394 | T36: ='Cash Ratio'!B17 -> 0.64899671 | AF36: 3 | AG36: MDLZ | AH36: ='Cash Ratio'!D13 -> 0.069108394 | AI36: ='Cash Ratio'!C13 -> 0.095198022 | AJ36: ='Cash Ratio'!B13 -> 0.11493635
P37: 4 | Q37: TMUS | R37: ='Cash Ratio'!D21 -> 0.26811738 | S37: ='Cash Ratio'!C21 -> 0.24536506 | T37: ='Cash Ratio'!B21 -> 0.18215989 | AF37: 4 | AG37: KDP | AH37: ='Cash Ratio'!D12 -> 0.063064177 | AI37: ='Cash Ratio'!C12 -> 0.029946164 | AJ37: ='Cash Ratio'!B12 -> 0.066245666
P38: 5 | Q38: CHTR | R38: ='Cash Ratio'!D8 -> 0.034035296 | S38: ='Cash Ratio'!C8 -> 0.053655214 | T38: ='Cash Ratio'!B8 -> 0.053460423 | AF38: 5 | AG38: CCEP | AH38: ='Cash Ratio'!D7 -> 0.19180268 | AI38: ='Cash Ratio'!C7 -> 0.19497115 | AJ38: ='Cash Ratio'!B7 -> 0.18966225
P40: Выводы: | X40: Выводы:
A41: По итогам анализа показателей финансовой устойчивости за 2022–2024 годы в данном блоке выбраны AMD и ASML. AMD демонстрирует отрицательный чистый долг (ND/EBITDA от -0.23 до -0.36) и лучшую ликвидность в группе (Current Ratio стабильно выше 2.36) на протяжении всего периода. ASML также показывает полное отсутствие долгового бремени (ND/EBITDA до -0.80) при уверенном росте показателей ликвидности (Current Ratio вырос с 1.28 до 1.53). Microsoft занимает среднюю позицию с умеренным долгом (ND/EBITDA не выше 0.47) и приемлемой ликвидностью, но уступает лидерам. Apple выбывает ввиду хронической нехватки ликвидности (Current и Quick Ratio стабильно ниже 1.0 все три года) и наибольшей в блоке долговой нагрузки (ND/EBITDA 0.57–0.83), что делает её аутсайдером по краткосрочной финансовой устойчивости. | H41: По итогам анализа показателей финансовой устойчивости в данном блоке выбраны PDD Holdings (PDD) и Tesla (TSLA). PDD демонстрирует отрицательный чистый долг (ND/EBITDA −0.35 в 2024 году) и лучшие показатели ликвидности в отрасли (Current Ratio 2.21, Quick Ratio 2.21), что свидетельствует о практически полном отсутствии долговой нагрузки и высоком краткосрочном запасе прочности. Tesla также имеет отрицательный чистый долг (ND/EBITDA −0.17 в 2024 году), причём этот показатель оставался отрицательным на протяжении всего трёхлетнего периода, а показатели ликвидности уверенно росли (Current Ratio вырос с 1.53 в 2022 до 2.02 в 2024 году, Cash Ratio устойчиво держится на уровне около 0.56–0.61). Amazon занимает промежуточную позицию: долговая нагрузка существенно снизилась с 2.25 в 2022 до 0.42 в 2024 году, однако Quick Ratio (0.87) остаётся ниже единицы, что ограничивает краткосрочную финансовую гибкость. MercadoLibre выбывает ввиду наибольшей в отрасли долговой нагрузки (ND/EBITDA 1.31 в 2024 году) и минимального Cash Ratio (0.16), что формирует относительно более высокие финансовые риски по сравнению с лидерами. | P41: По итогам анализа показателей финансовой устойчивости в данном блоке выбраны Alphabet/Google (GOOGL) и Meta (META). Alphabet демонстрирует практически нулевую долговую нагрузку (ND/EBITDA -0.01 в 2024 году) и высокую ликвидность (Current Ratio 1.84, Quick Ratio 1.81), что свидетельствует о полной финансовой независимости. Meta показывает исключительные показатели ликвидности в отрасли (Current Ratio 2.98, Cash Ratio 1.31) при минимальном долге (ND/EBITDA 0.06), что означает наличие значительного запаса денежных средств. Netflix занимает среднюю позицию с умеренной долговой нагрузкой и приемлемой ликвидностью выше 1.0, однако не является лидером ни по одному показателю блока. T-Mobile и Charter выбывают ввиду критически высокой закредитованности (ND/EBITDA 3.50 и 4.45 соответственно) и показателей ликвидности ниже нормы, что создаёт существенные финансовые риски. | X41: По итогам анализа показателей финансовой устойчивости за 2022 - 2024 годы в данном блоке выбраны Regeneron Pharmaceuticals (REGN) и Vertex Pharmaceuticals (VRTX). REGN демонстрирует отличную финансовую устойчивость: показатель ND/EBITDA равен практически нулю (0,04 в 2024 году, против -0,08 в 2022 году), компания фактически не имеет чистого долга. При этом ликвидность находится на лидирующем в группе уровне: Current Ratio = 4,73, Quick Ratio = 3,95, Cash Ratio = 0,63 в 2024 году являются самыми высокими значениями в отрасли, свидетельствующие о значительном запасе краткосрочной финансовой прочности. VRTX обладает наилучшим показателем ND/EBITDA в группе (-5,81 в 2024 году), компания является нетто-кредитором и располагает значительной денежной позицией, что обеспечивает абсолютную независимость от долгового финансирования. Показатели ликвидности VRTX также уверенно превышают норму (Current Ratio = 2,69, Cash Ratio = 1,28). AMGN и GILD выбывают по данному блоку ввиду высокой долговой нагрузки: ND/EBITDA AMGN составляет 3,60, у GILD 3,77 в 2024 году, что значительно превышает комфортный уровень для фармацевтического сектора и создает существенные риски при изменении процентных ставок или ухудшении операционных результатов. | AF41: По итогам анализа показателей финансовой устойчивости были отобраны Costco (COST) и PepsiCo (PEP). Costco имеет отрицательный ND/EBITDA (−0,14 в 2024 году), то есть денежные средства на балансе превышают долг, что говорит о высокой финансовой устойчивости. Компания также лидирует по Current Ratio (0,97) и Cash Ratio (0,28). Бизнес-модель Costco предполагает быструю оборачиваемость товаров и отсрочку платежей поставщикам, что создаёт отрицательный рабочий капитал при стабильном денежном потоке. PepsiCo демонстрирует умеренную и снижающуюся долговую нагрузку (ND/EBITDA снизился с 2,32 в 2022 году до 2,18 в 2024 году). Показатели Quick Ratio (0,65) и Cash Ratio (0,27) являются вторыми в группе, что подтверждает достаточную ликвидность для компании такого масштаба. KDP исключается из-за наихудших показателей (самый высокий долг ND/EBITDA = 4,45 и самая низкая ликвидность Current Ratio = 0,49, Quick Ratio = 0,33), что создаёт наибольший финансовый риск. Mondelez, несмотря на заметное снижение долга с 4,52 до 2,11, имеет минимальный Cash Ratio (0,07) в группе, что ограничивает финансовую гибкость компании.
A42: AMD | H42: PDD | P42: GOOGL | X42: REGN | AF42: COST
A43: ASML | H43: TSLA | P43: META | X43: VRTX | AF43: PEP

Sheet Агрегированный Итог
A3: Отрасль 1. Технологии и полупроводники. | F3: Отрасль 2. Потребительский discretionary, e-commerce и онлайн-сервисы. | O3: Отрасль 3. Коммуникационные сервисы, digital-реклама и подписки. | W3: Отрасль 4. Здравоохранение, биотехнологии и медицинские технологии. | AF3: Отрасль 5. Потребительские товары повседневного спроса.
A5: Рентабельность | F5: Рентабельность | O5: Рентабельность | W5: Рентабельность | AF5: Рентабельность
A6: AAPL | F6: PDD | O6: Лидеры - Alphabet/Google (GOOGL) и Meta (META) | W6: REGN | AF6: Лидеры - Costco Wholesale Corporation (COST) и Pepsico, Inc. (PEP)
A7: ASML | F7: MELI | W7: AMGN
A11: Мультипликаторы | F11: Мультипликаторы | O11: Мультипликаторы | W11: Мультипликаторы | AF11: Мультипликаторы
A12: AAPL | F12: PDD | O12: Лидеры по дешевизне оценки - Charter Communications (CHTR) и T-Mobile (TMUS) | W12: REGN | AF12: Лидеры - Coca-Cola Europacific Partners (CCEP) и Mondelez International, Inc. (MDLZ)
A13: ASML | F13: AMZN | W13: AMGN
F15: Показатели фин устойчивости | O15: Показатели фин устойчивости | W15: Показатели фин устойчивости | AF15: Показатели фин устойчивости
A16: Показатели фин устойчивости | F16: PDD | O16: лидеры - Alphabet/Google (GOOGL) и Meta (META) | W16: REGN | AF16: Лидеры - Costco Wholesale Corporation (COST) и Pepsico, Inc. (PEP)
A17: AMD | F17: TSLA | W17: VRTX
A18: ASML
A19: Итоговая рекомендация: | F19: Итоговая рекомендация: | O19: Итоговая рекомендация: | W19: Итоговая рекомендация: | AF19: Итоговая рекомендация:
A20: По результатам сравнительного анализа всех трёх блоков показателей в финальную выборку от отрасли "Технологии и полупроводники" проходят Apple (AAPL) и ASML Holding (ASML). Обе компании являются лидерами по рентабельности и привлекательности рыночной оценки, а низкая краткосрочная ликвидность Apple оправдана фундаментально сильным бизнесом и исключительной эффективностью использования капитала. Microsoft и AMD, несмотря на сильные показатели финансовой устойчивости, не прошли отбор ввиду отставания по отдаче на капитал у первой и критически низкой операционной эффективности при сильной переоценке рынком у второй. | F20: По результатам сравнительного анализа всех трёх блоков показателей в финальную выборку от отрасли «Потребительский discretionary, e-commerce и онлайн-сервисы» проходят PDD Holdings (PDD) и Amazon (AMZN). PDD является безусловным лидером отрасли по совокупности критериев: компания занимает первые позиции по рентабельности, обладает наиболее привлекательной рыночной оценкой и демонстрирует лучшие показатели финансовой устойчивости, неизменно занимая лидирующие позиции во всех трёх блоках анализа. Amazon проходит отбор как компания с наиболее сбалансированным профилем среди оставшихся претендентов: восстанавливающаяся и растущая рентабельность, умеренная рыночная оценка и управляемая долговая нагрузка. MercadoLibre, несмотря на лидерство по ROE и сильную динамику роста, не проходит отбор ввиду более дорогой рыночной оценки и более высокой долговой нагрузки. Tesla выбывает из-за сочетания устойчивого снижения рентабельности по всем метрикам и критически завышенных мультипликаторов, которые несовместимы с реальными финансовыми результатами компании. | O20: По результатам сравнительного анализа всех трёх блоков показателей в финальную выборку от отрасли "Коммуникационные сервисы, digital-реклама и подписки" проходят Alphabet/Google (GOOGL) и Meta Platforms (META). Обе компании являются лидерами по рентабельности и финансовой устойчивости, а их более высокая рыночная оценка относительно CHTR и TMUS оправдана фундаментально сильным бизнесом и высокой рентабельностью. Charter Communications и T-Mobile, несмотря на формально низкие мультипликаторы, не прошли отбор ввиду слабой операционной эффективности и высокой долговой нагрузки. | W20: По результатам сравнительного анализа всех трех блоков показателей в финальную выборку от отрасли «Здравоохранение, биотехнологии и медицинские технологии» были выбраны Regeneron Pharmaceuticals (REGN) и Amgen (AMGN). Regeneron является безусловным лидером отрасли по совокупности критериев: компания демонстрирует наиболее высокую рентабельность продаж в группе (31,1%), наиболее привлекательную рыночную оценку по P/E среди компаний с положительной прибылью (18,43x) и абсолютную финансовую устойчивость с практически нулевым чистым долгом и наивысшей ликвидностью в отрасли. AMGN также был выбран как компания с наиболее сбалансированным профилем среди оставшихся претендентов: лидерство по ROE, наименьший EV/EBITDA в группе (13,68x) и достаточный уровень ликвидности, несмотря на повышенную долговую нагрузку, оправданную масштабом и устойчивостью денежных потоков компании. GILD не проходит отбор ввиду резкого ухудшения всех показателей рентабельности в 2024 году и слишком высоких мультипликаторов, а VRTX из-за сочетания отрицательной рентабельности по итогам 2024 года и сильно завышенного EV/EBITDA, несмотря на лидирующую финансовую устойчивость. | AF20: По результатам анализа трех блоков показателей в финальную выборку по отрасли «Потребительские товары повседневного спроса» проходят Costco (COST) и PepsiCo (PEP). Обе компании входят в число лидеров по двум из трёх направлений. Costco показывает лучшие результаты по рентабельности (ROIC 25,48%, ROA 10,61%) и финансовой устойчивости (отрицательный ND/EBITDA). PepsiCo имеет самый высокий ROE в группе (52,42%) и умеренную, снижающуюся долговую нагрузку. Mondelez и CCEP отличаются наиболее низкими мультипликаторами (P/E, EV/EBITDA, P/S), но их рентабельность заметно ниже, чем у Costco и PepsiCo, а показатели финансовой устойчивости находятся на среднем уровне. Таким образом, их низкая рыночная оценка соответствует более скромным финансовым результатам, а не недооцененности.
AF21: COST
AF22: PEP

Sheet PEG
A1: Ticker | B1: 2024
A2: AAPL | B2: ='P E'!D2/'Summary (up to 2024)'!F2 -> -16650.045
A3: AMD | B3: ='P E'!D3/'Summary (up to 2024)'!F3 -> 1326.0592
A4: AMGN | B4: ='P E'!D4/'Summary (up to 2024)'!F4 -> -156.8032 | E4: PEG = P E/EPS growth rate
A5: AMZN
A6: ASML | B6: ='P E'!D6/'Summary (up to 2024)'!F6 -> 377.4867
A7: CCEP | B7: ='P E'!D7/'Summary (up to 2024)'!F7 -> -741.05925
A8: CHTR | B8: ='P E'!D8/'Summary (up to 2024)'!F8 -> 147.20553
A9: COST | B9: ='P E'!D9/'Summary (up to 2024)'!F9 -> 447.63244
A10: GILD | B10: ='P E'!D10/'Summary (up to 2024)'!F10 -> -347.3687
A11: GOOGL | B11: ='P E'!D11/'Summary (up to 2024)'!F11 -> 71.487486
A12: KDP | B12: ='P E'!D12/'Summary (up to 2024)'!F12 -> 1488.3421
A13: MDLZ | B13: ='P E'!D13/'Summary (up to 2024)'!F13 -> 52.297749
A14: MELI | B14: ='P E'!D14/'Summary (up to 2024)'!F14 -> 45.632679
A15: META | B15: ='P E'!D15/'Summary (up to 2024)'!F15 -> 36.664131
A16: MSFT | B16: ='P E'!D16/'Summary (up to 2024)'!F16 -> 333.657
A17: NFLX | B17: ='P E'!D17/'Summary (up to 2024)'!F17 -> 109.17035
... A22: TSLA | B22: ='P E'!D22/'Summary (up to 2024)'!F22 -> -794.03559
A23: VRTX

Sheet Показатели рентабельностимаржин
A1: Отрасль Технологии и полупроводники
A3: ROE | B3: 2022 | C3: 2023 | D3: 2024
A4: AAPL | B4: =ROE!B2 -> 1.9695887 | C4: =ROE!C2 -> 1.7194951 | D4: =ROE!D2 -> 1.5741251
A5: MSFT | B5: =ROE!B16 -> 0.43675469 | C5: =ROE!C16 -> 0.38823924 | D5: =ROE!D16 -> 0.37133347
A6: AMD | B6: =ROE!B3 -> 0.024109589 | C6: =ROE!C3 -> 0.015437176 | D6: =ROE!D3 -> 0.028926494
A7: ASML | B7: =ROE!B6 -> 0.63833023 | C7: =ROE!C6 -> 0.70421143 | D7: =ROE!D6 -> 0.47427433
A8: Итог
A9: =A4 -> AAPL
A10: =A7 -> ASML
A12: ROA | B12: 2022 | C12: 2023 | D12: 2024
A13: AAPL | B13: =ROA!B2 -> 0.28292441 | C13: =ROA!C2 -> 0.27503126 | D13: =ROA!D2 -> 0.26126208
A14: MSFT | B14: =ROA!B16 -> 0.19936959 | C14: =ROA!C16 -> 0.18630152 | D14: =ROA!D16 -> 0.19074187
A15: AMD | B15: =ROA!B3 -> 0.019532406 | C15: =ROA!C3 -> 0.012608423 | D15: =ROA!D3 -> 0.02393681
A16: ASML | B16: =ROA!B6 -> 0.15493493 | C16: =ROA!C6 -> 0.20559181 | D16: =ROA!D6 -> 0.17101859
A17: Итог
A18: =A13 -> AAPL
A19: =A14 -> MSFT
A22: ROIC | B22: 2022 | C22: 2023 | D22: 2024
A23: AAPL | B23: =ROIC!B2 -> 0.5861678 | C23: =ROIC!C2 -> 0.56268883 | D23: =ROIC!D2 -> 0.5717837
A24: MSFT | B24: =ROIC!B16 -> 0.34453327 | C24: =ROIC!C16 -> 0.29178372 | D24: =ROIC!D16 -> 0.28283015
A25: AMD | B25: =ROIC!B3 -> 0.024521865 | C25: =ROIC!C3 -> 0.017452788 | D25: =ROIC!D3 -> 0.028375872
A26: ASML | B26: =ROIC!B6 -> 0.42366929 | C26: =ROIC!C6 -> 0.43000792 | D26: =ROIC!D6 -> 0.32352142
A27: Итог
A28: =A23 -> AAPL
A29: =A26 -> ASML
A31: Profit margin | B31: 2022 | C31: 2023 | D31: 2024
A32: AAPL | B32: ='Net Profit Margin'!B2 -> 0.25309641 | C32: ='Net Profit Margin'!C2 -> 0.25306234 | D32: ='Net Profit Margin'!D2 -> 0.23971256
A33: MSFT | B33: ='Net Profit Margin'!B16 -> 0.36686337 | C33: ='Net Profit Margin'!C16 -> 0.34146238 | D33: ='Net Profit Margin'!D16 -> 0.35955973
A34: AMD | B34: ='Net Profit Margin'!B3 -> 0.055929833 | C34: ='Net Profit Margin'!C3 -> 0.037654321 | D34: ='Net Profit Margin'!D3 -> 0.063641652
A35: ASML | B35: ='Net Profit Margin'!B6 -> 0.26562574 | C35: ='Net Profit Margin'!C6 -> 0.28444944 | D35: ='Net Profit Margin'!D6 -> 0.26789891
A36: Итог
A37: =A35 -> ASML
A38: =A33 -> MSFT

Sheet Raw Data
A1: Ticker | B1: Year | C1: Price | D1: Revenue | E1: Gross Profit | F1: Net Income | G1: EPS | H1: DPS | I1: Diluted Shares | J1: FCF | K1: Operating Cash Flow | L1: Capital Expenditure | M1: Common Dividends Paid | N1: Cash | O1: Current Assets | P1: Total Assets | Q1: Average Total Assets | R1: Current Liabilities | S1: Inventory | T1: Equity | U1: Average Equity | V1: Total Debt | W1: Invested Capital | X1: EBITDA | Y1: EBIT | Z1: Interest Expense | AA1: Pretax Income | AB1: Tax Provision | AC1: Tax Rate | AD1: Warnings | AE1: Gross Margin | AF1: Operating Margin | AG1: Net Profit Margin | AH1: ROE | AI1: ROA | AJ1: NOPAT | AK1: ROIC | AL1: Payout Ratio based on NI | AM1: Payout Ratio based on FCF | AN1: D/E | AO1: Interest Coverage | AP1: OCF / Total Debt | AQ1: Net Debt | AR1: Net Debt / EBITDA | AS1: Current Ratio | AT1: Quick Ratio | AU1: Cash Ratio | AV1: Market Cap | AW1: EV | AX1: P/E | AY1: P/S | AZ1: P/FCF | BA1: EV/EBITDA | BB1: Dividend Yield | BC1: P/B
A2: AAPL | B2: 2022 | C2: 127.76161 | D2: 394328000000 | E2: 170782000000 | F2: 99803000000 | G2: 6.11 | H2: 0.91 | I2: 16325819000 | J2: 111443000000 | K2: 122151000000 | L2: -10708000000 | M2: 14841000000 | N2: 23646000000 | O2: 135405000000 | P2: 352755000000 | Q2: 352755000000 | R2: 153982000000 | S2: 4946000000 | T2: 50672000000 | U2: 50672000000 | V2: 132480000000 | W2: 170741000000 | X2: 130541000000 | Y2: 119437000000 | Z2: 2931000000 | AA2: 119103000000 | AB2: 19300000000 | AC2: 0.16204462 | AE2: 0.43309631 | AF2: 0.30288744 | AG2: 0.25309641 | AH2: 1.9695887 | AI2: 0.28292441 | AJ2: 1.0008288e+11 | AK2: 0.5861678 | AL2: 0.14870294 | AM2: 0.13317122 | AN2: 2.6144616 | AO2: 40.749574 | AP2: 0.92203351 | AQ2: 108834000000 | AR2: 0.83371508 | AS2: 0.87935603 | AT2: 0.84723539 | AU2: 0.1535634 | AV2: 2.085813e+12 | AW2: 2.194647e+12 | AX2: 20.910247 | AY2: 5.289538 | AZ2: 18.716411 | BA2: 16.811936 | BB2: 0.0071226403 | BC2: 41.163028
A3: AAPL | B3: 2023 | C3: 190.37509 | D3: 383285000000 | E3: 169148000000 | F3: 96995000000 | G3: 6.13 | H3: 0.95 | I3: 15812547000 | J3: 99584000000 | K3: 110543000000 | L3: -10959000000 | M3: 15025000000 | N3: 29965000000 | O3: 143566000000 | P3: 352583000000 | Q3: 352669000000 | R3: 145308000000 | S3: 6331000000 | T3: 62146000000 | U3: 56409000000 | V3: 111088000000 | W3: 173234000000 | X3: 125820000000 | Y3: 114301000000 | Z3: 3933000000 | AA3: 113736000000 | AB3: 16741000000 | AC3: 0.14719174 | AE3: 0.4413113 | AF3: 0.29821412 | AG3: 0.25306234 | AH3: 1.7194951 | AI3: 0.27503126 | AJ3: 9.7476837e+10 | AK3: 0.56268883 | AL3: 0.15490489 | AM3: 0.15087765 | AN3: 1.7875326 | AO3: 29.062039 | AP3: 0.99509398 | AQ3: 81123000000 | AR3: 0.64475441 | AS3: 0.98801167 | AT3: 0.94444215 | AU3: 0.20621714 | AV3: 3.0103151e+12 | AW3: 3.0914381e+12 | AX3: 31.056296 | AY3: 7.8539862 | AZ3: 30.228903 | BA3: 24.570323 | BB3: 0.0049901486 | BC3: 48.439402
A4: AAPL | B4: 2024 | C4: 248.83022 | D4: 391035000000 | E4: 180683000000 | F4: 93736000000 | G4: 6.08 | H4: 0.99 | I4: 15408095000 | J4: 108807000000 | K4: 118254000000 | L4: -9447000000 | M4: 15234000000 | N4: 29943000000 | O4: 152987000000 | P4: 364980000000 | Q4: 358781500000 | R4: 176392000000 | S4: 7286000000 | T4: 56950000000 | U4: 59548000000 | V4: 106629000000 | W4: 163579000000 | X4: 134661000000 | Y4: 123216000000 | Z4: 3933000000 | AA4: 123485000000 | AB4: 29749000000 | AC4: 0.24091185 | AE4: 0.4620635 | AF4: 0.31510223 | AG4: 0.23971256 | AH4: 1.5741251 | AI4: 0.26126208 | AJ4: 9.3531805e+10 | AK4: 0.5717837 | AL4: 0.16252027 | AM4: 0.14000937 | AN4: 1.8723266 | AO4: 31.328757 | AP4: 1.1090229 | AQ4: 76686000000 | AR4: 0.56947446 | AS4: 0.86731258 | AT4: 0.82600685 | AU4: 0.1697526 | AV4: 3.8339996e+12 | AW4: 3.9106856e+12 | AX4: 40.926022 | AY4: 9.8047479 | AZ4: 35.2367 | BA4: 29.040967 | BB4: 0.0039786165 | BC4: 67.322205
A5: AAPL | B5: 2025 | C5: 271.35583 | D5: 416161000000 | E5: 195201000000 | F5: 112010000000 | G5: 7.46 | H5: 1.03 | I5: 15004697000 | J5: 98767000000 | K5: 111482000000 | L5: -12715000000 | M5: 15421000000 | N5: 35934000000 | O5: 147957000000 | P5: 359241000000 | Q5: 362110500000 | R5: 165631000000 | S5: 5718000000 | T5: 73733000000 | U5: 65341500000 | V5: 98657000000 | W5: 172390000000 | X5: 144748000000 | Y5: 133050000000 | Z5: 3933000000 | AA5: 132729000000 | AB5: 20719000000 | AC5: 0.15610002 | AE5: 0.46905164 | AF5: 0.319708 | AG5: 0.26915064 | AH5: 1.7142245 | AI5: 0.30932547 | AJ5: 1.1228089e+11 | AK5: 0.65131906 | AL5: 0.13767521 | AM5: 0.15613515 | AN5: 1.3380305 | AO5: 33.829138 | AP5: 1.1299958 | AQ5: 62723000000 | AR5: 0.4333255 | AS5: 0.89329292 | AT5: 0.8587704 | AU5: 0.21695214 | AV5: 4.0716121e+12 | AW5: 4.1343351e+12 | AX5: 36.374777 | AY5: 9.7837425 | AZ5: 41.224418 | BA5: 28.562295 | BB5: 0.003795754 | BC5: 55.221028
A6: AMD | B6: 2022 | C6: 64.769997 | D6: 23601000000 | E6: 10603000000 | F6: 1320000000 | G6: 0.84 | I6: 1571000000 | J6: 3115000000 | K6: 3565000000 | L6: -450000000 | N6: 4835000000 | O6: 15019000000 | P6: 67580000000 | Q6: 67580000000 | R6: 6369000000 | S6: 3771000000 | T6: 54750000000 | U6: 54750000000 | V6: 2863000000 | W6: 57217000000 | X6: 5534000000 | Y6: 1272000000 | Z6: 88000000 | AA6: 1184000000 | AB6: -122000000 | AC6: -0.10304054 | AE6: 0.44926062 | AF6: 0.053896021 | AG6: 0.055929833 | AH6: 0.024109589 | AI6: 0.019532406 | AJ6: 1.4030676e+09 | AK6: 0.024521865 | AN6: 0.052292237 | AO6: 14.454545 | AP6: 1.2451973 | AQ6: -1972000000 | AR6: -0.35634261 | AS6: 2.358141 | AT6: 1.7660543 | AU6: 0.75914586 | AV6: 1.0175366e+11 | AW6: 9.9781665e+10 | AX6: 77.107139 | AY6: 4.3114133 | AZ6: 32.665703 | BA6: 18.030659 | BC6: 1.8585144
A7: AMD | B7: 2023 | C7: 147.41 | D7: 22680000000 | E7: 10460000000 | F7: 854000000 | G7: 0.53 | I7: 1625000000 | J7: 1121000000 | K7: 1667000000 | L7: -546000000 | N7: 3933000000 | O7: 16768000000 | P7: 67885000000 | Q7: 67732500000 | R7: 6689000000 | S7: 4351000000 | T7: 55892000000 | U7: 55321000000 | V7: 3003000000 | W7: 58360000000 | X7: 4051000000 | Y7: 598000000 | Z7: 106000000 | AA7: 492000000 | AB7: -346000000 | AC7: -0.70325203 | AE7: 0.46119929 | AF7: 0.026366843 | AG7: 0.037654321 | AH7: 0.015437176 | AI7: 0.012608423 | AJ7: 1.0185447e+09 | AK7: 0.017452788 | AN7: 0.053728619 | AO7: 5.6415094 | AP7: 0.55511156 | AQ7: -930000000 | AR7: -0.22957294 | AS7: 2.5068022 | AT7: 1.8563313 | AU7: 0.58798027 | AV7: 2.3954126e+11 | AW7: 2.3861126e+11 | AX7: 278.13208 | AY7: 10.561784 | AZ7: 213.68533 | BA7: 58.901816 | BC7: 4.2857879
A8: AMD | B8: 2024 | C8: 120.79 | D8: 25785000000 | E8: 12725000000 | F8: 1641000000 | G8: 1 | I8: 1637000000 | J8: 2405000000 | K8: 3041000000 | L8: -636000000 | N8: 3787000000 | O8: 19049000000 | P8: 69226000000 | Q8: 68555500000 | R8: 7281000000 | S8: 5734000000 | T8: 57568000000 | U8: 56730000000 | V8: 2212000000 | W8: 59289000000 | X8: 5145000000 | Y8: 2081000000 | Z8: 92000000 | AA8: 1989000000 | AB8: 381000000 | AC8: 0.19155354 | AE8: 0.49350398 | AF8: 0.080705837 | AG8: 0.063641652 | AH8: 0.028926494 | AI8: 0.02393681 | AJ8: 1.6823771e+09 | AK8: 0.028375872 | AN8: 0.038424125 | AO8: 22.619565 | AP8: 1.374774 | AQ8: -1575000000 | AR8: -0.30612245 | AS8: 2.6162615 | AT8: 1.8287323 | AU8: 0.52012086 | AV8: 1.9773323e+11 | AW8: 1.9615823e+11 | AX8: 120.79 | AY8: 7.6685372 | AZ8: 82.21756 | BA8: 38.125993 | BC8: 3.4347768
A9: AMD | B9: 2025 | C9: 214.16 | D9: 34639000000 | E9: 17152000000 | F9: 4335000000 | G9: 2.65 | I9: 1636000000 | J9: 6735000000 | K9: 7709000000 | L9: -974000000 | N9: 5539000000 | O9: 26947000000 | P9: 76926000000 | Q9: 73076000000 | R9: 9455000000 | S9: 7920000000 | T9: 62999000000 | U9: 60283500000 | V9: 3847000000 | W9: 66221000000 | X9: 7275000000 | Y9: 4271000000 | Z9: 131000000 | AA9: 4140000000 | AB9: -103000000 | AC9: -0.024879227 | AE9: 0.49516441 | AF9: 0.12330033 | AG9: 0.12514795 | AH9: 0.071910224 | AI9: 0.059321802 | AJ9: 4.3772592e+09 | AK9: 0.066100771 | AN9: 0.061064461 | AO9: 32.603053 | AP9: 2.0038991 | AQ9: -1692000000 | AR9: -0.23257732 | AS9: 2.8500264 | AT9: 2.0123744 | AU9: 0.5858276 | AV9: 3.5036577e+11 | AW9: 3.4867377e+11 | AX9: 80.815096 | AY9: 10.114777 | AZ9: 52.021643 | BA9: 47.927665 | BC9: 5.5614496
A10: AMGN | B10: 2022 | C10: 235.21104 | D10: 26323000000 | E10: 19917000000 | F10: 6552000000 | G10: 12.11 | H10: 7.76 | I10: 541000000 | J10: 8785000000 | K10: 9721000000 | L10: -936000000 | M10: 4196000000 | N10: 7629000000 | O10: 22186000000 | P10: 65121000000 | Q10: 65121000000 | R10: 15687000000 | S10: 4930000000 | T10: 3661000000 | U10: 3661000000 | V10: 38945000000 | W10: 42606000000 | X10: 12169000000 | Y10: 8752000000 | Z10: 1406000000 | AA10: 7346000000 | AB10: 794000000 | AC10: 0.10808603 | AE10: 0.75663868 | AF10: 0.3324849 | AG10: 0.2489078 | AH10: 1.789675 | AI10: 0.10061271 | AJ10: 7.806031e+09 | AK10: 0.18321436 | AL10: 0.64041514 | AM10: 0.47763233 | AN10: 10.637804 | AO10: 6.2247511 | AP10: 0.24960842 | AQ10: 31316000000 | AR10: 2.5734243 | AS10: 1.4142921 | AT10: 1.1000191 | AU10: 0.48632626 | AV10: 1.2724917e+11 | AW10: 1.5856517e+11 | AX10: 19.422877 | AY10: 4.8341441 | AZ10: 14.484824 | BA10: 13.030255 | BB10: 0.032991648 | BC10: 34.758037
A11: AMGN | B11: 2023 | C11: 266.88065 | D11: 28190000000 | E11: 19739000000 | F11: 6717000000 | G11: 12.49 | H11: 8.52 | I11: 538000000 | J11: 7359000000 | K11: 8471000000 | L11: -1112000000 | M11: 4556000000 | N11: 10944000000 | O11: 30332000000 | P11: 97154000000 | Q11: 81137500000 | R11: 18392000000 | S11: 9518000000 | T11: 6232000000 | U11: 4946500000 | V11: 64613000000 | W11: 70845000000 | X11: 14801000000 | Y11: 10730000000 | Z11: 2875000000 | AA11: 7855000000 | AB11: 1138000000 | AC11: 0.14487588 | AE11: 0.70021284 | AF11: 0.38063143 | AG11: 0.23827598 | AH11: 1.3579298 | AI11: 0.082785395 | AJ11: 9.1754819e+09 | AK11: 0.12951488 | AL11: 0.67827899 | AM11: 0.61910586 | AN11: 10.36794 | AO11: 3.7321739 | AP11: 0.13110365 | AQ11: 53669000000 | AR11: 3.6260388 | AS11: 1.6491953 | AT11: 1.1316877 | AU11: 0.59504132 | AV11: 1.4358179e+11 | AW11: 1.9725079e+11 | AX11: 21.367546 | AY11: 5.0933589 | AZ11: 19.511046 | BA11: 13.326855 | BB11: 0.031924383 | BC11: 23.03944
A12: AMGN | B12: 2024 | C12: 248.80763 | D12: 33424000000 | E12: 20566000000 | F12: 4090000000 | G12: 7.56 | H12: 9 | I12: 541000000 | J12: 10394000000 | K12: 11490000000 | L12: -1096000000 | M12: 4832000000 | N12: 11973000000 | O12: 29030000000 | P12: 91839000000 | Q12: 94496500000 | R12: 23099000000 | S12: 6998000000 | T12: 5877000000 | U12: 6054500000 | V12: 60099000000 | W12: 65976000000 | X12: 13356000000 | Y12: 7764000000 | Z12: 3155000000 | AA12: 4609000000 | AB12: 519000000 | AC12: 0.11260577 | AE12: 0.61530637 | AF12: 0.23228818 | AG12: 0.12236716 | AH12: 0.6755306 | AI12: 0.043282026 | AJ12: 6.8897288e+09 | AK12: 0.1044278 | AL12: 1.1814181 | AM12: 0.46488359 | AN12: 10.226136 | AO12: 2.4608558 | AP12: 0.19118455 | AQ12: 48126000000 | AR12: 3.6033243 | AS12: 1.2567644 | AT12: 0.95380752 | AU12: 0.51833413 | AV12: 1.3460493e+11 | AW12: 1.8273093e+11 | AX12: 32.911062 | AY12: 4.0271939 | AZ12: 12.950253 | BA12: 13.681561 | BB12: 0.036172524 | BC12: 22.90368
A13: AMGN | B13: 2025 | C13: 322.62134 | D13: 36751000000 | E13: 24714000000 | F13: 7711000000 | G13: 14.23 | H13: 9.52 | I13: 542000000 | J13: 8100000000 | K13: 9958000000 | L13: -1858000000 | M13: 5124000000 | N13: 9129000000 | O13: 29057000000 | P13: 90586000000 | Q13: 91212500000 | R13: 25489000000 | S13: 6225000000 | T13: 8658000000 | U13: 7267500000 | V13: 54604000000 | W13: 63262000000 | X13: 16898000000 | Y13: 11731000000 | Z13: 2755000000 | AA13: 8976000000 | AB13: 1265000000 | AC13: 0.14093137 | AE13: 0.6724715 | AF13: 0.3192022 | AG13: 0.20981742 | AH13: 1.0610251 | AI13: 0.084538852 | AJ13: 1.0077734e+10 | AK13: 0.15930154 | AL13: 0.66450525 | AM13: 0.63259259 | AN13: 6.3067683 | AO13: 4.2580762 | AP13: 0.18236759 | AQ13: 45475000000 | AR13: 2.6911469 | AS13: 1.139982 | AT13: 0.89575895 | AU13: 0.3581545 | AV13: 1.7486077e+11 | AW13: 2.2033577e+11 | AX13: 22.671914 | AY13: 4.7579866 | AZ13: 21.587749 | BA13: 13.039162 | BB13: 0.029508278 | BC13: 20.196439
A14: AMZN | B14: 2022 | C14: 84 | D14: 513983000000 | E14: 225152000000 | F14: -2722000000 | G14: -0.27 | I14: 10189000000 | J14: -16893000000 | K14: 46752000000 | L14: -63645000000 | N14: 53888000000 | O14: 146791000000 | P14: 462675000000 | Q14: 462675000000 | R14: 155393000000 | S14: 34405000000 | T14: 146043000000 | U14: 146043000000 | V14: 140118000000 | W14: 213193000000 | X14: 38352000000 | Y14: -3569000000 | Z14: 2367000000 | AA14: -5936000000 | AE14: 0.4380534 | AF14: -0.0069438094 | AG14: -0.005295895 | AH14: -0.018638346 | AI14: -0.0058831793 | AJ14: -2819510000 | AK14: -0.013225153 | AN14: 0.95942976 | AO14: -1.5078158 | AP14: 0.33366163 | AQ14: 86230000000 | AR14: 2.2483834 | AS14: 0.94464358 | AT14: 0.72323721 | AU14: 0.34678525 | AV14: 855876000000 | AW14: 942106000000 | AX14: -311.11111 | AY14: 1.6651835 | AZ14: -50.664536 | BA14: 24.564716 | BC14: 5.8604384
A15: AMZN | B15: 2023 | C15: 151.94 | D15: 574785000000 | E15: 270046000000 | F15: 30425000000 | G15: 2.9 | I15: 10492000000 | J15: 32217000000 | K15: 84946000000 | L15: -52729000000 | N15: 73387000000 | O15: 172351000000 | P15: 527854000000 | Q15: 495264500000 | R15: 164917000000 | S15: 33318000000 | T15: 201875000000 | U15: 173959000000 | V15: 135611000000 | W15: 260189000000 | X15: 89402000000 | Y15: 40739000000 | Z15: 3182000000 | AA15: 37557000000 | AE15: 0.46982089 | AF15: 0.070876937 | AG15: 0.052932836 | AH15: 0.17489753 | AI15: 0.061431821 | AJ15: 32183810000 | AK15: 0.12369397 | AN15: 0.67175728 | AO15: 12.802954 | AP15: 0.62639461 | AQ15: 62224000000 | AR15: 0.69600233 | AS15: 1.0450772 | AT15: 0.84304832 | AU15: 0.44499354 | AV15: 1.5941545e+12 | AW15: 1.6563785e+12 | AX15: 52.393104 | AY15: 2.7734797 | AZ15: 49.48178 | BA15: 18.527309 | BC15: 7.8967406
A16: AMZN | B16: 2024 | C16: 219.39 | D16: 637959000000 | E16: 311671000000 | F16: 59248000000 | G16: 5.53 | I16: 10721000000 | J16: 32878000000 | K16: 115877000000 | L16: -82999000000 | N16: 78779000000 | O16: 190867000000 | P16: 624894000000 | Q16: 576374000000 | R16: 179431000000 | S16: 34214000000 | T16: 285970000000 | U16: 243922500000 | V16: 130900000000 | W16: 338593000000 | X16: 123815000000 | Y16: 71020000000 | Z16: 2406000000 | AA16: 68614000000 | AE16: 0.48854393 | AF16: 0.11132377 | AG16: 0.092871172 | AH16: 0.24289682 | AI16: 0.10279437 | AJ16: 56105800000 | AK16: 0.16570278 | AN16: 0.45774032 | AO16: 29.517872 | AP16: 0.885233 | AQ16: 52121000000 | AR16: 0.42095869 | AS16: 1.0637348 | AT16: 0.87305427 | AU16: 0.43904899 | AV16: 2.3520802e+12 | AW16: 2.4042012e+12 | AX16: 39.672694 | AY16: 3.686883 | AZ16: 71.539637 | BA16: 19.417689 | BC16: 8.2249193
A17: AMZN | B17: 2025 | C17: 230.82001 | D17: 716924000000 | E17: 360510000000 | F17: 77670000000 | G17: 7.17 | I17: 10827000000 | J17: 7695000000 | K17: 139514000000 | L17: -131819000000 | N17: 86810000000 | O17: 229083000000 | P17: 818042000000 | Q17: 721468000000 | R17: 218005000000 | S17: 38325000000 | T17: 411065000000 | U17: 348517500000 | V17: 152987000000 | W17: 476713000000 | X17: 165341000000 | Y17: 99585000000 | Z17: 2274000000 | AA17: 97311000000 | AE17: 0.50285665 | AF17: 0.13890594 | AG17: 0.10833784 | AH17: 0.22285825 | AI17: 0.1076555 | AJ17: 78672150000 | AK17: 0.16503043 | AN17: 0.37217228 | AO17: 43.792876 | AP17: 0.91193369 | AQ17: 66177000000 | AR17: 0.40024555 | AS17: 1.0508153 | AT17: 0.87501663 | AU17: 0.39820188 | AV17: 2.4990882e+12 | AW17: 2.5652652e+12 | AX17: 32.19247 | AY17: 3.4858482 | AZ17: 324.7678 | BA17: 15.514998 | BC17: 6.0795451
A18: ASML | B18: 2022 | C18: 529.78485 | D18: 21173400000 | E18: 10700100000 | F18: 5624200000 | G18: 16.07 | H18: 6.634 | I18: 398000000 | J18: 7167500000 | L18: -1319300000 | M18: 2559800000 | N18: 7268300000 | O18: 23064900000 | P18: 36300400000 | Q18: 36300400000 | R18: 17983600000 | S18: 7199700000 | T18: 8810800000 | U18: 8810800000 | V18: 4260400000 | W18: 13071200000 | X18: 7100500000 | Y18: 6516900000 | Z18: 60800000 | AA18: 6456100000 | AB18: 969900000 | AC18: 0.15023002 | AE18: 0.50535578 | AF18: 0.30778713 | AG18: 0.26562574 | AH18: 0.63833023 | AI18: 0.15493493 | AJ18: 5.537866e+09 | AK18: 0.42366929 | AL18: 0.45514029 | AM18: 0.35713987 | AN18: 0.48354292 | AO18: 107.18586 | AQ18: -3007900000 | AR18: -0.42361806 | AS18: 1.2825519 | AT18: 0.88220379 | AU18: 0.40416268 | AV18: 2.1085437e+11 | AW18: 2.0784647e+11 | AX18: 32.967321 | AY18: 9.9584559 | AZ18: 29.418119 | BA18: 29.272089 | BB18: 0.012522064 | BC18: 23.931354
A19: ASML | B19: 2023 | C19: 741.18604 | D19: 27558500000 | E19: 14136100000 | F19: 7839000000 | G19: 20.59 | H19: 6.453 | I19: 394100000 | J19: 3247200000 | L19: -2196200000 | M19: 2348300000 | N19: 7004700000 | O19: 24393900000 | P19: 39957500000 | Q19: 38128950000 | R19: 16274700000 | S19: 8850700000 | T19: 13452400000 | U19: 11131600000 | V19: 4631600000 | W19: 18084000000 | X19: 9976000000 | Y19: 9236200000 | Z19: 152700000 | AA19: 9083500000 | AB19: 1435800000 | AC19: 0.15806682 | AE19: 0.51294882 | AF19: 0.33514887 | AG19: 0.28444944 | AH19: 0.70421143 | AI19: 0.20559181 | AJ19: 7.7762632e+09 | AK19: 0.43000792 | AL19: 0.29956627 | AM19: 0.72317689 | AN19: 0.34429544 | AO19: 60.48592 | AQ19: -2373100000 | AR19: -0.23788091 | AS19: 1.4988848 | AT19: 0.95505293 | AU19: 0.43040425 | AV19: 2.9210142e+11 | AW19: 2.8972832e+11 | AX19: 35.997379 | AY19: 10.599322 | AZ19: 89.954858 | BA19: 29.042534 | BB19: 0.0087063162 | BC19: 21.713703
A20: ASML | B20: 2024 | C20: 684.12122 | D20: 28262900000 | E20: 14492000000 | F20: 7571600000 | G20: 19.24 | H20: 6.713 | I20: 393600000 | J20: 9083100000 | L20: -2083100000 | M20: 2452900000 | N20: 12735900000 | O20: 30737400000 | P20: 48589600000 | Q20: 44273550000 | R20: 20051400000 | S20: 10891500000 | T20: 18476800000 | U20: 15964600000 | V20: 4687600000 | W20: 23164400000 | X20: 10123600000 | Y20: 9205000000 | Z20: 162600000 | AA20: 9042400000 | AB20: 1680600000 | AC20: 0.18585774 | AE20: 0.51275701 | AF20: 0.32569198 | AG20: 0.26789891 | AH20: 0.47427433 | AI20: 0.17101859 | AJ20: 7.4941795e+09 | AK20: 0.32352142 | AL20: 0.32396059 | AM20: 0.27005097 | AN20: 0.25370194 | AO20: 56.611316 | AQ20: -8048300000 | AR20: -0.79500375 | AS20: 1.5329304 | AT20: 0.98975134 | AU20: 0.63516263 | AV20: 2.6927011e+11 | AW20: 2.6122181e+11 | AX20: 35.557236 | AY20: 9.5273348 | AZ20: 29.645177 | BA20: 25.803253 | BB20: 0.0098125885 | BC20: 14.573417
A21: ASML | B21: 2025 | C21: 1066.1221 | D21: 32667300000 | E21: 17258000000 | F21: 9609400000 | G21: 26.26 | H21: 7.372 | I21: 388900000 | J21: 11027300000 | L21: -1631200000 | M21: 2550300000 | N21: 12916000000 | O21: 30616100000 | P21: 50566600000 | Q21: 49578100000 | R21: 24263900000 | S21: 11429300000 | T21: 19612200000 | U21: 19044500000 | V21: 4390900000 | W21: 24003100000 | X21: 12550300000 | Y21: 11524400000 | Z21: 118300000 | AA21: 11406100000 | AB21: 2013400000 | AC21: 0.17651958 | AE21: 0.52829588 | AF21: 0.35278092 | AG21: 0.2941596 | AH21: 0.50457612 | AI21: 0.19382348 | AJ21: 9.4901177e+09 | AK21: 0.3953705 | AL21: 0.26539638 | AM21: 0.23127148 | AN21: 0.22388615 | AO21: 97.416737 | AQ21: -8525100000 | AR21: -0.6792746 | AS21: 1.2617963 | AT21: 0.79075499 | AU21: 0.53231344 | AV21: 4.1461487e+11 | AW21: 4.0608977e+11 | AX21: 40.598708 | AY21: 12.692046 | AZ21: 37.598947 | BA21: 32.356977 | BB21: 0.0069147804 | BC21: 21.140661
A22: CCEP | B22: 2022 | C22: 50.251957 | D22: 17320000000 | E22: 6224000000 | F22: 1508000000 | G22: 3.29 | H22: 1.7 | I22: 458358663 | J22: 2329000000 | K22: 2932000000 | L22: -603000000 | M22: 763000000 | N22: 1387000000 | O22: 6543000000 | P22: 29313000000 | Q22: 29313000000 | R22: 7313000000 | S22: 1380000000 | T22: 7447000000 | U22: 7447000000 | V22: 11907000000 | W22: 18678000000 | X22: 2935000000 | Y22: 2119000000 | Z22: 162000000 | AA22: 1957000000 | AB22: 436000000 | AC22: 0.22278998 | AE22: 0.35935335 | AF22: 0.12234411 | AG22: 0.087066975 | AH22: 0.20249765 | AI22: 0.051444751 | AJ22: 1.646908e+09 | AK22: 0.088173681 | AL22: 0.50596817 | AM22: 0.32760842 | AN22: 1.5988989 | AO22: 13.080247 | AP22: 0.24624171 | AQ22: 10520000000 | AR22: 3.5843271 | AS22: 0.89470805 | AT22: 0.70600301 | AU22: 0.18966225 | AV22: 2.303342e+10 | AW22: 3.355342e+10 | AX22: 15.274151 | AY22: 1.3298741 | AZ22: 9.8898325 | BA22: 11.43217 | BB22: 0.033829528 | BC22: 3.0929797
A23: CCEP | B23: 2023 | C23: 62.563965 | D23: 18302000000 | E23: 6720000000 | F23: 1669000000 | G23: 3.63 | H23: 1.97 | I23: 459779614 | J23: 1994000000 | K23: 2806000000 | L23: -812000000 | M23: 841000000 | N23: 1419000000 | O23: 6605000000 | P23: 29254000000 | Q23: 29283500000 | R23: 7278000000 | S23: 1356000000 | T23: 7976000000 | U23: 7711500000 | V23: 11396000000 | W23: 18680000000 | X23: 3157000000 | Y23: 2365000000 | Z23: 162000000 | AA23: 2203000000 | AB23: 534000000 | AC23: 0.24239673 | AE23: 0.36717299 | AF23: 0.12922085 | AG23: 0.091192219 | AH23: 0.21643001 | AI23: 0.056994553 | AJ23: 1.7917317e+09 | AK23: 0.095917116 | AL23: 0.50389455 | AM23: 0.4217653 | AN23: 1.4287864 | AO23: 14.598765 | AP23: 0.24622675 | AQ23: 9977000000 | AR23: 3.1602787 | AS23: 0.90752954 | AT23: 0.72121462 | AU23: 0.19497115 | AV23: 2.8765636e+10 | AW23: 3.8742636e+10 | AX23: 17.235252 | AY23: 1.5717209 | AZ23: 14.426096 | BA23: 12.271978 | BB23: 0.031487774 | BC23: 3.606524
A24: CCEP | B24: 2024 | C24: 74.045609 | D24: 20438000000 | E24: 7211000000 | F24: 1418000000 | G24: 3.08 | H24: 2.13 | I24: 461000000 | J24: 2122000000 | K24: 3061000000 | L24: -939000000 | M24: 910000000 | N24: 1563000000 | O24: 6638000000 | P24: 31100000000 | Q24: 30177000000 | R24: 8149000000 | S24: 1608000000 | T24: 8489000000 | U24: 8232500000 | V24: 11331000000 | W24: 19112000000 | X24: 3111000000 | Y24: 2178000000 | Z24: 242000000 | AA24: 1936000000 | AB24: 492000000 | AC24: 0.25413223 | AE24: 0.35282317 | AF24: 0.1065662 | AG24: 0.069380566 | AH24: 0.17224415 | AI24: 0.046989429 | AJ24: 1624500000 | AK24: 0.084998954 | AL24: 0.64174894 | AM24: 0.42884072 | AN24: 1.3347862 | AO24: 9 | AP24: 0.27014385 | AQ24: 9768000000 | AR24: 3.1398264 | AS24: 0.81457848 | AT24: 0.61725365 | AU24: 0.19180268 | AV24: 3.4135026e+10 | AW24: 4.3903026e+10 | AX24: 24.040782 | AY24: 1.6701745 | AZ24: 16.086251 | BA24: 14.112191 | BB24: 0.028766054 | BC24: 4.0210891
A25: CCEP | B25: 2025 | C25: 89.741371 | D25: 20901000000 | E25: 7440000000 | F25: 1942000000 | G25: 4.26 | H25: 2.33 | I25: 456000000 | J25: 2003000000 | K25: 2953000000 | L25: -950000000 | M25: 927000000 | N25: 918000000 | O25: 6079000000 | P25: 29872000000 | Q25: 30486000000 | R25: 7585000000 | S25: 1547000000 | T25: 7835000000 | U25: 8162000000 | V25: 10694000000 | W25: 17830000000 | X25: 3766000000 | Y25: 2843000000 | Z25: 274000000 | AA25: 2569000000 | AB25: 590000000 | AC25: 0.22966135 | AE25: 0.35596383 | AF25: 0.1360222 | AG25: 0.092914215 | AH25: 0.23793188 | AI25: 0.063701371 | AJ25: 2.1900728e+09 | AK25: 0.12283078 | AL25: 0.47734295 | AM25: 0.46280579 | AN25: 1.3649011 | AO25: 10.375912 | AP25: 0.27613615 | AQ25: 9776000000 | AR25: 2.5958577 | AS25: 0.80145023 | AT25: 0.59749506 | AU25: 0.12102835 | AV25: 4.0922065e+10 | AW25: 5.0698065e+10 | AX25: 21.06605 | AY25: 1.9578999 | AZ25: 20.430387 | BA25: 13.462046 | BB25: 0.025963499 | BC25: 5.2229822
A26: CHTR | B26: 2022 | C26: 339.10001 | D26: 54022000000 | E26: 29511000000 | F26: 5055000000 | G26: 30.74 | I26: 164433596 | J26: 5549000000 | K26: 14925000000 | L26: -9376000000 | N26: 645000000 | O26: 4017000000 | P26: 144523000000 | Q26: 144523000000 | R26: 12065000000 | T26: 9119000000 | U26: 9119000000 | V26: 97603000000 | W26: 106722000000 | X26: 20921000000 | Y26: 12018000000 | Z26: 4556000000 | AA26: 7462000000 | AB26: 1613000000 | AC26: 0.21616189 | AE26: 0.54627744 | AF26: 0.22246492 | AG26: 0.093572989 | AH26: 0.5543371 | AI26: 0.034977132 | AJ26: 9.4201664e+09 | AK26: 0.088268271 | AN26: 10.703257 | AO26: 2.6378402 | AP26: 0.15291538 | AQ26: 96958000000 | AR26: 4.6344821 | AS26: 0.33294654 | AT26: 0.33294654 | AU26: 0.053460423 | AV26: 5.5759433e+10 | AW26: 1.5271743e+11 | AX26: 11.03123 | AY26: 1.0321616 | AZ26: 10.048555 | BA26: 7.2997196 | BC26: 6.1146434
A27: CHTR | B27: 2023 | C27: 388.67999 | D27: 54607000000 | E27: 29907000000 | F27: 4557000000 | G27: 29.99 | I27: 151966313 | J27: 3318000000 | K27: 14433000000 | L27: -11115000000 | N27: 709000000 | O27: 4132000000 | P27: 147193000000 | Q27: 145858000000 | R27: 13214000000 | T27: 11086000000 | U27: 10102500000 | V27: 98202000000 | W27: 109288000000 | X27: 20738000000 | Y27: 12042000000 | Z27: 5188000000 | AA27: 6854000000 | AB27: 1593000000 | AC27: 0.23241903 | AE27: 0.54767704 | AF27: 0.22052118 | AG27: 0.08345084 | AH27: 0.45107647 | AI27: 0.031242716 | AJ27: 9.2432101e+09 | AK27: 0.084576624 | AN27: 8.8581995 | AO27: 2.3211257 | AP27: 0.14697257 | AQ27: 97493000000 | AR27: 4.7011766 | AS27: 0.31269865 | AT27: 0.31269865 | AU27: 0.053655214 | AV27: 5.9066265e+10 | AW27: 1.5655927e+11 | AX27: 12.96032 | AY27: 1.0816611 | AZ27: 17.801768 | BA27: 7.5493908 | BC27: 5.3280052
A28: CHTR | B28: 2024 | C28: 342.76999 | D28: 55085000000 | E28: 30736000000 | F28: 5083000000 | G28: 34.97 | I28: 145363771 | J28: 3161000000 | K28: 14430000000 | L28: -11269000000 | N28: 459000000 | O28: 4233000000 | P28: 150020000000 | Q28: 148606500000 | R28: 13486000000 | T28: 15587000000 | U28: 13336500000 | V28: 95763000000 | W28: 111350000000 | X28: 21404000000 | Y28: 12731000000 | Z28: 5229000000 | AA28: 7502000000 | AB28: 1649000000 | AC28: 0.21980805 | AE28: 0.55797404 | AF28: 0.23111555 | AG28: 0.092275574 | AH28: 0.38113448 | AI28: 0.034204426 | AJ28: 9.9326237e+09 | AK28: 0.089201829 | AN28: 6.1437737 | AO28: 2.4346911 | AP28: 0.1506845 | AQ28: 95304000000 | AR28: 4.4526257 | AS28: 0.31388106 | AT28: 0.31388106 | AU28: 0.034035296 | AV28: 4.9826338e+10 | AW28: 1.4513034e+11 | AX28: 9.8018298 | AY28: 0.9045355 | AZ28: 15.76284 | BA28: 6.7805241 | BC28: 3.1966599
A29: CHTR | B29: 2025 | C29: 208.75 | D29: 54774000000 | E29: 30968000000 | F29: 4987000000 | G29: 36.21 | I29: 137743676 | J29: 4418000000 | K29: 16077000000 | L29: -11659000000 | N29: 477000000 | O29: 5144000000 | P29: 154213000000 | Q29: 152116500000 | R29: 13306000000 | T29: 16054000000 | U29: 15820500000 | V29: 97121000000 | W29: 113175000000 | X29: 21211000000 | Y29: 12500000000 | Z29: 5042000000 | AA29: 7458000000 | AB29: 1692000000 | AC29: 0.22687047 | AE29: 0.56537773 | AF29: 0.22821046 | AG29: 0.091046847 | AH29: 0.31522392 | AI29: 0.032784083 | AJ29: 9.6641191e+09 | AK29: 0.085390935 | AN29: 6.0496449 | AO29: 2.4791749 | AP29: 0.16553577 | AQ29: 96644000000 | AR29: 4.5563151 | AS29: 0.38659251 | AT29: 0.38659251 | AU29: 0.035848489 | AV29: 28753992365 | AW29: 125397992365 | AX29: 5.764982 | AY29: 0.52495696 | AZ29: 6.5083731 | BA29: 5.9119321 | BC29: 1.7910796
A30: COST | B30: 2022 | C30: 436.90512 | D30: 226954000000 | E30: 27572000000 | F30: 5844000000 | G30: 13.14 | H30: 3.49 | I30: 444757000 | J30: 3501000000 | K30: 7392000000 | L30: -3891000000 | M30: 1498000000 | N30: 10203000000 | O30: 32696000000 | P30: 64166000000 | Q30: 64166000000 | R30: 31998000000 | S30: 17907000000 | T30: 20642000000 | U30: 20642000000 | V30: 9039000000 | W30: 27199000000 | X30: 9898000000 | Y30: 7998000000 | Z30: 158000000 | AA30: 7840000000 | AB30: 1925000000 | AC30: 0.24553571 | AE30: 0.12148717 | AF30: 0.035240621 | AG30: 0.025749711 | AH30: 0.2831121 | AI30: 0.091076271 | AJ30: 6.0342054e+09 | AK30: 0.22185394 | AL30: 0.25633128 | AM30: 0.42787775 | AN30: 0.43789361 | AO30: 50.620253 | AP30: 0.81778958 | AQ30: -1164000000 | AR30: -0.11759952 | AS30: 1.0218139 | AT30: 0.46218514 | AU30: 0.31886368 | AV30: 1.9431661e+11 | AW30: 1.9315261e+11 | AX30: 33.250009 | AY30: 0.85619381 | AZ30: 55.503174 | BA30: 19.514307 | BB30: 0.0079880043 | BC30: 9.4136523
A31: COST | B31: 2023 | C31: 651.00543 | D31: 242290000000 | E31: 29704000000 | F31: 6292000000 | G31: 14.16 | H31: 18.96 | I31: 444452000 | J31: 6745000000 | K31: 11068000000 | L31: -4323000000 | M31: 1251000000 | N31: 13700000000 | O31: 35879000000 | P31: 68994000000 | Q31: 66580000000 | R31: 33583000000 | S31: 16651000000 | T31: 25058000000 | U31: 22850000000 | V31: 8884000000 | W31: 31516000000 | X31: 10724000000 | Y31: 8647000000 | Z31: 160000000 | AA31: 8487000000 | AB31: 2195000000 | AC31: 0.25863085 | AE31: 0.12259689 | AF31: 0.035688638 | AG31: 0.02596888 | AH31: 0.27536105 | AI31: 0.094502854 | AJ31: 6.4106191e+09 | AK31: 0.2034084 | AL31: 0.1988239 | AM31: 0.18547072 | AN31: 0.35453747 | AO31: 54.04375 | AP31: 1.2458352 | AQ31: -4816000000 | AR31: -0.44908616 | AS31: 1.0683679 | AT31: 0.57255159 | AU31: 0.4079445 | AV31: 2.8934067e+11 | AW31: 2.8452467e+11 | AX31: 45.97496 | AY31: 1.1941915 | AZ31: 42.897059 | BA31: 26.53158 | BB31: 0.029124181 | BC31: 11.546838
A32: COST | B32: 2024 | C32: 908.95111 | D32: 254453000000 | E32: 32095000000 | F32: 7367000000 | G32: 16.56 | H32: 4.5 | I32: 444759000 | J32: 6629000000 | K32: 11339000000 | L32: -4710000000 | M32: 1251000000 | N32: 9906000000 | O32: 34246000000 | P32: 69831000000 | Q32: 69412500000 | R32: 35464000000 | S32: 18647000000 | T32: 23622000000 | U32: 24340000000 | V32: 8169000000 | W32: 29416000000 | X32: 12146000000 | Y32: 9909000000 | Z32: 169000000 | AA32: 9740000000 | AB32: 2373000000 | AC32: 0.2436345 | AE32: 0.12613331 | AF32: 0.038942359 | AG32: 0.028952302 | AH32: 0.3026705 | AI32: 0.10613362 | AJ32: 7.4948258e+09 | AK32: 0.25478739 | AL32: 0.16981132 | AM32: 0.18871625 | AN32: 0.34582169 | AO32: 58.633136 | AP32: 1.3880524 | AQ32: -1737000000 | AR32: -0.14301004 | AS32: 0.96565531 | AT32: 0.4398545 | AU32: 0.27932551 | AV32: 4.0426419e+11 | AW32: 4.0252719e+11 | AX32: 54.888352 | AY32: 1.5887578 | AZ32: 60.984189 | BA32: 33.14072 | BB32: 0.0049507613 | BC32: 17.113885
A33: COST | B33: 2025 | C33: 859.91577 | D33: 275235000000 | E33: 35349000000 | F33: 8099000000 | G33: 18.21 | H33: 5.06 | I33: 444803000 | J33: 7837000000 | K33: 13335000000 | L33: -5498000000 | M33: 1251000000 | N33: 14161000000 | O33: 38380000000 | P33: 77099000000 | Q33: 73465000000 | R33: 37108000000 | S33: 18116000000 | T33: 29164000000 | U33: 26393000000 | V33: 8173000000 | W33: 34877000000 | X33: 13398000000 | Y33: 10972000000 | Z33: 154000000 | AA33: 10818000000 | AB33: 2719000000 | AC33: 0.25134036 | AE33: 0.12843207 | AF33: 0.039864116 | AG33: 0.029425763 | AH33: 0.30686167 | AI33: 0.11024297 | AJ33: 8.2142936e+09 | AK33: 0.23552179 | AL33: 0.15446351 | AM33: 0.15962741 | AN33: 0.28024277 | AO33: 71.246753 | AP33: 1.6315918 | AQ33: -5988000000 | AR33: -0.44693238 | AS33: 1.0342783 | AT33: 0.54608171 | AU33: 0.38161582 | AV33: 3.8249311e+11 | AW33: 3.7650511e+11 | AX33: 47.222173 | AY33: 1.3896965 | AZ33: 48.806063 | BA33: 28.101591 | BB33: 0.0058842972 | BC33: 13.115249
A34: GILD | B34: 2022 | C34: 76.816048 | D34: 27281000000 | E34: 21624000000 | F34: 4592000000 | G34: 3.64 | H34: 2.92 | I34: 1262000000 | J34: 8344000000 | K34: 9072000000 | L34: -728000000 | M34: 3709000000 | N34: 5412000000 | O34: 14443000000 | P34: 63171000000 | Q34: 63171000000 | R34: 11238000000 | S34: 1507000000 | T34: 21240000000 | U34: 21240000000 | V34: 25230000000 | W34: 46470000000 | X34: 8852000000 | Y34: 6749000000 | Z34: 935000000 | AA34: 5814000000 | AB34: 1248000000 | AC34: 0.21465428 | AE34: 0.79263957 | AF34: 0.24738829 | AG34: 0.16832228 | AH34: 0.21619586 | AI34: 0.072691583 | AJ34: 5.3002982e+09 | AK34: 0.11405849 | AL34: 0.80770906 | AM34: 0.44451103 | AN34: 1.1878531 | AO34: 7.2181818 | AP34: 0.35957194 | AQ34: 19818000000 | AR34: 2.2388161 | AS34: 1.2851931 | AT34: 1.1510945 | AU34: 0.48158035 | AV34: 9.6941852e+10 | AW34: 1.1675985e+11 | AX34: 21.10331 | AY34: 3.5534567 | AZ34: 11.618151 | BA34: 13.190223 | BB34: 0.03801289 | BC34: 4.5641173
A35: GILD | B35: 2023 | C35: 75.285263 | D35: 27116000000 | E35: 20618000000 | F35: 5665000000 | G35: 4.5 | H35: 3 | I35: 1258000000 | J35: 7421000000 | K35: 8006000000 | L35: -585000000 | M35: 3809000000 | N35: 6085000000 | O35: 16085000000 | P35: 62125000000 | Q35: 62648000000 | R35: 11280000000 | S35: 1787000000 | T35: 22833000000 | U35: 22036500000 | V35: 24987000000 | W35: 47820000000 | X35: 10496000000 | Y35: 7803000000 | Z35: 944000000 | AA35: 6859000000 | AB35: 1247000000 | AC35: 0.18180493 | AE35: 0.76036289 | AF35: 0.28776368 | AG35: 0.20891724 | AH35: 0.25707349 | AI35: 0.090425872 | AJ35: 6.3843761e+09 | AK35: 0.13350849 | AL35: 0.67237423 | AM35: 0.51327314 | AN35: 1.0943371 | AO35: 8.2658898 | AP35: 0.32040661 | AQ35: 18902000000 | AR35: 1.8008765 | AS35: 1.4259752 | AT35: 1.2675532 | AU35: 0.53945035 | AV35: 9.4708861e+10 | AW35: 1.1361086e+11 | AX35: 16.730058 | AY35: 3.4927298 | AZ35: 12.762277 | BA35: 10.824206 | BB35: 0.039848436 | BC35: 4.1478939
A36: GILD | B36: 2024 | C36: 89.350464 | D36: 28754000000 | E36: 22503000000 | F36: 480000000 | G36: 0.38 | H36: 3.08 | I36: 1255000000 | J36: 10305000000 | K36: 10828000000 | L36: -523000000 | M36: 3918000000 | N36: 9991000000 | O36: 19173000000 | P36: 58995000000 | Q36: 60560000000 | R36: 12004000000 | S36: 1710000000 | T36: 19330000000 | U36: 21081500000 | V36: 26711000000 | W36: 46041000000 | X36: 4434000000 | Y36: 1667000000 | Z36: 977000000 | AA36: 690000000 | AB36: 211000000 | AC36: 0.3057971 | AE36: 0.78260416 | AF36: 0.057974543 | AG36: 0.01669333 | AH36: 0.022768778 | AI36: 0.0079260238 | AJ36: 1.1572362e+09 | AK36: 0.025134907 | AL36: 8.1625 | AM36: 0.38020378 | AN36: 1.3818417 | AO36: 1.7062436 | AP36: 0.40537606 | AQ36: 16720000000 | AR36: 3.7708615 | AS36: 1.5972176 | AT36: 1.4547651 | AU36: 0.8323059 | AV36: 1.1213483e+11 | AW36: 1.2885483e+11 | AX36: 235.1328 | AY36: 3.8997994 | AZ36: 10.881595 | BA36: 29.06063 | BB36: 0.034471002 | BC36: 5.8010777
A37: GILD | B37: 2025 | C37: 122.04688 | D37: 29442000000 | E37: 23208000000 | F37: 8510000000 | G37: 6.78 | H37: 3.16 | I37: 1255000000 | J37: 9456000000 | K37: 10019000000 | L37: -563000000 | M37: 4003000000 | N37: 7564000000 | O37: 18342000000 | P37: 59023000000 | Q37: 59009000000 | R37: 11813000000 | S37: 1774000000 | T37: 22702000000 | U37: 21016000000 | V37: 24936000000 | W37: 47638000000 | X37: 13580000000 | Y37: 10820000000 | Z37: 1024000000 | AA37: 9796000000 | AB37: 1286000000 | AC37: 0.13127807 | AE37: 0.78826167 | AF37: 0.36750221 | AG37: 0.28904286 | AH37: 0.40492958 | AI37: 0.14421529 | AJ37: 9.3995713e+09 | AK37: 0.19731247 | AL37: 0.47038778 | AM37: 0.4233291 | AN37: 1.0984054 | AO37: 10.566406 | AP37: 0.40178858 | AQ37: 17372000000 | AR37: 1.2792342 | AS37: 1.5526962 | AT37: 1.4025226 | AU37: 0.64031152 | AV37: 1.5316884e+11 | AW37: 1.7054084e+11 | AX37: 18.001015 | AY37: 5.2023924 | AZ37: 16.198058 | BA37: 12.558235 | BB37: 0.02589169 | BC37: 6.7469314
A38: GOOGL | B38: 2022 | C38: 87.50676 | D38: 282836000000 | E38: 156633000000 | F38: 59972000000 | G38: 4.56 | H38: 0 | I38: 13159000000 | J38: 60010000000 | K38: 91495000000 | L38: -31485000000 | M38: 0 | N38: 21879000000 | O38: 164795000000 | P38: 365264000000 | Q38: 365264000000 | R38: 69300000000 | S38: 2670000000 | T38: 256144000000 | U38: 256144000000 | V38: 29679000000 | W38: 269001000000 | X38: 85160000000 | Y38: 71685000000 | Z38: 357000000 | AA38: 71328000000 | AB38: 11356000000 | AC38: 0.15920817 | AE38: 0.55379443 | AF38: 0.25345076 | AG38: 0.21203807 | AH38: 0.23413392 | AI38: 0.16418809 | AJ38: 6.0272163e+10 | AK38: 0.22405925 | AL38: 0 | AM38: 0 | AN38: 0.11586842 | AO38: 200.79832 | AP38: 3.0828195 | AQ38: 7800000000 | AR38: 0.091592297 | AS38: 2.3779942 | AT38: 2.3394661 | AU38: 0.31571429 | AV38: 1.1515015e+12 | AW38: 1.1593015e+12 | AX38: 19.190079 | AY38: 4.071269 | AZ38: 19.188493 | BA38: 13.613216 | BB38: 0 | BC38: 4.4955238
A39: GOOGL | B39: 2023 | C39: 138.54494 | D39: 307394000000 | E39: 174062000000 | F39: 73795000000 | G39: 5.8 | H39: 0 | I39: 12722000000 | J39: 69495000000 | K39: 101746000000 | L39: -32251000000 | M39: 0 | N39: 24048000000 | O39: 171530000000 | P39: 402392000000 | Q39: 383828000000 | R39: 81814000000 | S39: 2670000000 | T39: 283379000000 | U39: 269761500000 | V39: 27121000000 | W39: 295249000000 | X39: 97971000000 | Y39: 86025000000 | Z39: 308000000 | AA39: 85717000000 | AB39: 11922000000 | AC39: 0.1390856 | AE39: 0.56625048 | AF39: 0.27985257 | AG39: 0.24006649 | AH39: 0.27355646 | AI39: 0.1922606 | AJ39: 7.4060162e+10 | AK39: 0.25083967 | AL39: 0 | AM39: 0 | AN39: 0.095705751 | AO39: 279.30195 | AP39: 3.7515578 | AQ39: 3073000000 | AR39: 0.031366425 | AS39: 2.0965849 | AT39: 2.0639499 | AU39: 0.29393502 | AV39: 1.7625687e+12 | AW39: 1.7656417e+12 | AX39: 23.887058 | AY39: 5.7339073 | AZ39: 25.362525 | BA39: 18.022085 | BB39: 0 | BC39: 6.2198282
A40: GOOGL | B40: 2024 | C40: 188.42886 | D40: 350018000000 | E40: 203712000000 | F40: 100118000000 | G40: 8.04 | H40: 0.6 | I40: 12447000000 | J40: 72764000000 | K40: 125299000000 | L40: -52535000000 | M40: 7363000000 | N40: 23466000000 | O40: 163711000000 | P40: 450256000000 | Q40: 426324000000 | R40: 89122000000 | S40: 2670000000 | T40: 325084000000 | U40: 304231500000 | V40: 22574000000 | W40: 335967000000 | X40: 135394000000 | Y40: 120083000000 | Z40: 268000000 | AA40: 119815000000 | AB40: 19697000000 | AC40: 0.16439511 | AE40: 0.58200435 | AF40: 0.34307664 | AG40: 0.28603672 | AH40: 0.32908492 | AI40: 0.23484017 | AJ40: 1.0034194e+11 | AK40: 0.29866607 | AL40: 0.073543219 | AM40: 0.10119015 | AN40: 0.069440514 | AO40: 448.0709 | AP40: 5.5505892 | AQ40: -892000000 | AR40: -0.0065881797 | AS40: 1.8369314 | AT40: 1.8069725 | AU40: 0.26330199 | AV40: 2.3453741e+12 | AW40: 2.3444821e+12 | AX40: 23.436426 | AY40: 6.7007241 | AZ40: 32.232616 | BA40: 17.315997 | BB40: 0.0031842255 | BC40: 7.2146709
A41: GOOGL | B41: 2025 | C41: 312.77982 | D41: 402836000000 | E41: 240301000000 | F41: 132170000000 | G41: 10.81 | H41: 0.83 | I41: 12230000000 | J41: 73266000000 | K41: 164713000000 | L41: -91447000000 | M41: 10049000000 | N41: 30708000000 | O41: 206038000000 | P41: 595281000000 | Q41: 522768500000 | R41: 102745000000 | S41: 2670000000 | T41: 415265000000 | U41: 370174500000 | V41: 59291000000 | W41: 461812000000 | X41: 180698000000 | Y41: 159562000000 | Z41: 736000000 | AA41: 158826000000 | AB41: 26656000000 | AC41: 0.16783146 | AE41: 0.59652315 | AF41: 0.39609667 | AG41: 0.32809878 | AH41: 0.35704782 | AI41: 0.25282702 | AJ41: 1.3278248e+11 | AK41: 0.28752496 | AL41: 0.076030869 | AM41: 0.13715775 | AN41: 0.14277871 | AO41: 216.7962 | AP41: 2.7780439 | AQ41: 28583000000 | AR41: 0.15818105 | AS41: 2.0053336 | AT41: 1.9793469 | AU41: 0.29887586 | AV41: 3.8252971e+12 | AW41: 3.8538801e+12 | AX41: 28.934303 | AY41: 9.4959168 | AZ41: 52.211082 | BA41: 21.327741 | BB41: 0.0026536239 | BC41: 9.2117013
... A53: MELI | B53: 2025 | C53: 2014.26 | D53: 28893000000 | E53: 12858000000 | F53: 1997000000 | G53: 39.4 | H53: 0 | I53: 50697320 | J53: 10773000000 | K53: 12116000000 | L53: -1343000000 | M53: 0 | N53: 3670000000 | O53: 33573000000 | P53: 42667000000 | Q53: 33931500000 | R53: 28633000000 | S53: 570000000 | T53: 6748000000 | U53: 5549500000 | V53: 11392000000 | W53: 15811000000 | X53: 3820000000 | Y53: 3002000000 | Z53: 160000000 | AA53: 2842000000 | AB53: 845000000 | AC53: 0.29732583 | AE53: 0.44502129 | AF53: 0.1039006 | AG53: 0.069117087 | AH53: 0.35985224 | AI53: 0.058853867 | AJ53: 2.1094279e+09 | AK53: 0.13341521 | AL53: 0 | AM53: 0 | AN53: 1.6882039 | AO53: 18.7625 | AP53: 1.0635534 | AQ53: 7722000000 | AR53: 2.021466 | AS53: 1.1725282 | AT53: 1.1526211 | AU53: 0.12817379 | AV53: 1.0211758e+11 | AW53: 1.0983958e+11 | AX53: 51.123351 | AY53: 3.5343365 | AZ53: 9.4790295 | BA53: 28.753818 | BB53: 0 | BC53: 15.133015
A54: META | B54: 2022 | C54: 119.40299 | D54: 116609000000 | E54: 91360000000 | F54: 23200000000 | G54: 8.59 | H54: 0 | I54: 2702000000 | J54: 19289000000 | K54: 50475000000 | L54: -31186000000 | M54: 0 | N54: 14681000000 | O54: 59549000000 | P54: 185727000000 | Q54: 185727000000 | R54: 27026000000 | T54: 125713000000 | U54: 125713000000 | V54: 26591000000 | W54: 135636000000 | X54: 37690000000 | Y54: 29004000000 | Z54: 185000000 | AA54: 28819000000 | AB54: 5619000000 | AC54: 0.19497554 | AE54: 0.78347297 | AF54: 0.24872866 | AG54: 0.19895548 | AH54: 0.18454734 | AI54: 0.12491453 | AJ54: 2.334893e+10 | AK54: 0.17214404 | AL54: 0 | AM54: 0 | AN54: 0.21152148 | AO54: 156.77838 | AP54: 1.8981986 | AQ54: 11910000000 | AR54: 0.31599894 | AS54: 2.2033967 | AT54: 2.2033967 | AU54: 0.54321764 | AV54: 3.2262689e+11 | AW54: 3.3453689e+11 | AX54: 13.900232 | AY54: 2.7667409 | AZ54: 16.725952 | BA54: 8.8760118 | BB54: 0 | BC54: 2.5663765
A55: META | B55: 2023 | C55: 351.20392 | D55: 134902000000 | E55: 108943000000 | F55: 39098000000 | G55: 14.87 | H55: 0 | I55: 2629000000 | J55: 44068000000 | K55: 71113000000 | L55: -27045000000 | M55: 0 | N55: 41862000000 | O55: 85365000000 | P55: 229623000000 | Q55: 207675000000 | R55: 31960000000 | T55: 153168000000 | U55: 139440500000 | V55: 37234000000 | W55: 171553000000 | X55: 59052000000 | Y55: 47874000000 | Z55: 446000000 | AA55: 47428000000 | AB55: 8330000000 | AC55: 0.17563465 | AE55: 0.80757142 | AF55: 0.35487984 | AG55: 0.28982521 | AH55: 0.280392 | AI55: 0.18826532 | AJ55: 3.9465667e+10 | AK55: 0.23004941 | AL55: 0 | AM55: 0 | AN55: 0.24309255 | AO55: 107.34081 | AP55: 1.9098942 | AQ55: -4628000000 | AR55: -0.078371605 | AS55: 2.670995 | AT55: 2.670995 | AU55: 1.3098248 | AV55: 9.233151e+11 | AW55: 9.186871e+11 | AX55: 23.618286 | AY55: 6.8443396 | AZ55: 20.952054 | BA55: 15.557256 | BB55: 0 | BC55: 6.0281201
A56: META | B56: 2024 | C56: 583.17017 | D56: 164501000000 | E56: 134340000000 | F56: 62360000000 | G56: 23.86 | H56: 2 | I56: 2614000000 | J56: 54072000000 | K56: 91328000000 | L56: -37256000000 | M56: 5072000000 | N56: 43889000000 | O56: 100045000000 | P56: 276054000000 | Q56: 252838500000 | R56: 33596000000 | T56: 182637000000 | U56: 167902500000 | V56: 49060000000 | W56: 211463000000 | X56: 86876000000 | Y56: 71378000000 | Z56: 715000000 | AA56: 70663000000 | AB56: 8303000000 | AC56: 0.11750138 | AE56: 0.81665157 | AF56: 0.43390618 | AG56: 0.37908584 | AH56: 0.37140602 | AI56: 0.24663965 | AJ56: 6.2990987e+10 | AK56: 0.29788184 | AL56: 0.081334189 | AM56: 0.093800858 | AN56: 0.26862027 | AO56: 99.829371 | AP56: 1.8615573 | AQ56: 5171000000 | AR56: 0.059521617 | AS56: 2.9778843 | AT56: 2.9778843 | AU56: 1.3063758 | AV56: 1.5244068e+12 | AW56: 1.5295778e+12 | AX56: 24.441331 | AY56: 9.2668544 | AZ56: 28.192166 | BA56: 17.606448 | BB56: 0.0034295307 | BC56: 8.3466483
A57: META | B57: 2025 | C57: 659.52533 | D57: 200966000000 | E57: 164791000000 | F57: 60458000000 | G57: 23.49 | H57: 2.1 | I57: 2574000000 | J57: 46109000000 | K57: 115800000000 | L57: -69691000000 | M57: 5324000000 | N57: 35873000000 | O57: 108722000000 | P57: 366021000000 | Q57: 321037500000 | R57: 41836000000 | T57: 217243000000 | U57: 199940000000 | V57: 83897000000 | W57: 275987000000 | X57: 105713000000 | Y57: 87097000000 | Z57: 1165000000 | AA57: 85932000000 | AB57: 25474000000 | AC57: 0.2964437 | AE57: 0.81999443 | AF57: 0.43339172 | AG57: 0.30083696 | AH57: 0.30238071 | AI57: 0.18832068 | AJ57: 6.1277643e+10 | AK57: 0.2220309 | AL57: 0.088061133 | AM57: 0.11546553 | AN57: 0.38618966 | AO57: 74.761373 | AP57: 1.3802639 | AQ57: 48024000000 | AR57: 0.45428661 | AS57: 2.5987666 | AT57: 2.5987666 | AU57: 0.85746725 | AV57: 1.6976182e+12 | AW57: 1.7456422e+12 | AX57: 28.076855 | AY57: 8.4472906 | AZ57: 36.817502 | BA57: 16.513032 | BB57: 0.0031841082 | BC57: 7.8143747
A58: MSFT | B58: 2022 | C58: 233.18163 | D58: 198270000000 | E58: 135620000000 | F58: 72738000000 | G58: 9.65 | H58: 2.54 | I58: 7540000000 | J58: 65149000000 | K58: 89035000000 | L58: -23886000000 | M58: 18135000000 | N58: 13931000000 | O58: 169684000000 | P58: 364840000000 | Q58: 364840000000 | R58: 95082000000 | S58: 3742000000 | T58: 166542000000 | U58: 166542000000 | V58: 61270000000 | W58: 216323000000 | X58: 100239000000 | Y58: 85779000000 | Z58: 2063000000 | AA58: 83716000000 | AB58: 10978000000 | AC58: 0.13113383 | AE58: 0.68401674 | AF58: 0.43263731 | AG58: 0.36686337 | AH58: 0.43675469 | AI58: 0.19936959 | AJ58: 7.4530471e+10 | AK58: 0.34453327 | AL58: 0.24931948 | AM58: 0.27836191 | AN58: 0.36789519 | AO58: 41.579738 | AP58: 1.4531582 | AQ58: 47339000000 | AR58: 0.4722613 | AS58: 1.784607 | AT58: 1.7452515 | AU58: 0.14651564 | AV58: 1.7581895e+12 | AW58: 1.8055285e+12 | AX58: 24.163899 | AY58: 8.8676525 | AZ58: 26.987206 | BA58: 18.012235 | BB58: 0.010892797 | BC58: 10.557033
A59: MSFT | B59: 2023 | C59: 368.87302 | D59: 211915000000 | E59: 146052000000 | F59: 72361000000 | G59: 9.68 | H59: 2.79 | I59: 7472000000 | J59: 59475000000 | K59: 87582000000 | L59: -28107000000 | M59: 19800000000 | N59: 34704000000 | O59: 184257000000 | P59: 411976000000 | Q59: 388408000000 | R59: 104149000000 | S59: 2500000000 | T59: 206223000000 | U59: 186382500000 | V59: 59965000000 | W59: 253460000000 | X59: 105140000000 | Y59: 91279000000 | Z59: 1968000000 | AA59: 89311000000 | AB59: 16950000000 | AC59: 0.18978625 | AE59: 0.68920086 | AF59: 0.43073402 | AG59: 0.34146238 | AH59: 0.38823924 | AI59: 0.18630152 | AJ59: 7.3955501e+10 | AK59: 0.29178372 | AL59: 0.27362806 | AM59: 0.33291299 | AN59: 0.29077746 | AO59: 46.381606 | AP59: 1.460552 | AQ59: 25261000000 | AR59: 0.2402606 | AS59: 1.7691673 | AT59: 1.7451632 | AU59: 0.33321491 | AV59: 2.7562192e+12 | AW59: 2.7814802e+12 | AX59: 38.106717 | AY59: 13.006249 | AZ59: 46.342483 | BA59: 26.455014 | BB59: 0.0075635785 | BC59: 13.365237
A60: MSFT | B60: 2024 | C60: 416.55838 | D60: 245122000000 | E60: 171008000000 | F60: 88136000000 | G60: 11.8 | H60: 3.08 | I60: 7469000000 | J60: 74071000000 | K60: 118548000000 | L60: -44477000000 | M60: 21771000000 | N60: 18315000000 | O60: 159734000000 | P60: 512163000000 | Q60: 462069500000 | R60: 125286000000 | S60: 1246000000 | T60: 268477000000 | U60: 237350000000 | V60: 67127000000 | W60: 320107000000 | X60: 133009000000 | Y60: 110722000000 | Z60: 2935000000 | AA60: 107787000000 | AB60: 19651000000 | AC60: 0.18231327 | AE60: 0.69764444 | AF60: 0.4517016 | AG60: 0.35955973 | AH60: 0.37133347 | AI60: 0.19074187 | AJ60: 9.0535911e+10 | AK60: 0.28283015 | AL60: 0.24701598 | AM60: 0.2939207 | AN60: 0.25002887 | AO60: 37.724702 | AP60: 1.7660256 | AQ60: 48812000000 | AR60: 0.36698269 | AS60: 1.2749549 | AT60: 1.2650097 | AU60: 0.14618553 | AV60: 3.1112745e+12 | AW60: 3.1600865e+12 | AX60: 35.301558 | AY60: 12.692759 | AZ60: 42.003949 | BA60: 23.758441 | BB60: 0.0073939216 | BC60: 11.588607
A61: MSFT | B61: 2025 | C61: 481.47586 | D61: 281724000000 | E61: 193893000000 | F61: 101832000000 | G61: 13.64 | H61: 3.4 | I61: 7465000000 | J61: 71611000000 | K61: 136162000000 | L61: -64551000000 | M61: 24082000000 | N61: 30242000000 | O61: 191131000000 | P61: 619003000000 | Q61: 565583000000 | R61: 141218000000 | S61: 938000000 | T61: 343479000000 | U61: 305978000000 | V61: 60588000000 | W61: 386630000000 | X61: 160165000000 | Y61: 126012000000 | Z61: 2385000000 | AA61: 123627000000 | AB61: 21795000000 | AC61: 0.17629644 | AE61: 0.68823742 | AF61: 0.44728884 | AG61: 0.36146015 | AH61: 0.33280824 | AI61: 0.18004784 | AJ61: 1.0379653e+11 | AK61: 0.26846477 | AL61: 0.23648755 | AM61: 0.33628912 | AN61: 0.17639506 | AO61: 52.83522 | AP61: 2.2473427 | AQ61: 30346000000 | AR61: 0.18946711 | AS61: 1.3534464 | AT61: 1.3468042 | AU61: 0.21415117 | AV61: 3.5942173e+12 | AW61: 3.6245633e+12 | AX61: 35.298817 | AY61: 12.757938 | AZ61: 50.190855 | BA61: 22.630183 | BB61: 0.0070616209 | BC61: 10.464154
A62: NFLX | B62: 2022 | C62: 29.488001 | D62: 31615550000 | E62: 12447265000 | F62: 4491924000 | G62: 0.995 | I62: 4512900000 | J62: 1618528000 | K62: 2026257000 | L62: -407729000 | N62: 5147176000 | O62: 9266473000 | P62: 48594768000 | Q62: 48594768000 | R62: 7930974000 | T62: 20777401000 | U62: 20777401000 | V62: 14353076000 | W62: 35130477000 | X62: 20332955000 | Y62: 5970141000 | Z62: 706212000 | AA62: 5263929000 | AB62: 772005000 | AC62: 0.14665946 | AE62: 0.39370705 | AF62: 0.18883559 | AG62: 0.14207958 | AH62: 0.21619278 | AI62: 0.092436371 | AJ62: 5.0945633e+09 | AK62: 0.14501834 | AN62: 0.69080228 | AO62: 8.4537518 | AP62: 0.14117232 | AQ62: 9205900000 | AR62: 0.4527576 | AS62: 1.1683903 | AT62: 1.1683903 | AU62: 0.64899671 | AV62: 1.330764e+11 | AW62: 1.422823e+11 | AX62: 29.636182 | AY62: 4.2092072 | AZ62: 82.220635 | BA62: 6.9976203 | BC62: 6.4048626
A63: NFLX | B63: 2023 | C63: 48.688 | D63: 33723297000 | E63: 14007929000 | F63: 5407990000 | G63: 1.203 | I63: 4494980000 | J63: 6925749000 | K63: 7274301000 | L63: -348552000 | N63: 7116913000 | O63: 9918133000 | P63: 48731992000 | Q63: 48663380000 | R63: 8860655000 | T63: 20588313000 | U63: 20682857000 | V63: 14543261000 | W63: 35131574000 | X63: 21508387000 | Y63: 6954003000 | Z63: 748598000 | AA63: 6205405000 | AB63: 797415000 | AC63: 0.1285033 | AE63: 0.4153784 | AF63: 0.20620768 | AG63: 0.16036362 | AH63: 0.2614721 | AI63: 0.11113059 | AJ63: 6.0603907e+09 | AK63: 0.17250553 | AN63: 0.7063843 | AO63: 9.2893689 | AP63: 0.50018362 | AQ63: 7426348000 | AR63: 0.34527684 | AS63: 1.1193454 | AT63: 1.1193454 | AU63: 0.80320394 | AV63: 2.1885159e+11 | AW63: 2.2627793e+11 | AX63: 40.472153 | AY63: 6.489626 | AZ63: 31.599699 | BA63: 10.520451 | BC63: 10.629894
A64: NFLX | B64: 2024 | C64: 89.132004 | D64: 39000966000 | E64: 17962502000 | F64: 8711631000 | G64: 1.983 | I64: 4392610000 | J64: 6921826000 | K64: 7361364000 | L64: -439538000 | N64: 7804733000 | O64: 13100379000 | P64: 53630374000 | Q64: 51181183000 | R64: 10755400000 | T64: 24743567000 | U64: 22665940000 | V64: 15582804000 | W64: 40326371000 | X64: 26314821000 | Y64: 10684390000 | Z64: 718733000 | AA64: 9965657000 | AB64: 1254026000 | AC64: 0.12583475 | AE64: 0.46056557 | AF64: 0.27395193 | AG64: 0.22336962 | AH64: 0.38434898 | AI64: 0.1702116 | AJ64: 9.3399224e+09 | AK64: 0.2316083 | AN64: 0.62977193 | AO64: 14.86559 | AP64: 0.47240304 | AQ64: 7778071000 | AR64: 0.29557758 | AS64: 1.2180281 | AT64: 1.2180281 | AU64: 0.72565716 | AV64: 3.9152213e+11 | AW64: 3.993002e+11 | AX64: 44.94806 | AY64: 10.03878 | AZ64: 56.563417 | BA64: 15.173966 | BC64: 15.823189
A65: NFLX | B65: 2025 | C65: 93.760002 | D65: 45183036000 | E65: 21907707000 | F65: 10981201000 | G65: 2.53 | I65: 4343863000 | J65: 9461053000 | K65: 10149273000 | L65: -688220000 | N65: 9033681000 | O65: 13020191000 | P65: 55596993000 | Q65: 54613683500 | R65: 10980930000 | T65: 26615488000 | U65: 25679527500 | V65: 14462836000 | W65: 41078324000 | X65: 30254617000 | Y65: 13499062000 | Z65: 776510000 | AA65: 12722552000 | AB65: 1741351000 | AC65: 0.1368712 | AE65: 0.48486576 | AF65: 0.29876394 | AG65: 0.24303814 | AH65: 0.42762473 | AI65: 0.20107051 | AJ65: 1.1651429e+10 | AK65: 0.28363935 | AN65: 0.54339924 | AO65: 17.384273 | AP65: 0.70174847 | AQ65: 5429155000 | AR65: 0.17944881 | AS65: 1.1857093 | AT65: 1.1857093 | AU65: 0.82266994 | AV65: 4.072806e+11 | AW65: 4.1270976e+11 | AX65: 37.059289 | AY65: 9.0140159 | AZ65: 43.048126 | BA65: 13.641216 | BC65: 15.302391
A66: PDD | B66: 2022 | C66: 81.550003 | D66: 130557589000 | E66: 99095291000 | F66: 31538062000 | G66: 21.92 | I66: 1440322750 | J66: 47872144000 | K66: 48507860000 | L66: -635716000 | N66: 34326192000 | O66: 216617876000 | P66: 237119953000 | Q66: 237119953000 | R66: 116889480000 | T66: 117770911000 | U66: 117770911000 | V66: 16934324000 | W66: 133232417000 | X66: 39205753000 | Y66: 36470669000 | Z66: 51655000 | AA66: 36419014000 | AB66: 4725667000 | AC66: 0.12975824 | AE66: 0.75901594 | AF66: 0.27934545 | AG66: 0.24156437 | AH66: 0.26779161 | AI66: 0.13300467 | AJ66: 3.1738299e+10 | AK66: 0.23821755 | AN66: 0.14379038 | AO66: 706.04335 | AP66: 2.8644698 | AQ66: -17391868000 | AR66: -0.443605 | AS66: 1.8531854 | AT66: 1.8531854 | AU66: 0.29366366 | AV66: 1.1745832e+11 | AW66: 1.0006646e+11 | AX66: 3.7203469 | AY66: 0.89966677 | AZ66: 2.453584 | BA66: 2.5523411 | BC66: 0.99734581
A67: PDD | B67: 2023 | C67: 146.31 | D67: 247639205000 | E67: 155915628000 | F67: 60026544000 | G67: 41.16 | I67: 1459907500 | J67: 93578652000 | K67: 94162531000 | L67: -583879000 | N67: 59794469000 | O67: 294750472000 | P67: 348078120000 | Q67: 292599036500 | R67: 152900901000 | T67: 187241607000 | U67: 152506259000 | V67: 10165901000 | W67: 193121700000 | X67: 73813347000 | Y67: 71925142000 | Z67: 43987000 | AA67: 71881155000 | AB67: 11849904000 | AC67: 0.16485411 | AE67: 0.62960801 | AF67: 0.29044328 | AG67: 0.24239516 | AH67: 0.39360053 | AI67: 0.20514949 | AJ67: 6.0067987e+10 | AK67: 0.31103696 | AN67: 0.05429296 | AO67: 1635.1454 | AP67: 9.2625859 | AQ67: -49628568000 | AR67: -0.67235222 | AS67: 1.9277223 | AT67: 1.9277223 | AU67: 0.39106682 | AV67: 2.1359906e+11 | AW67: 1.6397049e+11 | AX67: 3.5546647 | AY67: 0.86254138 | AZ67: 2.2825619 | BA67: 2.2214207 | BC67: 1.1407671
A68: PDD | B68: 2024 | C68: 96.989998 | D68: 393836097000 | E68: 239935723000 | F68: 112434512000 | G68: 76 | I68: 1479148000 | J68: 120962155000 | K68: 121929292000 | L68: -967137000 | N68: 57768053000 | O68: 415648232000 | P68: 505034316000 | Q68: 426556218000 | R68: 188422853000 | T68: 313313124000 | U68: 250277365500 | V68: 10607140000 | W68: 318622721000 | X68: 135324955000 | Y68: 132684068000 | Z68: 0 | AA68: 132684068000 | AB68: 20266781000 | AC68: 0.15274465 | AE68: 0.60922735 | AF68: 0.33690174 | AG68: 0.28548554 | AH68: 0.44923963 | AI68: 0.26358662 | AJ68: 112417287000 | AK68: 0.35282257 | AN68: 0.033854758 | AP68: 11.495021 | AQ68: -47160913000 | AR68: -0.34850123 | AS68: 2.2059332 | AT68: 2.2059332 | AU68: 0.3065873 | AV68: 1.4346256e+11 | AW68: 9.6301648e+10 | AX68: 1.2761842 | AY68: 0.36426971 | AZ68: 1.186012 | BA68: 0.71163259 | BC68: 0.45788877
A69: PDD | B69: 2025 | C69: 113.39 | D69: 431845713000 | E69: 243043960000 | F69: 97842539000 | G69: 66 | I69: 1482394000 | J69: 105793613000 | K69: 106938690000 | L69: -1145077000 | N69: 108900587000 | O69: 518979892000 | P69: 630044327000 | Q69: 567539321500 | R69: 213737168000 | T69: 413385156000 | U69: 363349140000 | V69: 5378795000 | W69: 413385156000 | X69: 122446654000 | Y69: 119446290000 | Z69: 0 | AA69: 119446290000 | AB69: 21732756000 | AC69: 0.18194584 | AE69: 0.56280276 | AF69: 0.27659483 | AG69: 0.22656828 | AH69: 0.26927968 | AI69: 0.17239782 | AJ69: 97713534000 | AK69: 0.23637408 | AN69: 0.013011582 | AP69: 19.881533 | AQ69: -103521792000 | AR69: -0.84544402 | AS69: 2.4281219 | AT69: 2.4281219 | AU69: 0.50950702 | AV69: 1.6808865e+11 | AW69: 6.4566863e+10 | AX69: 1.7180303 | AY69: 0.38923312 | AZ69: 1.5888356 | BA69: 0.52730606 | BC69: 0.40661512
A70: PEP | B70: 2022 | C70: 162.1813 | D70: 86392000000 | E70: 45816000000 | F70: 8910000000 | G70: 6.42 | H70: 4.525 | I70: 1387000000 | J70: 5604000000 | K70: 10811000000 | L70: -5207000000 | M70: 6172000000 | N70: 4954000000 | O70: 21539000000 | P70: 92187000000 | Q70: 92187000000 | R70: 26785000000 | S70: 5222000000 | T70: 17149000000 | U70: 17149000000 | V70: 39554000000 | W70: 56220000000 | X70: 14924000000 | Y70: 11644000000 | Z70: 939000000 | AA70: 10705000000 | AB70: 1727000000 | AC70: 0.16132648 | AE70: 0.53032688 | AF70: 0.134781 | AG70: 0.10313455 | AH70: 0.51956382 | AI70: 0.096651372 | AJ70: 9.7655144e+09 | AK70: 0.17370179 | AL70: 0.69270483 | AM70: 1.1013562 | AN70: 2.3064902 | AO70: 12.400426 | AP70: 0.27332255 | AQ70: 34600000000 | AR70: 2.3184133 | AS70: 0.80414411 | AT70: 0.60918424 | AU70: 0.18495427 | AV70: 2.2494547e+11 | AW70: 2.5954547e+11 | AX70: 25.261886 | AY70: 2.6037766 | AZ70: 40.140162 | BA70: 17.391146 | BB70: 0.027900873 | BC70: 13.117119
A71: PEP | B71: 2023 | C71: 156.84494 | D71: 91471000000 | E71: 49590000000 | F71: 9074000000 | G71: 6.56 | H71: 4.945 | I71: 1383000000 | J71: 7924000000 | K71: 13442000000 | L71: -5518000000 | M71: 6682000000 | N71: 9711000000 | O71: 26950000000 | P71: 100495000000 | Q71: 96341000000 | R71: 31647000000 | S71: 5334000000 | T71: 18503000000 | U71: 17826000000 | V71: 44661000000 | W71: 62608000000 | X71: 15754000000 | Y71: 12236000000 | Z71: 819000000 | AA71: 11417000000 | AB71: 2262000000 | AC71: 0.1981256 | AE71: 0.54213904 | AF71: 0.13376917 | AG71: 0.09920084 | AH71: 0.50903175 | AI71: 0.094186276 | AJ71: 9.8117351e+09 | AK71: 0.15671696 | AL71: 0.73638968 | AM71: 0.84326098 | AN71: 2.4137167 | AO71: 14.940171 | AP71: 0.30097848 | AQ71: 34950000000 | AR71: 2.2184842 | AS71: 0.85158151 | AT71: 0.68303473 | AU71: 0.30685373 | AV71: 2.1691655e+11 | AW71: 2.5186655e+11 | AX71: 23.90929 | AY71: 2.3714243 | AZ71: 27.374628 | BA71: 15.987467 | BB71: 0.031527954 | BC71: 11.723318
A72: PEP | B72: 2024 | C72: 144.92221 | D72: 91854000000 | E72: 50110000000 | F72: 9578000000 | G72: 6.95 | H72: 5.33 | I72: 1378000000 | J72: 7189000000 | K72: 12507000000 | L72: -5318000000 | M72: 7229000000 | N72: 8505000000 | O72: 25826000000 | P72: 99467000000 | Q72: 99981000000 | R72: 31536000000 | S72: 5306000000 | T72: 18041000000 | U72: 18272000000 | V72: 44948000000 | W72: 62347000000 | X72: 16680000000 | Y72: 12865000000 | Z72: 919000000 | AA72: 11946000000 | AB72: 2320000000 | AC72: 0.19420727 | AE72: 0.54553966 | AF72: 0.14005922 | AG72: 0.10427417 | AH72: 0.52419002 | AI72: 0.095798202 | AJ72: 1.0366524e+10 | AK72: 0.16627141 | AL72: 0.75475047 | AM72: 1.0055641 | AN72: 2.4914362 | AO72: 13.998912 | AP72: 0.27825487 | AQ72: 36443000000 | AR72: 2.1848321 | AS72: 0.81893709 | AT72: 0.65068493 | AU72: 0.26969178 | AV72: 1.9970281e+11 | AW72: 2.3614581e+11 | AX72: 20.852117 | AY72: 2.1741329 | AZ72: 27.778941 | BA72: 14.157422 | BB72: 0.036778351 | BC72: 11.069387
A73: PEP | B73: 2025 | C73: 142.24913 | D73: 93925000000 | E73: 50859000000 | F73: 8240000000 | G73: 6 | H73: 5.624 | I73: 1373000000 | J73: 7672000000 | K73: 12087000000 | L73: -4415000000 | M73: 7638000000 | N73: 9159000000 | O73: 27949000000 | P73: 107399000000 | Q73: 103433000000 | R73: 32764000000 | S73: 5845000000 | T73: 20406000000 | U73: 19223500000 | V73: 49901000000 | W73: 69588000000 | X73: 15543000000 | Y73: 11365000000 | Z73: 1121000000 | AA73: 10244000000 | AB73: 1949000000 | AC73: 0.19025771 | AE73: 0.54148523 | AF73: 0.1210008 | AG73: 0.087729571 | AH73: 0.42864203 | AI73: 0.079665097 | AJ73: 9.2027211e+09 | AK73: 0.13224581 | AL73: 0.92694175 | AM73: 0.9955683 | AN73: 2.4454082 | AO73: 10.138269 | AP73: 0.24221959 | AQ73: 40742000000 | AR73: 2.6212443 | AS73: 0.85303992 | AT73: 0.6746429 | AU73: 0.27954462 | AV73: 1.9530806e+11 | AW73: 2.3605006e+11 | AX73: 23.708188 | AY73: 2.0794044 | AZ73: 25.457254 | BA73: 15.186904 | BB73: 0.03953627 | BC73: 9.5711093
A74: REGN | B74: 2022 | C74: 715.57977 | D74: 12172900000 | E74: 10612500000 | F74: 4338400000 | G74: 38.22 | I74: 113500000 | J74: 3398000000 | K74: 5014900000 | L74: -1616900000 | N74: 3105900000 | O74: 15884100000 | P74: 29214500000 | Q74: 29214500000 | R74: 3141300000 | S74: 2401900000 | T74: 22664000000 | U74: 22664000000 | V74: 2701400000 | W74: 24645400000 | X74: 5259600000 | Y74: 4918200000 | Z74: 59400000 | AA74: 4858800000 | AB74: 520400000 | AC74: 0.10710463 | AE74: 0.87181362 | AF74: 0.40402862 | AG74: 0.35639823 | AH74: 0.19142252 | AI74: 0.1485016 | AJ74: 4.391438e+09 | AK74: 0.17818489 | AN74: 0.11919343 | AO74: 82.79798 | AP74: 1.8564078 | AQ74: -404500000 | AR74: -0.076906989 | AS74: 5.0565371 | AT74: 4.2919174 | AU74: 0.98873078 | AV74: 8.1218304e+10 | AW74: 8.0813804e+10 | AX74: 18.722652 | AY74: 6.6720588 | AZ74: 23.901796 | BA74: 15.36501 | BC74: 3.5835821
A75: REGN | B75: 2023 | C75: 871.09528 | D75: 13117200000 | E75: 11301400000 | F75: 3953600000 | G75: 34.77 | H75: 0 | I75: 113700000 | J75: 3667600000 | K75: 4594000000 | L75: -926400000 | M75: 0 | N75: 2730000000 | O75: 19479200000 | P75: 33080200000 | Q75: 31147350000 | R75: 3423400000 | S75: 2580500000 | T75: 25973100000 | U75: 24318550000 | V75: 2702900000 | W75: 27956000000 | X75: 4693300000 | Y75: 4272300000 | Z75: 73000000 | AA75: 4199300000 | AB75: 245700000 | AC75: 0.058509752 | AE75: 0.86157107 | AF75: 0.32570213 | AG75: 0.30140579 | AH75: 0.16257548 | AI75: 0.12693215 | AJ75: 4.0223288e+09 | AK75: 0.1438807 | AL75: 0 | AM75: 0 | AN75: 0.10406536 | AO75: 58.524658 | AP75: 1.6996559 | AQ75: -27100000 | AR75: -0.0057741887 | AS75: 5.6900158 | AT75: 4.936233 | AU75: 0.79745282 | AV75: 9.9043533e+10 | AW75: 9.9016433e+10 | AX75: 25.053071 | AY75: 7.5506612 | AZ75: 27.004999 | BA75: 21.097401 | BB75: 0 | BC75: 3.813312
A76: REGN | B76: 2024 | C76: 706.49481 | D76: 14202000000 | E76: 12231500000 | F76: 4412600000 | G76: 38.34 | H76: 0 | I76: 115100000 | J76: 3538900000 | K76: 4420500000 | L76: -881600000 | M76: 0 | N76: 2488200000 | O76: 18660900000 | P76: 37759400000 | Q76: 35419800000 | R76: 3944300000 | S76: 3087300000 | T76: 29353600000 | U76: 27663350000 | V76: 2704400000 | W76: 31338000000 | X76: 5318000000 | Y76: 4835100000 | Z76: 55200000 | AA76: 4779900000 | AB76: 367300000 | AC76: 0.076842612 | AE76: 0.86125194 | AF76: 0.34045205 | AG76: 0.31070272 | AH76: 0.15951069 | AI76: 0.12458004 | AJ76: 4.4635583e+09 | AK76: 0.14243277 | AL76: 0 | AM76: 0 | AN76: 0.0921318 | AO76: 87.592391 | AP76: 1.6345585 | AQ76: 216200000 | AR76: 0.040654381 | AS76: 4.7311056 | AT76: 3.9483812 | AU76: 0.63083437 | AV76: 8.1317553e+10 | AW76: 8.1533753e+10 | AX76: 18.427095 | AY76: 5.7257818 | AZ76: 22.9782 | BA76: 15.331657 | BB76: 0 | BC76: 2.7702753
A77: REGN | B77: 2025 | C77: 769.79285 | D77: 14342900000 | E77: 12242200000 | F77: 4504900000 | G77: 41.48 | H77: 3.52 | I77: 108600000 | J77: 3765200000 | K77: 4978900000 | L77: -1213700000 | M77: 370300000 | N77: 3118100000 | O77: 18021900000 | P77: 40558700000 | Q77: 39159050000 | R77: 4368400000 | S77: 3200800000 | T77: 31256900000 | U77: 30305250000 | V77: 2705900000 | W77: 33242800000 | X77: 5818200000 | Y77: 5274500000 | Z77: 43800000 | AA77: 5230700000 | AB77: 725800000 | AC77: 0.13875772 | AE77: 0.85353729 | AF77: 0.36774293 | AG77: 0.31408571 | AH77: 0.14865081 | AI77: 0.1150411 | AJ77: 4.5426224e+09 | AK77: 0.13664981 | AL77: 0.082199383 | AM77: 0.098348029 | AN77: 0.086569685 | AO77: 120.42237 | AP77: 1.8400163 | AQ77: -412200000 | AR77: -0.070846654 | AS77: 4.1255151 | AT77: 3.3927983 | AU77: 0.71378537 | AV77: 8.3599503e+10 | AW77: 8.3187303e+10 | AX77: 18.558169 | AY77: 5.8286332 | AZ77: 22.203204 | BA77: 14.297773 | BB77: 0.0045726588 | BC77: 2.6745936
A78: TMUS | B78: 2022 | C78: 133.88115 | D78: 79571000000 | E78: 43365000000 | F78: 2590000000 | G78: 2.06 | H78: 0 | I78: 1255376769 | J78: -520000000 | K78: 16781000000 | L78: -17301000000 | M78: 0 | N78: 4507000000 | O78: 19067000000 | P78: 211338000000 | Q78: 211338000000 | R78: 24742000000 | S78: 1884000000 | T78: 69656000000 | U78: 69656000000 | V78: 111792000000 | W78: 141616000000 | X78: 20161000000 | Y78: 6510000000 | Z78: 3364000000 | AA78: 3146000000 | AB78: 556000000 | AC78: 0.17673236 | AE78: 0.54498498 | AF78: 0.081813726 | AG78: 0.032549547 | AH78: 0.037182727 | AI78: 0.01225525 | AJ78: 5.3594723e+09 | AK78: 0.037845105 | AL78: 0 | AM78: 0 | AN78: 1.6049156 | AO78: 1.9351962 | AP78: 0.15010913 | AQ78: 107285000000 | AR78: 5.3214126 | AS78: 0.77063293 | AT78: 0.69448711 | AU78: 0.18215989 | AV78: 1.6807128e+11 | AW78: 2.7535628e+11 | AX78: 64.990849 | AY78: 2.1122178 | AZ78: -323.21401 | BA78: 13.657868 | BB78: 0 | BC78: 2.4128759
A79: TMUS | B79: 2023 | C79: 153.99193 | D79: 78558000000 | E79: 48370000000 | F79: 8317000000 | G79: 6.93 | H79: 0.65 | I79: 1200286264 | J79: 7748000000 | K79: 18559000000 | L79: -10811000000 | M79: 747000000 | N79: 5135000000 | O79: 19015000000 | P79: 207682000000 | Q79: 209510000000 | R79: 20928000000 | S79: 1678000000 | T79: 64715000000 | U79: 67185500000 | V79: 113086000000 | W79: 139733000000 | X79: 27152000000 | Y79: 14334000000 | Z79: 3335000000 | AA79: 10999000000 | AB79: 2682000000 | AC79: 0.24384035 | AE79: 0.61572341 | AF79: 0.18246391 | AG79: 0.10587082 | AH79: 0.12379159 | AI79: 0.039697389 | AJ79: 1.0838792e+10 | AK79: 0.077567879 | AL79: 0.089816039 | AM79: 0.096411977 | AN79: 1.7474465 | AO79: 4.298051 | AP79: 0.16411404 | AQ79: 107951000000 | AR79: 3.9758029 | AS79: 0.90859136 | AT79: 0.8284117 | AU79: 0.24536506 | AV79: 1.848344e+11 | AW79: 2.927854e+11 | AX79: 22.221057 | AY79: 2.3528399 | AZ79: 23.855756 | BA79: 10.783198 | BB79: 0.0042210005 | BC79: 2.8561291
A80: TMUS | B80: 2024 | C80: 215.13181 | D80: 81400000000 | E80: 51747000000 | F80: 11339000000 | G80: 9.66 | H80: 2.83 | I80: 1173213898 | J80: 9982000000 | K80: 22293000000 | L80: -12311000000 | M80: 3300000000 | N80: 5409000000 | O80: 18404000000 | P80: 208035000000 | Q80: 207858500000 | R80: 20174000000 | S80: 1607000000 | T80: 61741000000 | U80: 63228000000 | V80: 113944000000 | W80: 140006000000 | X80: 31042000000 | Y80: 18123000000 | Z80: 3411000000 | AA80: 14712000000 | AB80: 3373000000 | AC80: 0.22926862 | AE80: 0.63571253 | AF80: 0.22264128 | AG80: 0.13929975 | AH80: 0.1793351 | AI80: 0.054551534 | AJ80: 1.3967965e+10 | AK80: 0.099766901 | AL80: 0.29103096 | AM80: 0.33059507 | AN80: 1.8455159 | AO80: 5.3131047 | AP80: 0.19564874 | AQ80: 108535000000 | AR80: 3.496392 | AS80: 0.91226331 | AT80: 0.83260632 | AU80: 0.26811738 | AV80: 2.5239562e+11 | AW80: 3.6093062e+11 | AX80: 22.270373 | AY80: 3.1006833 | AZ80: 25.285076 | BA80: 11.62717 | BB80: 0.013154726 | BC80: 4.0879743
A81: TMUS | B81: 2025 | C81: 200.97791 | D81: 88309000000 | E81: 55535000000 | F81: 10992000000 | G81: 9.72 | H81: 3.66 | I81: 1131076251 | J81: 15427000000 | K81: 27950000000 | L81: -12523000000 | M81: 4121000000 | N81: 5598000000 | O81: 24461000000 | P81: 219237000000 | Q81: 213636000000 | R81: 24500000000 | S81: 2405000000 | T81: 59203000000 | U81: 60472000000 | V81: 122269000000 | W81: 145485000000 | X81: 31563000000 | Y81: 18055000000 | Z81: 3774000000 | AA81: 14281000000 | AB81: 3289000000 | AC81: 0.230306 | AE81: 0.62887135 | AF81: 0.20445255 | AG81: 0.12447202 | AH81: 0.18177008 | AI81: 0.051452002 | AJ81: 1.3896825e+10 | AK81: 0.095520673 | AL81: 0.37490902 | AM81: 0.26712906 | AN81: 2.0652501 | AO81: 4.7840488 | AP81: 0.22859433 | AQ81: 116671000000 | AR81: 3.6964484 | AS81: 0.99840816 | AT81: 0.9002449 | AU81: 0.2284898 | AV81: 2.2732134e+11 | AW81: 3.4399234e+11 | AX81: 20.676739 | AY81: 2.5741582 | AZ81: 14.735291 | BA81: 10.898594 | BB81: 0.018210957 | BC81: 3.8396928
A82: TSLA | B82: 2022 | C82: 123.18 | D82: 81462000000 | E82: 20853000000 | F82: 12583000000 | G82: 3.62 | I82: 3475000000 | J82: 7552000000 | K82: 14724000000 | L82: -7172000000 | N82: 16253000000 | O82: 40917000000 | P82: 82338000000 | Q82: 82338000000 | R82: 26709000000 | S82: 12839000000 | T82: 44704000000 | U82: 44704000000 | V82: 5748000000 | W82: 46749000000 | X82: 17657000000 | Y82: 13910000000 | Z82: 191000000 | AA82: 13719000000 | AB82: 1132000000 | AC82: 0.082513303 | AE82: 0.25598439 | AF82: 0.17075446 | AG82: 0.15446466 | AH82: 0.28147369 | AI82: 0.1528213 | AJ82: 1.276224e+10 | AK82: 0.27299493 | AN82: 0.1285791 | AO82: 72.827225 | AP82: 2.5615866 | AQ82: -10505000000 | AR82: -0.59494818 | AS82: 1.5319555 | AT82: 1.0512561 | AU82: 0.60852147 | AV82: 4.280505e+11 | AW82: 4.175455e+11 | AX82: 34.027624 | AY82: 5.2546034 | AZ82: 56.680416 | BA82: 23.64759 | BC82: 9.575217
A83: TSLA | B83: 2023 | C83: 248.48 | D83: 96773000000 | E83: 17660000000 | F83: 14999000000 | G83: 4.31 | I83: 3482750000 | J83: 4357000000 | K83: 13256000000 | L83: -8899000000 | N83: 16398000000 | O83: 49616000000 | P83: 106618000000 | Q83: 94478000000 | R83: 28748000000 | S83: 13626000000 | T83: 62634000000 | U83: 53669000000 | V83: 9573000000 | W83: 67291000000 | X83: 14796000000 | Y83: 10129000000 | Z83: 156000000 | AA83: 9973000000 | AB83: -5001000000 | AC83: -0.50145393 | AE83: 0.18248892 | AF83: 0.10466762 | AG83: 0.15499158 | AH83: 0.27947232 | AI83: 0.15875654 | AJ83: 1.5208227e+10 | AK83: 0.22600685 | AN83: 0.15284031 | AO83: 64.929487 | AP83: 1.3847279 | AQ83: -6825000000 | AR83: -0.46127332 | AS83: 1.725894 | AT83: 1.2519132 | AU83: 0.5704049 | AV83: 8.6539371e+11 | AW83: 8.5856871e+11 | AX83: 57.651971 | AY83: 8.9425119 | AZ83: 198.62146 | BA83: 58.027082 | BC83: 13.816676
A84: TSLA | B84: 2024 | C84: 403.84 | D84: 97690000000 | E84: 17450000000 | F84: 7130000000 | G84: 2.04 | I84: 3216000000 | J84: 3581000000 | K84: 14923000000 | L84: -11342000000 | N84: 16139000000 | O84: 58360000000 | P84: 122070000000 | Q84: 114344000000 | R84: 28821000000 | S84: 12017000000 | T84: 72913000000 | U84: 67773500000 | V84: 13623000000 | W84: 80791000000 | X84: 14708000000 | Y84: 9340000000 | Z84: 350000000 | AA84: 8990000000 | AB84: 1837000000 | AC84: 0.20433815 | AE84: 0.17862627 | AF84: 0.095608558 | AG84: 0.072985976 | AH84: 0.10520336 | AI84: 0.062355699 | AJ84: 7.4314816e+09 | AK84: 0.091984028 | AN84: 0.18683911 | AO84: 26.685714 | AP84: 1.0954269 | AQ84: -2516000000 | AR84: -0.17106337 | AS84: 2.0249124 | AT84: 1.6079595 | AU84: 0.55997363 | AV84: 1.2987494e+12 | AW84: 1.2962334e+12 | AX84: 197.96078 | AY84: 13.2946 | AZ84: 362.67786 | BA84: 88.131182 | BC84: 17.812316
A85: TSLA | B85: 2025 | C85: 449.72 | D85: 94827000000 | E85: 17094000000 | F85: 3794000000 | G85: 1.08 | I85: 3526250000 | J85: 6220000000 | K85: 14747000000 | L85: -8527000000 | N85: 16513000000 | O85: 68642000000 | P85: 137806000000 | Q85: 129938000000 | R85: 31714000000 | S85: 12392000000 | T85: 82137000000 | U85: 77525000000 | V85: 14719000000 | W85: 90290000000 | X85: 11764000000 | Y85: 5616000000 | Z85: 338000000 | AA85: 5278000000 | AB85: 1423000000 | AC85: 0.2696097 | AE85: 0.18026511 | AF85: 0.059223639 | AG85: 0.040009702 | AH85: 0.048939052 | AI85: 0.029198541 | AJ85: 4.1018719e+09 | AK85: 0.045429969 | AN85: 0.1792006 | AO85: 16.615385 | AP85: 1.0019023 | AQ85: -1794000000 | AR85: -0.15249915 | AS85: 2.1644069 | AT85: 1.7736646 | AU85: 0.52068487 | AV85: 1.5858252e+12 | AW85: 1.5840312e+12 | AX85: 416.40741 | AY85: 16.72335 | AZ85: 254.95581 | BA85: 134.65073 | BC85: 19.307074
A86: VRTX | B86: 2022 | C86: 288.78 | D86: 8930700000 | E86: 7850400000 | F86: 3322000000 | G86: 12.82 | I86: 259100000 | J86: 3925200000 | K86: 4129900000 | L86: -204700000 | N86: 10504000000 | O86: 13234800000 | P86: 18150900000 | Q86: 18150900000 | R86: 2742100000 | S86: 460600000 | T86: 13912700000 | U86: 13912700000 | V86: 899700000 | W86: 13912700000 | X86: 4435500000 | Y86: 4287200000 | Z86: 54800000 | AA86: 4232400000 | AB86: 910400000 | AC86: 0.21510254 | AD86: missing prev balance column | AE86: 0.87903524 | AF86: 0.48005196 | AG86: 0.37197532 | AH86: 0.23877464 | AI86: 0.18302123 | AJ86: 3.3650124e+09 | AK86: 0.24186624 | AN86: 0.064667534 | AO86: 78.233577 | AP86: 4.5903079 | AQ86: -9604300000 | AR86: -2.1653252 | AS86: 4.8265198 | AT86: 4.6585464 | AU86: 3.8306407 | AV86: 7.4822898e+10 | AW86: 6.5218598e+10 | AX86: 22.525741 | AY86: 8.3781672 | AZ86: 19.062187 | BA86: 14.703776 | BC86: 5.3780285
A87: VRTX | B87: 2023 | C87: 406.89001 | D87: 9869200000 | E87: 8607000000 | F87: 3619600000 | G87: 13.89 | I87: 260500000 | J87: 3278900000 | K87: 3537300000 | L87: -258400000 | N87: 10369100000 | O87: 14144200000 | P87: 22730200000 | Q87: 20440550000 | R87: 3547400000 | S87: 738800000 | T87: 17580400000 | U87: 15746550000 | V87: 808400000 | W87: 17580400000 | X87: 4605200000 | Y87: 4423900000 | Z87: 44100000 | AA87: 4379800000 | AB87: 760200000 | AC87: 0.17356957 | AE87: 0.87210716 | AF87: 0.44825315 | AG87: 0.36675718 | AH87: 0.22986622 | AI87: 0.17707938 | AJ87: 3.6560456e+09 | AK87: 0.20796146 | AN87: 0.045983027 | AO87: 100.31519 | AP87: 4.3756804 | AQ87: -9560700000 | AR87: -2.0760662 | AS87: 3.9872019 | AT87: 3.7789367 | AU87: 2.923014 | AV87: 1.0599485e+11 | AW87: 9.6434149e+10 | AX87: 29.293738 | AY87: 10.739964 | AZ87: 32.326344 | BA87: 20.940274 | BC87: 6.0291489
A88: VRTX | B88: 2024 | C88: 402.70001 | D88: 11020100000 | E88: 9489600000 | F88: -535600000 | G88: -2.08 | I88: 257900000 | J88: -978000000 | K88: -492600000 | L88: -485400000 | N88: 4569600000 | O88: 9596400000 | P88: 22533200000 | Q88: 22631700000 | R88: 3564600000 | S88: 1205400000 | T88: 16409600000 | U88: 16995000000 | V88: 1744300000 | W88: 16409600000 | X88: 486300000 | Y88: 279100000 | Z88: 30600000 | AA88: 248500000 | AB88: 784100000 | AC88: 3.155332 | AE88: 0.86111741 | AF88: 0.025326449 | AG88: -0.0486021 | AH88: -0.031515152 | AI88: -0.02366592 | AJ88: -6.0155316e+08 | AK88: -0.036658612 | AN88: 0.10629753 | AO88: 9.120915 | AP88: -0.28240555 | AQ88: -2825300000 | AR88: -5.8097882 | AS88: 2.6921394 | AT88: 2.3539808 | AU88: 1.2819391 | AV88: 1.0385633e+11 | AW88: 1.0103103e+11 | AX88: -193.60578 | AY88: 9.4242641 | AZ88: -106.19257 | BA88: 207.75454 | BC88: 6.3289985
A89: VRTX | B89: 2025 | C89: 453.35999 | D89: 12001300000 | E89: 10350000000 | F89: 3953200000 | G89: 15.32 | I89: 258000000 | J89: 3193800000 | K89: 3631400000 | L89: -437600000 | N89: 5084800000 | O89: 11201000000 | P89: 25643000000 | Q89: 24088100000 | R89: 3861200000 | S89: 1686800000 | T89: 18665800000 | U89: 17537700000 | V89: 2030500000 | W89: 18665800000 | X89: 4866300000 | Y89: 4656500000 | Z89: 13300000 | AA89: 4643200000 | AB89: 690000000 | AC89: 0.14860441 | AE89: 0.86240657 | AF89: 0.38799963 | AG89: 0.32939765 | AH89: 0.22541154 | AI89: 0.16411423 | AJ89: 3.9645236e+09 | AK89: 0.21239505 | AN89: 0.10878184 | AO89: 350.11278 | AP89: 1.7884265 | AQ89: -3054300000 | AR89: -0.62764318 | AS89: 2.9009116 | AT89: 2.4640526 | AU89: 1.3168963 | AV89: 1.1696688e+11 | AW89: 1.1391258e+11 | AX89: 29.592688 | AY89: 9.7461838 | AZ89: 36.623106 | BA89: 23.408457 | BC89: 6.2663736

Sheet Market Info
A1: Ticker | B1: Name | C1: Yahoo Sector | D1: Yahoo Industry
A2: AAPL | B2: Apple Inc. | C2: Technology | D2: Consumer Electronics
A3: MSFT | B3: Microsoft Corporation | C3: Technology | D3: Software - Infrastructure
A4: AMD | B4: Advanced Micro Devices, Inc. | C4: Technology | D4: Semiconductors
A5: ASML | B5: ASML Holding N.V. - New York Re | C5: Technology | D5: Semiconductor Equipment & Materials
A6: AMZN | B6: Amazon.com, Inc. | C6: Consumer Cyclical | D6: Internet Retail
A7: TSLA | B7: Tesla, Inc. | C7: Consumer Cyclical | D7: Auto Manufacturers
A8: MELI | B8: MercadoLibre, Inc. | C8: Consumer Cyclical | D8: Internet Retail
A9: PDD | B9: PDD Holdings Inc. | C9: Consumer Cyclical | D9: Internet Retail
A10: GOOGL | B10: Alphabet Inc. | C10: Communication Services | D10: Internet Content & Information
A11: META | B11: Meta Platforms, Inc. | C11: Communication Services | D11: Internet Content & Information
A12: NFLX | B12: Netflix, Inc. | C12: Communication Services | D12: Entertainment
... A23: CCEP | B23: Coca-Cola Europacific Partners | C23: Consumer Defensive | D23: Beverages - Non-Alcoholic

Sheet Summary (up to 2024)
A1: Ticker | B1: Start Year | C1: End Year (Base) | D1: Revenue CAGR | E1: Net Income CAGR | F1: EPS CAGR | G1: DPS CAGR | H1: FCF CAGR | I1: Average Gross Margin | J1: Average Operating Margin | K1: Average Net Profit Margin | L1: Average ROE | M1: Average ROA | N1: Average ROIC | O1: Average Tax Rate | P1: Average Payout NI | Q1: Average Payout FCF | R1: Average D/E | S1: Average Interest Coverage | T1: Average OCF / Total Debt | U1: Average Net Debt / EBITDA | V1: Average Current Ratio | W1: Average Quick Ratio | X1: Average Cash Ratio | Y1: Latest Price | Z1: Latest DPS | AA1: Latest EPS | AB1: Latest FCF | AC1: Latest Revenue | AD1: Latest EBITDA | AE1: Latest Total Debt | AF1: Latest Cash | AG1: Latest Equity | AH1: Latest Diluted Shares | AI1: Name | AJ1: Yahoo Sector | AK1: Yahoo Industry | AL1: Market Cap (2024) | AM1: EV (2024) | AN1: P/E (2024) | AO1: P/S (2024) | AP1: P/FCF (2024) | AQ1: EV/EBITDA (2024) | AR1: Dividend Yield (2024) | AS1: P/B (2024) | AT1: PEG (2024)
A2: AAPL | B2: 2022 | C2: 2024 | D2: -0.0041842118 | E2: -0.0308714 | F2: -0.0024580127 | G2: 0.043030243 | H2: -0.011897448 | I2: 0.44549037 | J2: 0.30540127 | K2: 0.24862377 | L2: 1.754403 | M2: 0.27307258 | N2: 0.57354678 | O2: 0.18338274 | P2: 0.15537604 | Q2: 0.14135275 | R2: 2.0914403 | S2: 33.713456 | T2: 1.0087168 | U2: 0.68264798 | V2: 0.91156009 | W2: 0.87256146 | X2: 0.17651105 | Y2: 248.83022 | Z2: 0.99 | AA2: 6.08 | AB2: 108807000000 | AC2: 391035000000 | AD2: 134661000000 | AE2: 106629000000 | AF2: 29943000000 | AG2: 56950000000 | AH2: 15408095000 | AI2: Apple Inc. | AJ2: Technology | AK2: Consumer Electronics | AL2: 3.8339996e+12 | AM2: 3.9106856e+12 | AN2: 40.926022 | AO2: 9.8047479 | AP2: 35.2367 | AQ2: 29.040967 | AR2: 0.0039786165 | AS2: 67.322205
A3: AMD | B3: 2022 | C3: 2024 | D3: 0.045245642 | E3: 0.11498064 | F3: 0.091089451 | H3: -0.1213245 | I3: 0.46798796 | J3: 0.053656234 | K3: 0.052408602 | L3: 0.02282442 | M3: 0.018692546 | N3: 0.023450175 | O3: -0.20491301 | R3: 0.048148327 | S3: 14.23854 | T3: 1.058361 | U3: -0.297346 | V3: 2.4937349 | W3: 1.8170393 | X3: 0.62241566 | Y3: 120.79 | AA3: 1 | AB3: 2405000000 | AC3: 25785000000 | AD3: 5145000000 | AE3: 2212000000 | AF3: 3787000000 | AG3: 57568000000 | AH3: 1637000000 | AI3: Advanced Micro Devices, Inc. | AJ3: Technology | AK3: Semiconductors | AL3: 1.9773323e+11 | AM3: 1.9615823e+11 | AN3: 120.79 | AO3: 7.6685372 | AP3: 82.21756 | AQ3: 38.125993 | AS3: 3.4347768 | AT3: 13.260592
A4: AMGN | B4: 2022 | C4: 2024 | D4: 0.12683809 | E4: -0.20991338 | F4: -0.20988769 | G4: 0.076937238 | H4: 0.087728414 | I4: 0.6907193 | J4: 0.31513483 | K4: 0.20318365 | L4: 1.2743785 | M4: 0.075560042 | N4: 0.13905235 | O4: 0.12185589 | P4: 0.83337074 | Q4: 0.52054059 | R4: 10.410626 | S4: 4.1392603 | T4: 0.19063221 | U4: 3.2675958 | V4: 1.4400839 | W4: 1.0618381 | X4: 0.5332339 | Y4: 248.80763 | Z4: 9 | AA4: 7.56 | AB4: 10394000000 | AC4: 33424000000 | AD4: 13356000000 | AE4: 60099000000 | AF4: 11973000000 | AG4: 5877000000 | AH4: 541000000 | AI4: Amgen Inc. | AJ4: Healthcare | AK4: Drug Manufacturers - General | AL4: 1.3460493e+11 | AM4: 1.8273093e+11 | AN4: 32.911062 | AO4: 4.0271939 | AP4: 12.950253 | AQ4: 13.681561 | AR4: 0.036172524 | AS4: 22.90368
A5: AMZN | B5: 2022 | C5: 2024 | D5: 0.11409444 | I5: 0.46547274 | J5: 0.058418965 | K5: 0.046836038 | L5: 0.133052 | M5: 0.052781003 | N5: 0.092057197 | R5: 0.69630912 | S5: 13.604337 | T5: 0.61509641 | U5: 1.1217815 | V5: 1.0178185 | W5: 0.81311327 | X5: 0.41027593 | Y5: 219.39 | AA5: 5.53 | AB5: 32878000000 | AC5: 637959000000 | AD5: 123815000000 | AE5: 130900000000 | AF5: 78779000000 | AG5: 285970000000 | AH5: 10721000000 | AI5: Amazon.com, Inc. | AJ5: Consumer Cyclical | AK5: Internet Retail | AL5: 2.3520802e+12 | AM5: 2.4042012e+12 | AN5: 39.672694 | AO5: 3.686883 | AP5: 71.539637 | AQ5: 19.417689 | AS5: 8.2249193
A6: ASML | B6: 2022 | C6: 2024 | D6: 0.15534865 | E6: 0.16028173 | F6: 0.094194671 | G6: 0.0059365541 | H6: 0.1257273 | I6: 0.51035387 | J6: 0.32287599 | K6: 0.27265803 | L6: 0.60560533 | M6: 0.17718178 | N6: 0.39239954 | O6: 0.16471819 | P6: 0.35955572 | Q6: 0.45012258 | R6: 0.36051344 | S6: 74.76103 | U6: -0.48550091 | V6: 1.4381223 | W6: 0.94233602 | X6: 0.48990985 | Y6: 684.12122 | Z6: 6.713 | AA6: 19.24 | AB6: 9083100000 | AC6: 28262900000 | AD6: 10123600000 | AE6: 4687600000 | AF6: 12735900000 | AG6: 18476800000 | AH6: 393600000 | AI6: ASML Holding N.V. - New York Re | AJ6: Technology | AK6: Semiconductor Equipment & Materials | AL6: 2.6927011e+11 | AM6: 2.6122181e+11 | AN6: 35.557236 | AO6: 9.5273348 | AP6: 29.645177 | AQ6: 25.803253 | AR6: 0.0098125885 | AS6: 14.573417 | AT6: 3.774867
A7: CCEP | B7: 2022 | C7: 2024 | D7: 0.086288679 | E7: -0.03029989 | F7: -0.032441106 | G7: 0.11934855 | H7: -0.045473598 | I7: 0.35978317 | J7: 0.11937705 | K7: 0.082546587 | L7: 0.19705727 | M7: 0.051809578 | N7: 0.089696584 | O7: 0.23977298 | P7: 0.55053722 | Q7: 0.39273814 | R7: 1.4541571 | S7: 12.226337 | T7: 0.2542041 | U7: 3.2948108 | V7: 0.87227202 | W7: 0.68149043 | X7: 0.19214536 | Y7: 74.045609 | Z7: 2.13 | AA7: 3.08 | AB7: 2122000000 | AC7: 20438000000 | AD7: 3111000000 | AE7: 11331000000 | AF7: 1563000000 | AG7: 8489000000 | AH7: 461000000 | AI7: Coca-Cola Europacific Partners | AJ7: Consumer Defensive | AK7: Beverages - Non-Alcoholic | AL7: 3.4135026e+10 | AM7: 4.3903026e+10 | AN7: 24.040782 | AO7: 1.6701745 | AP7: 16.086251 | AQ7: 14.112191 | AR7: 0.028766054 | AS7: 4.0210891
A8: CHTR | B8: 2022 | C8: 2024 | D8: 0.0097906558 | E8: 0.0027657105 | F8: 0.066586014 | H8: -0.24524693 | I8: 0.55064284 | J8: 0.22470055 | K8: 0.089766468 | L8: 0.46218268 | M8: 0.033474758 | N8: 0.087348908 | O8: 0.22279632 | R8: 8.56841 | S8: 2.4645523 | T8: 0.15019082 | U8: 4.5960948 | V8: 0.31984208 | W8: 0.31984208 | X8: 0.047050311 | Y8: 342.76999 | AA8: 34.97 | AB8: 3161000000 | AC8: 55085000000 | AD8: 21404000000 | AE8: 95763000000 | AF8: 459000000 | AG8: 15587000000 | AH8: 145363771 | AI8: Charter Communications, Inc. | AJ8: Communication Services | AK8: Telecom Services | AL8: 4.9826338e+10 | AM8: 1.4513034e+11 | AN8: 9.8018298 | AO8: 0.9045355 | AP8: 15.76284 | AQ8: 6.7805241 | AS8: 3.1966599 | AT8: 1.4720553
A9: COST | B9: 2022 | C9: 2024 | D9: 0.058851039 | E9: 0.12276853 | F9: 0.12261925 | G9: 0.13551675 | H9: 0.37603016 | I9: 0.12340579 | J9: 0.036623873 | K9: 0.026890298 | L9: 0.28704788 | M9: 0.097237582 | N9: 0.22668324 | O9: 0.24926702 | P9: 0.20832217 | Q9: 0.26735491 | R9: 0.37941759 | S9: 54.43238 | T9: 1.1505591 | U9: -0.23656524 | V9: 1.0186124 | W9: 0.49153041 | X9: 0.3353779 | Y9: 908.95111 | Z9: 4.5 | AA9: 16.56 | AB9: 6629000000 | AC9: 254453000000 | AD9: 12146000000 | AE9: 8169000000 | AF9: 9906000000 | AG9: 23622000000 | AH9: 444759000 | AI9: Costco Wholesale Corporation | AJ9: Consumer Defensive | AK9: Discount Stores | AL9: 4.0426419e+11 | AM9: 4.0252719e+11 | AN9: 54.888352 | AO9: 1.5887578 | AP9: 60.984189 | AQ9: 33.14072 | AR9: 0.0049507613 | AS9: 17.113885 | AT9: 4.4763244
A10: GILD | B10: 2022 | C10: 2024 | D10: 0.026641915 | E10: -0.6766896 | F10: -0.67689691 | G10: 0.027031899 | H10: 0.11131417 | I10: 0.77853554 | J10: 0.19770884 | K10: 0.13131095 | L10: 0.16534604 | M10: 0.057014493 | N10: 0.090900631 | O10: 0.23408544 | P10: 3.2141944 | Q10: 0.44599598 | R10: 1.221344 | S10: 5.7301051 | T10: 0.36178487 | U10: 2.603518 | V10: 1.4361286 | W10: 1.2911376 | X10: 0.61777887 | Y10: 89.350464 | Z10: 3.08 | AA10: 0.38 | AB10: 10305000000 | AC10: 28754000000 | AD10: 4434000000 | AE10: 26711000000 | AF10: 9991000000 | AG10: 19330000000 | AH10: 1255000000 | AI10: Gilead Sciences, Inc. | AJ10: Healthcare | AK10: Drug Manufacturers - General | AL10: 1.1213483e+11 | AM10: 1.2885483e+11 | AN10: 235.1328 | AO10: 3.8997994 | AP10: 10.881595 | AQ10: 29.06063 | AR10: 0.034471002 | AS10: 5.8010777
A11: GOOGL | B11: 2022 | C11: 2024 | D11: 0.1124432 | E11: 0.29205743 | F11: 0.32783956 | H11: 0.10114996 | I11: 0.56734975 | J11: 0.29212666 | K11: 0.24604709 | L11: 0.2789251 | M11: 0.19709629 | N11: 0.257855 | O11: 0.15422962 | P11: 0.024514406 | Q11: 0.03373005 | R11: 0.093671561 | S11: 309.39039 | T11: 4.1283222 | U11: 0.038790181 | V11: 2.1038369 | W11: 2.0701295 | X11: 0.29098377 | Y11: 188.42886 | Z11: 0.6 | AA11: 8.04 | AB11: 72764000000 | AC11: 350018000000 | AD11: 135394000000 | AE11: 22574000000 | AF11: 23466000000 | AG11: 325084000000 | AH11: 12447000000 | AI11: Alphabet Inc. | AJ11: Communication Services | AK11: Internet Content & Information | AL11: 2.3453741e+12 | AM11: 2.3444821e+12 | AN11: 23.436426 | AO11: 6.7007241 | AP11: 32.232616 | AQ11: 17.315997 | AR11: 0.0031842255 | AS11: 7.2146709 | AT11: 0.71487486
A12: KDP | B12: 2022 | C12: 2024 | D12: 0.045013771 | E12: 0.0017394343 | F12: 0.01960971 | G12: 0.070181273 | H12: -0.19395086 | I12: 0.5406598 | J12: 0.18791291 | K12: 0.11441707 | L12: 0.066916081 | M12: 0.03231995 | N12: 0.056868606 | O12: 0.20708717 | P12: 0.68940245 | Q12: 0.83372351 | R12: 0.58651039 | S12: 4.5476896 | T12: 0.14706007 | U12: 4.0976496 | V12: 0.44793609 | W12: 0.29746381 | X12: 0.053085336 | Y12: 30.645254 | Z12: 0.875 | AA12: 1.05 | AB12: 1597000000 | AC12: 15351000000 | AD12: 3382000000 | AE12: 15554000000 | AF12: 510000000 | AG12: 24243000000 | AH12: 1368300000 | AI12: Keurig Dr Pepper Inc. | AJ12: Consumer Defensive | AK12: Beverages - Non-Alcoholic | AL12: 4.1931901e+10 | AM12: 5.6975901e+10 | AN12: 29.185956 | AO12: 2.731542 | AP12: 26.25667 | AQ12: 16.846807 | AR12: 0.028552545 | AS12: 1.7296498 | AT12: 14.883421
A13: MDLZ | B13: 2022 | C13: 2024 | D13: 0.075641234 | E13: 0.30272498 | F13: 0.32094586 | G13: 0.10348859 | H13: 0.083305574 | I13: 0.37751845 | J13: 0.16012077 | K13: 0.11682901 | L13: 0.14918814 | M13: 0.057893268 | N13: 0.089718725 | O13: 0.25466313 | P13: 0.55853028 | Q13: 0.64255133 | R13: 0.75277456 | S13: 11.185923 | T13: 0.22342609 | U13: 3.0000159 | V13: 0.63201098 | W13: 0.43601847 | X13: 0.093080921 | Y13: 57.403831 | Z13: 1.79 | AA13: 3.42 | AB13: 3523000000 | AC13: 36441000000 | AD13: 8071000000 | AE13: 18372000000 | AF13: 1351000000 | AG13: 26932000000 | AH13: 1347000000 | AI13: Mondelez International, Inc. | AJ13: Consumer Defensive | AK13: Confectioners | AL13: 7.7322961e+10 | AM13: 9.4343961e+10 | AN13: 16.784746 | AO13: 2.1218672 | AP13: 21.948045 | AQ13: 11.689253 | AR13: 0.031182588 | AS13: 2.8710441 | AT13: 0.52297749
A14: MELI | B14: 2022 | C14: 2024 | D14: 0.38829589 | E14: 0.99116305 | F14: 0.98868784 | H14: 0.68530159 | I14: 0.48184924 | J14: 0.10806375 | K14: 0.067341029 | L14: 0.39393255 | M14: 0.062447725 | N14: 0.14630843 | O14: 0.32088863 | P14: 0 | Q14: 0 | R14: 2.0914155 | S14: 10.814153 | T14: 0.88758641 | U14: 1.7345658 | V14: 1.2528346 | W14: 1.2339306 | X14: 0.20290758 | Y14: 1700.4399 | Z14: 0 | AA14: 37.69 | AB14: 7058000000 | AC14: 20777000000 | AD14: 3214000000 | AE14: 6850000000 | AF14: 2635000000 | AG14: 4351000000 | AH14: 50697428 | AI14: MercadoLibre, Inc. | AJ14: Consumer Cyclical | AK14: Internet Retail | AL14: 8.6207931e+10 | AM14: 9.0422931e+10 | AN14: 45.116475 | AO14: 4.1492001 | AP14: 12.214215 | AQ14: 28.134079 | AR14: 0 | AS14: 19.81336 | AT14: 0.45632679
A15: META | B15: 2022 | C15: 2024 | D15: 0.18773139 | E15: 0.63949109 | F15: 0.66662786 | H15: 0.67429261 | I15: 0.80256532 | J15: 0.34583822 | K15: 0.28928884 | L15: 0.27878179 | M15: 0.1866065 | N15: 0.23335843 | O15: 0.16270385 | P15: 0.027111396 | Q15: 0.031266953 | R15: 0.2410781 | S15: 121.31619 | T15: 1.8898834 | U15: 0.09904965 | V15: 2.6174253 | W15: 2.6174253 | X15: 1.0531394 | Y15: 583.17017 | Z15: 2 | AA15: 23.86 | AB15: 54072000000 | AC15: 164501000000 | AD15: 86876000000 | AE15: 49060000000 | AF15: 43889000000 | AG15: 182637000000 | AH15: 2614000000 | AI15: Meta Platforms, Inc. | AJ15: Communication Services | AK15: Internet Content & Information | AL15: 1.5244068e+12 | AM15: 1.5295778e+12 | AN15: 24.441331 | AO15: 9.2668544 | AP15: 28.192166 | AQ15: 17.606448 | AR15: 0.0034295307 | AS15: 8.3466483 | AT15: 0.36664131
A16: MSFT | B16: 2022 | C16: 2024 | D16: 0.11189209 | E16: 0.10076849 | F16: 0.10580194 | G16: 0.10118047 | H16: 0.066277456 | I16: 0.69028735 | J16: 0.43835765 | K16: 0.35596183 | L16: 0.3987758 | M16: 0.19213766 | N16: 0.30638238 | O16: 0.16774445 | P16: 0.2566545 | Q16: 0.30173187 | R16: 0.3029005 | S16: 41.895349 | T16: 1.5599119 | U16: 0.35983486 | V16: 1.6095764 | W16: 1.5851414 | X16: 0.20863869 | Y16: 416.55838 | Z16: 3.08 | AA16: 11.8 | AB16: 74071000000 | AC16: 245122000000 | AD16: 133009000000 | AE16: 67127000000 | AF16: 18315000000 | AG16: 268477000000 | AH16: 7469000000 | AI16: Microsoft Corporation | AJ16: Technology | AK16: Software - Infrastructure | AL16: 3.1112745e+12 | AM16: 3.1600865e+12 | AN16: 35.301558 | AO16: 12.692759 | AP16: 42.003949 | AQ16: 23.758441 | AR16: 0.0073939216 | AS16: 11.588607 | AT16: 3.33657
A17: NFLX | B17: 2022 | C17: 2024 | D17: 0.11067581 | E17: 0.39262291 | F17: 0.41172406 | H17: 1.0679986 | I17: 0.423217 | J17: 0.2229984 | K17: 0.17527094 | L17: 0.28733795 | M17: 0.12459285 | N17: 0.18304406 | O17: 0.13366584 | R17: 0.67565284 | S17: 10.86957 | T17: 0.37125299 | U17: 0.36453734 | V17: 1.1685879 | W17: 1.1685879 | X17: 0.7259526 | Y17: 89.132004 | AA17: 1.983 | AB17: 6921826000 | AC17: 39000966000 | AD17: 26314821000 | AE17: 15582804000 | AF17: 7804733000 | AG17: 24743567000 | AH17: 4392610000 | AI17: Netflix, Inc. | AJ17: Communication Services | AK17: Entertainment | AL17: 3.9152213e+11 | AM17: 3.993002e+11 | AN17: 44.94806 | AO17: 10.03878 | AP17: 56.563417 | AQ17: 15.173966 | AS17: 15.823189 | AT17: 1.0917035
A18: PDD | B18: 2022 | C18: 2024 | D18: 0.73682755 | E18: 0.88813185 | F18: 0.86202935 | H18: 0.5895834 | I18: 0.66595044 | J18: 0.30223016 | K18: 0.25648169 | L18: 0.37021059 | M18: 0.20058026 | N18: 0.30069236 | O18: 0.149119 | R18: 0.077312699 | S18: 1170.5944 | T18: 7.8740254 | U18: -0.48815282 | V18: 1.9956136 | W18: 1.9956136 | X18: 0.33043926 | Y18: 96.989998 | AA18: 76 | AB18: 120962155000 | AC18: 393836097000 | AD18: 135324955000 | AE18: 10607140000 | AF18: 57768053000 | AG18: 313313124000 | AH18: 1479148000 | AI18: PDD Holdings Inc. | AJ18: Consumer Cyclical | AK18: Internet Retail | AL18: 1.4346256e+11 | AM18: 9.6301648e+10 | AN18: 1.2761842 | AO18: 0.36426971 | AP18: 1.186012 | AQ18: 0.71163259 | AS18: 0.45788877 | AT18: 0.014804417
A19: PEP | B19: 2022 | C19: 2024 | D19: 0.03112727 | E19: 0.036808537 | F19: 0.040458801 | G19: 0.08531127 | H19: 0.13262248 | I19: 0.53933519 | J19: 0.13620313 | K19: 0.10220319 | L19: 0.5175952 | M19: 0.095545283 | N19: 0.16556338 | O19: 0.18455312 | P19: 0.72794833 | Q19: 0.98339374 | R19: 2.403881 | S19: 13.779836 | T19: 0.2841853 | U19: 2.2405765 | V19: 0.82488757 | W19: 0.64763463 | X19: 0.25383326 | Y19: 144.92221 | Z19: 5.33 | AA19: 6.95 | AB19: 7189000000 | AC19: 91854000000 | AD19: 16680000000 | AE19: 44948000000 | AF19: 8505000000 | AG19: 18041000000 | AH19: 1378000000 | AI19: Pepsico, Inc. | AJ19: Consumer Defensive | AK19: Beverages - Non-Alcoholic | AL19: 1.9970281e+11 | AM19: 2.3614581e+11 | AN19: 20.852117 | AO19: 2.1741329 | AP19: 27.778941 | AQ19: 14.157422 | AR19: 0.036778351 | AS19: 11.069387 | AT19: 5.1539136
A20: REGN | B20: 2022 | C20: 2024 | D20: 0.080134224 | E20: 0.0085152847 | F20: 0.0015686284 | H20: 0.020522204 | I20: 0.86487887 | J20: 0.3567276 | K20: 0.32283558 | L20: 0.17116956 | M20: 0.13333793 | N20: 0.15483279 | O20: 0.080818999 | P20: 0 | Q20: 0 | R20: 0.1051302 | S20: 76.30501 | T20: 1.7302074 | U20: -0.014008932 | V20: 5.1592195 | W20: 4.3921772 | X20: 0.80567266 | Y20: 706.49481 | Z20: 0 | AA20: 38.34 | AB20: 3538900000 | AC20: 14202000000 | AD20: 5318000000 | AE20: 2704400000 | AF20: 2488200000 | AG20: 29353600000 | AH20: 115100000 | AI20: Regeneron Pharmaceuticals, Inc. | AJ20: Healthcare | AK20: Biotechnology | AL20: 8.1317553e+10 | AM20: 8.1533753e+10 | AN20: 18.427095 | AO20: 5.7257818 | AP20: 22.9782 | AQ20: 15.331657 | AR20: 0 | AS20: 2.7702753 | AT20: 117.47266
A21: TMUS | B21: 2022 | C21: 2024 | D21: 0.011427586 | E21: 1.0923652 | F21: 1.1654839 | I21: 0.59880698 | J21: 0.16230631 | K21: 0.092573374 | L21: 0.11343647 | M21: 0.035501391 | N21: 0.071726628 | O21: 0.21661378 | P21: 0.126949 | Q21: 0.14233568 | R21: 1.732626 | S21: 3.8487839 | T21: 0.1699573 | U21: 4.2645358 | V21: 0.8638292 | W21: 0.78516838 | X21: 0.23188078 | Y21: 215.13181 | Z21: 2.83 | AA21: 9.66 | AB21: 9982000000 | AC21: 81400000000 | AD21: 31042000000 | AE21: 113944000000 | AF21: 5409000000 | AG21: 61741000000 | AH21: 1173213898 | AI21: T-Mobile US, Inc. | AJ21: Communication Services | AK21: Telecom Services | AL21: 2.5239562e+11 | AM21: 3.6093062e+11 | AN21: 22.270373 | AO21: 3.1006833 | AP21: 25.285076 | AQ21: 11.62717 | AR21: 0.013154726 | AS21: 4.0879743 | AT21: 0.19108264
A22: TSLA | B22: 2022 | C22: 2024 | D22: 0.095084219 | E22: -0.2472467 | F22: -0.24930971 | H22: -0.31139342 | I22: 0.20569986 | J22: 0.12367688 | K22: 0.12748074 | L22: 0.22204979 | M22: 0.12464451 | N22: 0.19699527 | O22: -0.071534156 | R22: 0.15608617 | S22: 54.814142 | T22: 1.6805805 | U22: -0.40909495 | V22: 1.7609206 | W22: 1.3037096 | X22: 0.57963333 | Y22: 403.84 | AA22: 2.04 | AB22: 3581000000 | AC22: 97690000000 | AD22: 14708000000 | AE22: 13623000000 | AF22: 16139000000 | AG22: 72913000000 | AH22: 3216000000 | AI22: Tesla, Inc. | AJ22: Consumer Cyclical | AK22: Auto Manufacturers | AL22: 1.2987494e+12 | AM22: 1.2962334e+12 | AN22: 197.96078 | AO22: 13.2946 | AP22: 362.67786 | AQ22: 88.131182 | AS22: 17.812316
A23: VRTX | B23: 2022 | C23: 2024 | D23: 0.11083618 | I23: 0.87075327 | J23: 0.31787719 | K23: 0.23004347 | L23: 0.14570857 | M23: 0.1121449 | N23: 0.13772303 | O23: 1.1813347 | R23: 0.072316031 | S23: 62.556561 | T23: 2.8945276 | U23: -3.3503932 | V23: 3.835287 | W23: 3.5971546 | X23: 2.6785313 | Y23: 402.70001 | AA23: -2.08 | AB23: -978000000 | AC23: 11020100000 | AD23: 486300000 | AE23: 1744300000 | AF23: 4569600000 | AG23: 16409600000 | AH23: 257900000 | AI23: Vertex Pharmaceuticals Incorpor | AJ23: Healthcare | AK23: Biotechnology | AL23: 1.0385633e+11 | AM23: 1.0103103e+11 | AN23: -193.60578 | AO23: 9.4242641 | AP23: -106.19257 | AQ23: 207.75454 | AS23: 6.3289985

Sheet Test Results (2025)
A1: Ticker | B1: Year | C1: Price (2025) | D1: Revenue (2025) | E1: Gross Profit (2025) | F1: Net Income (2025) | G1: EPS (2025) | H1: DPS (2025) | I1: Diluted Shares (2025) | J1: FCF (2025) | K1: Operating Cash Flow (2025) | L1: Capital Expenditure (2025) | M1: Common Dividends Paid (2025) | N1: Cash (2025) | O1: Current Assets (2025) | P1: Total Assets (2025) | Q1: Average Total Assets (2025) | R1: Current Liabilities (2025) | S1: Inventory (2025) | T1: Equity (2025) | U1: Average Equity (2025) | V1: Total Debt (2025) | W1: Invested Capital (2025) | X1: EBITDA (2025) | Y1: EBIT (2025) | Z1: Interest Expense (2025) | AA1: Pretax Income (2025) | AB1: Tax Provision (2025) | AC1: Tax Rate (2025) | AD1: Warnings | AE1: Gross Margin (2025) | AF1: Operating Margin (2025) | AG1: Net Profit Margin (2025) | AH1: ROE (2025) | AI1: ROA (2025) | AJ1: NOPAT (2025) | AK1: ROIC (2025) | AL1: Payout Ratio based on NI (2025) | AM1: Payout Ratio based on FCF (2025) | AN1: D/E (2025) | AO1: Interest Coverage (2025) | AP1: OCF / Total Debt (2025) | AQ1: Net Debt (2025) | AR1: Net Debt / EBITDA (2025) | AS1: Current Ratio (2025) | AT1: Quick Ratio (2025) | AU1: Cash Ratio (2025) | AV1: Market Cap (2025) | AW1: EV (2025) | AX1: P/E (2025) | AY1: P/S (2025) | AZ1: P/FCF (2025) | BA1: EV/EBITDA (2025) | BB1: Dividend Yield (2025) | BC1: P/B (2025) | BD1: Name | BE1: Yahoo Sector | BF1: Yahoo Industry | BG1: PEG (2025)
A2: AAPL | B2: 2025 | C2: 271.35583 | D2: 416161000000 | E2: 195201000000 | F2: 112010000000 | G2: 7.46 | H2: 1.03 | I2: 15004697000 | J2: 98767000000 | K2: 111482000000 | L2: -12715000000 | M2: 15421000000 | N2: 35934000000 | O2: 147957000000 | P2: 359241000000 | Q2: 362110500000 | R2: 165631000000 | S2: 5718000000 | T2: 73733000000 | U2: 65341500000 | V2: 98657000000 | W2: 172390000000 | X2: 144748000000 | Y2: 133050000000 | Z2: 3933000000 | AA2: 132729000000 | AB2: 20719000000 | AC2: 0.15610002 | AE2: 0.46905164 | AF2: 0.319708 | AG2: 0.26915064 | AH2: 1.7142245 | AI2: 0.30932547 | AJ2: 1.1228089e+11 | AK2: 0.65131906 | AL2: 0.13767521 | AM2: 0.15613515 | AN2: 1.3380305 | AO2: 33.829138 | AP2: 1.1299958 | AQ2: 62723000000 | AR2: 0.4333255 | AS2: 0.89329292 | AT2: 0.8587704 | AU2: 0.21695214 | AV2: 4.0716121e+12 | AW2: 4.1343351e+12 | AX2: 36.374777 | AY2: 9.7837425 | AZ2: 41.224418 | BA2: 28.562295 | BB2: 0.003795754 | BC2: 55.221028 | BD2: Apple Inc. | BE2: Technology | BF2: Consumer Electronics
A3: AMD | B3: 2025 | C3: 214.16 | D3: 34639000000 | E3: 17152000000 | F3: 4335000000 | G3: 2.65 | I3: 1636000000 | J3: 6735000000 | K3: 7709000000 | L3: -974000000 | N3: 5539000000 | O3: 26947000000 | P3: 76926000000 | Q3: 73076000000 | R3: 9455000000 | S3: 7920000000 | T3: 62999000000 | U3: 60283500000 | V3: 3847000000 | W3: 66221000000 | X3: 7275000000 | Y3: 4271000000 | Z3: 131000000 | AA3: 4140000000 | AB3: -103000000 | AC3: -0.024879227 | AE3: 0.49516441 | AF3: 0.12330033 | AG3: 0.12514795 | AH3: 0.071910224 | AI3: 0.059321802 | AJ3: 4.3772592e+09 | AK3: 0.066100771 | AN3: 0.061064461 | AO3: 32.603053 | AP3: 2.0038991 | AQ3: -1692000000 | AR3: -0.23257732 | AS3: 2.8500264 | AT3: 2.0123744 | AU3: 0.5858276 | AV3: 3.5036577e+11 | AW3: 3.4867377e+11 | AX3: 80.815096 | AY3: 10.114777 | AZ3: 52.021643 | BA3: 47.927665 | BC3: 5.5614496 | BD3: Advanced Micro Devices, Inc. | BE3: Technology | BF3: Semiconductors
A4: AMGN | B4: 2025 | C4: 322.62134 | D4: 36751000000 | E4: 24714000000 | F4: 7711000000 | G4: 14.23 | H4: 9.52 | I4: 542000000 | J4: 8100000000 | K4: 9958000000 | L4: -1858000000 | M4: 5124000000 | N4: 9129000000 | O4: 29057000000 | P4: 90586000000 | Q4: 91212500000 | R4: 25489000000 | S4: 6225000000 | T4: 8658000000 | U4: 7267500000 | V4: 54604000000 | W4: 63262000000 | X4: 16898000000 | Y4: 11731000000 | Z4: 2755000000 | AA4: 8976000000 | AB4: 1265000000 | AC4: 0.14093137 | AE4: 0.6724715 | AF4: 0.3192022 | AG4: 0.20981742 | AH4: 1.0610251 | AI4: 0.084538852 | AJ4: 1.0077734e+10 | AK4: 0.15930154 | AL4: 0.66450525 | AM4: 0.63259259 | AN4: 6.3067683 | AO4: 4.2580762 | AP4: 0.18236759 | AQ4: 45475000000 | AR4: 2.6911469 | AS4: 1.139982 | AT4: 0.89575895 | AU4: 0.3581545 | AV4: 1.7486077e+11 | AW4: 2.2033577e+11 | AX4: 22.671914 | AY4: 4.7579866 | AZ4: 21.587749 | BA4: 13.039162 | BB4: 0.029508278 | BC4: 20.196439 | BD4: Amgen Inc. | BE4: Healthcare | BF4: Drug Manufacturers - General
A5: AMZN | B5: 2025 | C5: 230.82001 | D5: 716924000000 | E5: 360510000000 | F5: 77670000000 | G5: 7.17 | I5: 10827000000 | J5: 7695000000 | K5: 139514000000 | L5: -131819000000 | N5: 86810000000 | O5: 229083000000 | P5: 818042000000 | Q5: 721468000000 | R5: 218005000000 | S5: 38325000000 | T5: 411065000000 | U5: 348517500000 | V5: 152987000000 | W5: 476713000000 | X5: 165341000000 | Y5: 99585000000 | Z5: 2274000000 | AA5: 97311000000 | AE5: 0.50285665 | AF5: 0.13890594 | AG5: 0.10833784 | AH5: 0.22285825 | AI5: 0.1076555 | AJ5: 78672150000 | AK5: 0.16503043 | AN5: 0.37217228 | AO5: 43.792876 | AP5: 0.91193369 | AQ5: 66177000000 | AR5: 0.40024555 | AS5: 1.0508153 | AT5: 0.87501663 | AU5: 0.39820188 | AV5: 2.4990882e+12 | AW5: 2.5652652e+12 | AX5: 32.19247 | AY5: 3.4858482 | AZ5: 324.7678 | BA5: 15.514998 | BC5: 6.0795451 | BD5: Amazon.com, Inc. | BE5: Consumer Cyclical | BF5: Internet Retail
A6: ASML | B6: 2025 | C6: 1066.1221 | D6: 32667300000 | E6: 17258000000 | F6: 9609400000 | G6: 26.26 | H6: 7.372 | I6: 388900000 | J6: 11027300000 | L6: -1631200000 | M6: 2550300000 | N6: 12916000000 | O6: 30616100000 | P6: 50566600000 | Q6: 49578100000 | R6: 24263900000 | S6: 11429300000 | T6: 19612200000 | U6: 19044500000 | V6: 4390900000 | W6: 24003100000 | X6: 12550300000 | Y6: 11524400000 | Z6: 118300000 | AA6: 11406100000 | AB6: 2013400000 | AC6: 0.17651958 | AE6: 0.52829588 | AF6: 0.35278092 | AG6: 0.2941596 | AH6: 0.50457612 | AI6: 0.19382348 | AJ6: 9.4901177e+09 | AK6: 0.3953705 | AL6: 0.26539638 | AM6: 0.23127148 | AN6: 0.22388615 | AO6: 97.416737 | AQ6: -8525100000 | AR6: -0.6792746 | AS6: 1.2617963 | AT6: 0.79075499 | AU6: 0.53231344 | AV6: 4.1461487e+11 | AW6: 4.0608977e+11 | AX6: 40.598708 | AY6: 12.692046 | AZ6: 37.598947 | BA6: 32.356977 | BB6: 0.0069147804 | BC6: 21.140661 | BD6: ASML Holding N.V. - New York Re | BE6: Technology | BF6: Semiconductor Equipment & Materials
A7: CCEP | B7: 2025 | C7: 89.741371 | D7: 20901000000 | E7: 7440000000 | F7: 1942000000 | G7: 4.26 | H7: 2.33 | I7: 456000000 | J7: 2003000000 | K7: 2953000000 | L7: -950000000 | M7: 927000000 | N7: 918000000 | O7: 6079000000 | P7: 29872000000 | Q7: 30486000000 | R7: 7585000000 | S7: 1547000000 | T7: 7835000000 | U7: 8162000000 | V7: 10694000000 | W7: 17830000000 | X7: 3766000000 | Y7: 2843000000 | Z7: 274000000 | AA7: 2569000000 | AB7: 590000000 | AC7: 0.22966135 | AE7: 0.35596383 | AF7: 0.1360222 | AG7: 0.092914215 | AH7: 0.23793188 | AI7: 0.063701371 | AJ7: 2.1900728e+09 | AK7: 0.12283078 | AL7: 0.47734295 | AM7: 0.46280579 | AN7: 1.3649011 | AO7: 10.375912 | AP7: 0.27613615 | AQ7: 9776000000 | AR7: 2.5958577 | AS7: 0.80145023 | AT7: 0.59749506 | AU7: 0.12102835 | AV7: 4.0922065e+10 | AW7: 5.0698065e+10 | AX7: 21.06605 | AY7: 1.9578999 | AZ7: 20.430387 | BA7: 13.462046 | BB7: 0.025963499 | BC7: 5.2229822 | BD7: Coca-Cola Europacific Partners | BE7: Consumer Defensive | BF7: Beverages - Non-Alcoholic
A8: CHTR | B8: 2025 | C8: 208.75 | D8: 54774000000 | E8: 30968000000 | F8: 4987000000 | G8: 36.21 | I8: 137743676 | J8: 4418000000 | K8: 16077000000 | L8: -11659000000 | N8: 477000000 | O8: 5144000000 | P8: 154213000000 | Q8: 152116500000 | R8: 13306000000 | T8: 16054000000 | U8: 15820500000 | V8: 97121000000 | W8: 113175000000 | X8: 21211000000 | Y8: 12500000000 | Z8: 5042000000 | AA8: 7458000000 | AB8: 1692000000 | AC8: 0.22687047 | AE8: 0.56537773 | AF8: 0.22821046 | AG8: 0.091046847 | AH8: 0.31522392 | AI8: 0.032784083 | AJ8: 9.6641191e+09 | AK8: 0.085390935 | AN8: 6.0496449 | AO8: 2.4791749 | AP8: 0.16553577 | AQ8: 96644000000 | AR8: 4.5563151 | AS8: 0.38659251 | AT8: 0.38659251 | AU8: 0.035848489 | AV8: 28753992365 | AW8: 125397992365 | AX8: 5.764982 | AY8: 0.52495696 | AZ8: 6.5083731 | BA8: 5.9119321 | BC8: 1.7910796 | BD8: Charter Communications, Inc. | BE8: Communication Services | BF8: Telecom Services
A9: COST | B9: 2025 | C9: 859.91577 | D9: 275235000000 | E9: 35349000000 | F9: 8099000000 | G9: 18.21 | H9: 5.06 | I9: 444803000 | J9: 7837000000 | K9: 13335000000 | L9: -5498000000 | M9: 1251000000 | N9: 14161000000 | O9: 38380000000 | P9: 77099000000 | Q9: 73465000000 | R9: 37108000000 | S9: 18116000000 | T9: 29164000000 | U9: 26393000000 | V9: 8173000000 | W9: 34877000000 | X9: 13398000000 | Y9: 10972000000 | Z9: 154000000 | AA9: 10818000000 | AB9: 2719000000 | AC9: 0.25134036 | AE9: 0.12843207 | AF9: 0.039864116 | AG9: 0.029425763 | AH9: 0.30686167 | AI9: 0.11024297 | AJ9: 8.2142936e+09 | AK9: 0.23552179 | AL9: 0.15446351 | AM9: 0.15962741 | AN9: 0.28024277 | AO9: 71.246753 | AP9: 1.6315918 | AQ9: -5988000000 | AR9: -0.44693238 | AS9: 1.0342783 | AT9: 0.54608171 | AU9: 0.38161582 | AV9: 3.8249311e+11 | AW9: 3.7650511e+11 | AX9: 47.222173 | AY9: 1.3896965 | AZ9: 48.806063 | BA9: 28.101591 | BB9: 0.0058842972 | BC9: 13.115249 | BD9: Costco Wholesale Corporation | BE9: Consumer Defensive | BF9: Discount Stores
A10: GILD | B10: 2025 | C10: 122.04688 | D10: 29442000000 | E10: 23208000000 | F10: 8510000000 | G10: 6.78 | H10: 3.16 | I10: 1255000000 | J10: 9456000000 | K10: 10019000000 | L10: -563000000 | M10: 4003000000 | N10: 7564000000 | O10: 18342000000 | P10: 59023000000 | Q10: 59009000000 | R10: 11813000000 | S10: 1774000000 | T10: 22702000000 | U10: 21016000000 | V10: 24936000000 | W10: 47638000000 | X10: 13580000000 | Y10: 10820000000 | Z10: 1024000000 | AA10: 9796000000 | AB10: 1286000000 | AC10: 0.13127807 | AE10: 0.78826167 | AF10: 0.36750221 | AG10: 0.28904286 | AH10: 0.40492958 | AI10: 0.14421529 | AJ10: 9.3995713e+09 | AK10: 0.19731247 | AL10: 0.47038778 | AM10: 0.4233291 | AN10: 1.0984054 | AO10: 10.566406 | AP10: 0.40178858 | AQ10: 17372000000 | AR10: 1.2792342 | AS10: 1.5526962 | AT10: 1.4025226 | AU10: 0.64031152 | AV10: 1.5316884e+11 | AW10: 1.7054084e+11 | AX10: 18.001015 | AY10: 5.2023924 | AZ10: 16.198058 | BA10: 12.558235 | BB10: 0.02589169 | BC10: 6.7469314 | BD10: Gilead Sciences, Inc. | BE10: Healthcare | BF10: Drug Manufacturers - General
A11: GOOGL | B11: 2025 | C11: 312.77982 | D11: 402836000000 | E11: 240301000000 | F11: 132170000000 | G11: 10.81 | H11: 0.83 | I11: 12230000000 | J11: 73266000000 | K11: 164713000000 | L11: -91447000000 | M11: 10049000000 | N11: 30708000000 | O11: 206038000000 | P11: 595281000000 | Q11: 522768500000 | R11: 102745000000 | S11: 2670000000 | T11: 415265000000 | U11: 370174500000 | V11: 59291000000 | W11: 461812000000 | X11: 180698000000 | Y11: 159562000000 | Z11: 736000000 | AA11: 158826000000 | AB11: 26656000000 | AC11: 0.16783146 | AE11: 0.59652315 | AF11: 0.39609667 | AG11: 0.32809878 | AH11: 0.35704782 | AI11: 0.25282702 | AJ11: 1.3278248e+11 | AK11: 0.28752496 | AL11: 0.076030869 | AM11: 0.13715775 | AN11: 0.14277871 | AO11: 216.7962 | AP11: 2.7780439 | AQ11: 28583000000 | AR11: 0.15818105 | AS11: 2.0053336 | AT11: 1.9793469 | AU11: 0.29887586 | AV11: 3.8252971e+12 | AW11: 3.8538801e+12 | AX11: 28.934303 | AY11: 9.4959168 | AZ11: 52.211082 | BA11: 21.327741 | BB11: 0.0026536239 | BC11: 9.2117013 | BD11: Alphabet Inc. | BE11: Communication Services | BF11: Internet Content & Information
A12: KDP | B12: 2025 | C12: 27.536779 | D12: 16603000000 | E12: 8999000000 | F12: 2079000000 | G12: 1.53 | H12: 0.92 | I12: 1362800000 | J12: 1488000000 | K12: 1991000000 | L12: -503000000 | M12: 1142000000 | N12: 1026000000 | O12: 5266000000 | P12: 55459000000 | Q12: 54444500000 | R12: 8290000000 | S12: 1733000000 | T12: 25516000000 | U12: 24879500000 | V12: 16141000000 | W12: 41657000000 | X12: 4194000000 | Y12: 3441000000 | Z12: 754000000 | AA12: 2687000000 | AB12: 608000000 | AC12: 0.22627466 | AE12: 0.54201048 | AF12: 0.2072517 | AG12: 0.12521833 | AH12: 0.083562773 | AI12: 0.038185675 | AJ12: 2.6623889e+09 | AK12: 0.063912161 | AL12: 0.54930255 | AM12: 0.76747312 | AN12: 0.63258348 | AO12: 4.5636605 | AP12: 0.12335047 | AQ12: 15115000000 | AR12: 3.603958 | AS12: 0.63522316 | AT12: 0.42617612 | AU12: 0.12376357 | AV12: 3.7527123e+10 | AW12: 5.2642123e+10 | AX12: 17.997895 | AY12: 2.2602616 | AZ12: 25.219841 | BA12: 12.55177 | BB12: 0.033409862 | BC12: 1.4707291 | BD12: Keurig Dr Pepper Inc. | BE12: Consumer Defensive | BF12: Beverages - Non-Alcoholic
A13: MDLZ | B13: 2025 | C13: 53.367943 | D13: 38537000000 | E13: 10935000000 | F13: 2451000000 | G13: 1.89 | H13: 1.94 | I13: 1298000000 | J13: 3235000000 | K13: 4514000000 | L13: -1279000000 | M13: 2487000000 | N13: 2125000000 | O13: 12951000000 | P13: 71487000000 | Q13: 69992000000 | R13: 21864000000 | S13: 4419000000 | T13: 25838000000 | U13: 26385000000 | V13: 21804000000 | W13: 47043000000 | X13: 4971000000 | Y13: 3613000000 | Z13: 599000000 | AA13: 3014000000 | AB13: 782000000 | AC13: 0.25945587 | AE13: 0.28375328 | AF13: 0.093754055 | AG13: 0.063601214 | AH13: 0.09289369 | AI13: 0.035018288 | AJ13: 2.6755859e+09 | AK13: 0.056875325 | AL13: 1.0146879 | AM13: 0.76877898 | AN13: 0.84387336 | AO13: 6.0317195 | AP13: 0.20702623 | AQ13: 19679000000 | AR13: 3.9587608 | AS13: 0.59234358 | AT13: 0.39023052 | AU13: 0.097191731 | AV13: 6.927159e+10 | AW13: 8.895059e+10 | AX13: 28.237007 | AY13: 1.7975346 | AZ13: 21.413165 | BA13: 17.893903 | BB13: 0.036351411 | BC13: 2.6809966 | BD13: Mondelez International, Inc. | BE13: Consumer Defensive | BF13: Confectioners
A14: MELI | B14: 2025 | C14: 2014.26 | D14: 28893000000 | E14: 12858000000 | F14: 1997000000 | G14: 39.4 | H14: 0 | I14: 50697320 | J14: 10773000000 | K14: 12116000000 | L14: -1343000000 | M14: 0 | N14: 3670000000 | O14: 33573000000 | P14: 42667000000 | Q14: 33931500000 | R14: 28633000000 | S14: 570000000 | T14: 6748000000 | U14: 5549500000 | V14: 11392000000 | W14: 15811000000 | X14: 3820000000 | Y14: 3002000000 | Z14: 160000000 | AA14: 2842000000 | AB14: 845000000 | AC14: 0.29732583 | AE14: 0.44502129 | AF14: 0.1039006 | AG14: 0.069117087 | AH14: 0.35985224 | AI14: 0.058853867 | AJ14: 2.1094279e+09 | AK14: 0.13341521 | AL14: 0 | AM14: 0 | AN14: 1.6882039 | AO14: 18.7625 | AP14: 1.0635534 | AQ14: 7722000000 | AR14: 2.021466 | AS14: 1.1725282 | AT14: 1.1526211 | AU14: 0.12817379 | AV14: 1.0211758e+11 | AW14: 1.0983958e+11 | AX14: 51.123351 | AY14: 3.5343365 | AZ14: 9.4790295 | BA14: 28.753818 | BB14: 0 | BC14: 15.133015 | BD14: MercadoLibre, Inc. | BE14: Consumer Cyclical | BF14: Internet Retail
A15: META | B15: 2025 | C15: 659.52533 | D15: 200966000000 | E15: 164791000000 | F15: 60458000000 | G15: 23.49 | H15: 2.1 | I15: 2574000000 | J15: 46109000000 | K15: 115800000000 | L15: -69691000000 | M15: 5324000000 | N15: 35873000000 | O15: 108722000000 | P15: 366021000000 | Q15: 321037500000 | R15: 41836000000 | T15: 217243000000 | U15: 199940000000 | V15: 83897000000 | W15: 275987000000 | X15: 105713000000 | Y15: 87097000000 | Z15: 1165000000 | AA15: 85932000000 | AB15: 25474000000 | AC15: 0.2964437 | AE15: 0.81999443 | AF15: 0.43339172 | AG15: 0.30083696 | AH15: 0.30238071 | AI15: 0.18832068 | AJ15: 6.1277643e+10 | AK15: 0.2220309 | AL15: 0.088061133 | AM15: 0.11546553 | AN15: 0.38618966 | AO15: 74.761373 | AP15: 1.3802639 | AQ15: 48024000000 | AR15: 0.45428661 | AS15: 2.5987666 | AT15: 2.5987666 | AU15: 0.85746725 | AV15: 1.6976182e+12 | AW15: 1.7456422e+12 | AX15: 28.076855 | AY15: 8.4472906 | AZ15: 36.817502 | BA15: 16.513032 | BB15: 0.0031841082 | BC15: 7.8143747 | BD15: Meta Platforms, Inc. | BE15: Communication Services | BF15: Internet Content & Information
A16: MSFT | B16: 2025 | C16: 481.47586 | D16: 281724000000 | E16: 193893000000 | F16: 101832000000 | G16: 13.64 | H16: 3.4 | I16: 7465000000 | J16: 71611000000 | K16: 136162000000 | L16: -64551000000 | M16: 24082000000 | N16: 30242000000 | O16: 191131000000 | P16: 619003000000 | Q16: 565583000000 | R16: 141218000000 | S16: 938000000 | T16: 343479000000 | U16: 305978000000 | V16: 60588000000 | W16: 386630000000 | X16: 160165000000 | Y16: 126012000000 | Z16: 2385000000 | AA16: 123627000000 | AB16: 21795000000 | AC16: 0.17629644 | AE16: 0.68823742 | AF16: 0.44728884 | AG16: 0.36146015 | AH16: 0.33280824 | AI16: 0.18004784 | AJ16: 1.0379653e+11 | AK16: 0.26846477 | AL16: 0.23648755 | AM16: 0.33628912 | AN16: 0.17639506 | AO16: 52.83522 | AP16: 2.2473427 | AQ16: 30346000000 | AR16: 0.18946711 | AS16: 1.3534464 | AT16: 1.3468042 | AU16: 0.21415117 | AV16: 3.5942173e+12 | AW16: 3.6245633e+12 | AX16: 35.298817 | AY16: 12.757938 | AZ16: 50.190855 | BA16: 22.630183 | BB16: 0.0070616209 | BC16: 10.464154 | BD16: Microsoft Corporation | BE16: Technology | BF16: Software - Infrastructure
A17: NFLX | B17: 2025 | C17: 93.760002 | D17: 45183036000 | E17: 21907707000 | F17: 10981201000 | G17: 2.53 | I17: 4343863000 | J17: 9461053000 | K17: 10149273000 | L17: -688220000 | N17: 9033681000 | O17: 13020191000 | P17: 55596993000 | Q17: 54613683500 | R17: 10980930000 | T17: 26615488000 | U17: 25679527500 | V17: 14462836000 | W17: 41078324000 | X17: 30254617000 | Y17: 13499062000 | Z17: 776510000 | AA17: 12722552000 | AB17: 1741351000 | AC17: 0.1368712 | AE17: 0.48486576 | AF17: 0.29876394 | AG17: 0.24303814 | AH17: 0.42762473 | AI17: 0.20107051 | AJ17: 1.1651429e+10 | AK17: 0.28363935 | AN17: 0.54339924 | AO17: 17.384273 | AP17: 0.70174847 | AQ17: 5429155000 | AR17: 0.17944881 | AS17: 1.1857093 | AT17: 1.1857093 | AU17: 0.82266994 | AV17: 4.072806e+11 | AW17: 4.1270976e+11 | AX17: 37.059289 | AY17: 9.0140159 | AZ17: 43.048126 | BA17: 13.641216 | BC17: 15.302391 | BD17: Netflix, Inc. | BE17: Communication Services | BF17: Entertainment
A18: PDD | B18: 2025 | C18: 113.39 | D18: 431845713000 | E18: 243043960000 | F18: 97842539000 | G18: 66 | I18: 1482394000 | J18: 105793613000 | K18: 106938690000 | L18: -1145077000 | N18: 108900587000 | O18: 518979892000 | P18: 630044327000 | Q18: 567539321500 | R18: 213737168000 | T18: 413385156000 | U18: 363349140000 | V18: 5378795000 | W18: 413385156000 | X18: 122446654000 | Y18: 119446290000 | Z18: 0 | AA18: 119446290000 | AB18: 21732756000 | AC18: 0.18194584 | AE18: 0.56280276 | AF18: 0.27659483 | AG18: 0.22656828 | AH18: 0.26927968 | AI18: 0.17239782 | AJ18: 97713534000 | AK18: 0.23637408 | AN18: 0.013011582 | AP18: 19.881533 | AQ18: -103521792000 | AR18: -0.84544402 | AS18: 2.4281219 | AT18: 2.4281219 | AU18: 0.50950702 | AV18: 1.6808865e+11 | AW18: 6.4566863e+10 | AX18: 1.7180303 | AY18: 0.38923312 | AZ18: 1.5888356 | BA18: 0.52730606 | BC18: 0.40661512 | BD18: PDD Holdings Inc. | BE18: Consumer Cyclical | BF18: Internet Retail
A19: PEP | B19: 2025 | C19: 142.24913 | D19: 93925000000 | E19: 50859000000 | F19: 8240000000 | G19: 6 | H19: 5.624 | I19: 1373000000 | J19: 7672000000 | K19: 12087000000 | L19: -4415000000 | M19: 7638000000 | N19: 9159000000 | O19: 27949000000 | P19: 107399000000 | Q19: 103433000000 | R19: 32764000000 | S19: 5845000000 | T19: 20406000000 | U19: 19223500000 | V19: 49901000000 | W19: 69588000000 | X19: 15543000000 | Y19: 11365000000 | Z19: 1121000000 | AA19: 10244000000 | AB19: 1949000000 | AC19: 0.19025771 | AE19: 0.54148523 | AF19: 0.1210008 | AG19: 0.087729571 | AH19: 0.42864203 | AI19: 0.079665097 | AJ19: 9.2027211e+09 | AK19: 0.13224581 | AL19: 0.92694175 | AM19: 0.9955683 | AN19: 2.4454082 | AO19: 10.138269 | AP19: 0.24221959 | AQ19: 40742000000 | AR19: 2.6212443 | AS19: 0.85303992 | AT19: 0.6746429 | AU19: 0.27954462 | AV19: 1.9530806e+11 | AW19: 2.3605006e+11 | AX19: 23.708188 | AY19: 2.0794044 | AZ19: 25.457254 | BA19: 15.186904 | BB19: 0.03953627 | BC19: 9.5711093 | BD19: Pepsico, Inc. | BE19: Consumer Defensive | BF19: Beverages - Non-Alcoholic
A20: REGN | B20: 2025 | C20: 769.79285 | D20: 14342900000 | E20: 12242200000 | F20: 4504900000 | G20: 41.48 | H20: 3.52 | I20: 108600000 | J20: 3765200000 | K20: 4978900000 | L20: -1213700000 | M20: 370300000 | N20: 3118100000 | O20: 18021900000 | P20: 40558700000 | Q20: 39159050000 | R20: 4368400000 | S20: 3200800000 | T20: 31256900000 | U20: 30305250000 | V20: 2705900000 | W20: 33242800000 | X20: 5818200000 | Y20: 5274500000 | Z20: 43800000 | AA20: 5230700000 | AB20: 725800000 | AC20: 0.13875772 | AE20: 0.85353729 | AF20: 0.36774293 | AG20: 0.31408571 | AH20: 0.14865081 | AI20: 0.1150411 | AJ20: 4.5426224e+09 | AK20: 0.13664981 | AL20: 0.082199383 | AM20: 0.098348029 | AN20: 0.086569685 | AO20: 120.42237 | AP20: 1.8400163 | AQ20: -412200000 | AR20: -0.070846654 | AS20: 4.1255151 | AT20: 3.3927983 | AU20: 0.71378537 | AV20: 8.3599503e+10 | AW20: 8.3187303e+10 | AX20: 18.558169 | AY20: 5.8286332 | AZ20: 22.203204 | BA20: 14.297773 | BB20: 0.0045726588 | BC20: 2.6745936 | BD20: Regeneron Pharmaceuticals, Inc. | BE20: Healthcare | BF20: Biotechnology
A21: TMUS | B21: 2025 | C21: 200.97791 | D21: 88309000000 | E21: 55535000000 | F21: 10992000000 | G21: 9.72 | H21: 3.66 | I21: 1131076251 | J21: 15427000000 | K21: 27950000000 | L21: -12523000000 | M21: 4121000000 | N21: 5598000000 | O21: 24461000000 | P21: 219237000000 | Q21: 213636000000 | R21: 24500000000 | S21: 2405000000 | T21: 59203000000 | U21: 60472000000 | V21: 122269000000 | W21: 145485000000 | X21: 31563000000 | Y21: 18055000000 | Z21: 3774000000 | AA21: 14281000000 | AB21: 3289000000 | AC21: 0.230306 | AE21: 0.62887135 | AF21: 0.20445255 | AG21: 0.12447202 | AH21: 0.18177008 | AI21: 0.051452002 | AJ21: 1.3896825e+10 | AK21: 0.095520673 | AL21: 0.37490902 | AM21: 0.26712906 | AN21: 2.0652501 | AO21: 4.7840488 | AP21: 0.22859433 | AQ21: 116671000000 | AR21: 3.6964484 | AS21: 0.99840816 | AT21: 0.9002449 | AU21: 0.2284898 | AV21: 2.2732134e+11 | AW21: 3.4399234e+11 | AX21: 20.676739 | AY21: 2.5741582 | AZ21: 14.735291 | BA21: 10.898594 | BB21: 0.018210957 | BC21: 3.8396928 | BD21: T-Mobile US, Inc. | BE21: Communication Services | BF21: Telecom Services
A22: TSLA | B22: 2025 | C22: 449.72 | D22: 94827000000 | E22: 17094000000 | F22: 3794000000 | G22: 1.08 | I22: 3526250000 | J22: 6220000000 | K22: 14747000000 | L22: -8527000000 | N22: 16513000000 | O22: 68642000000 | P22: 137806000000 | Q22: 129938000000 | R22: 31714000000 | S22: 12392000000 | T22: 82137000000 | U22: 77525000000 | V22: 14719000000 | W22: 90290000000 | X22: 11764000000 | Y22: 5616000000 | Z22: 338000000 | AA22: 5278000000 | AB22: 1423000000 | AC22: 0.2696097 | AE22: 0.18026511 | AF22: 0.059223639 | AG22: 0.040009702 | AH22: 0.048939052 | AI22: 0.029198541 | AJ22: 4.1018719e+09 | AK22: 0.045429969 | AN22: 0.1792006 | AO22: 16.615385 | AP22: 1.0019023 | AQ22: -1794000000 | AR22: -0.15249915 | AS22: 2.1644069 | AT22: 1.7736646 | AU22: 0.52068487 | AV22: 1.5858252e+12 | AW22: 1.5840312e+12 | AX22: 416.40741 | AY22: 16.72335 | AZ22: 254.95581 | BA22: 134.65073 | BC22: 19.307074 | BD22: Tesla, Inc. | BE22: Consumer Cyclical | BF22: Auto Manufacturers
A23: VRTX | B23: 2025 | C23: 453.35999 | D23: 12001300000 | E23: 10350000000 | F23: 3953200000 | G23: 15.32 | I23: 258000000 | J23: 3193800000 | K23: 3631400000 | L23: -437600000 | N23: 5084800000 | O23: 11201000000 | P23: 25643000000 | Q23: 24088100000 | R23: 3861200000 | S23: 1686800000 | T23: 18665800000 | U23: 17537700000 | V23: 2030500000 | W23: 18665800000 | X23: 4866300000 | Y23: 4656500000 | Z23: 13300000 | AA23: 4643200000 | AB23: 690000000 | AC23: 0.14860441 | AE23: 0.86240657 | AF23: 0.38799963 | AG23: 0.32939765 | AH23: 0.22541154 | AI23: 0.16411423 | AJ23: 3.9645236e+09 | AK23: 0.21239505 | AN23: 0.10878184 | AO23: 350.11278 | AP23: 1.7884265 | AQ23: -3054300000 | AR23: -0.62764318 | AS23: 2.9009116 | AT23: 2.4640526 | AU23: 1.3168963 | AV23: 1.1696688e+11 | AW23: 1.1391258e+11 | AX23: 29.592688 | AY23: 9.7461838 | AZ23: 36.623106 | BA23: 23.408457 | BC23: 6.2663736 | BD23: Vertex Pharmaceuticals Incorpor | BE23: Healthcare | BF23: Biotechnology

Sheet Price
A1: Ticker | B1: 2022 | C1: 2023 | D1: 2024 | E1: 2025
A2: AAPL | B2: 127.76161 | C2: 190.37509 | D2: 248.83022 | E2: 271.35583
A3: AMD | B3: 64.769997 | C3: 147.41 | D3: 120.79 | E3: 214.16
A4: AMGN | B4: 235.21104 | C4: 266.88065 | D4: 248.80763 | E4: 322.62134
A5: AMZN | B5: 84 | C5: 151.94 | D5: 219.39 | E5: 230.82001
A6: ASML | B6: 529.78485 | C6: 741.18604 | D6: 684.12122 | E6: 1066.1221
A7: CCEP | B7: 50.251957 | C7: 62.563965 | D7: 74.045609 | E7: 89.741371
A8: CHTR | B8: 339.10001 | C8: 388.67999 | D8: 342.76999 | E8: 208.75
A9: COST | B9: 436.90512 | C9: 651.00543 | D9: 908.95111 | E9: 859.91577
A10: GILD | B10: 76.816048 | C10: 75.285263 | D10: 89.350464 | E10: 122.04688
A11: GOOGL | B11: 87.50676 | C11: 138.54494 | D11: 188.42886 | E11: 312.77982
A12: KDP | B12: 32.340981 | C12: 30.970909 | D12: 30.645254 | E12: 27.536779
... A23: VRTX | B23: 288.78 | C23: 406.89001 | D23: 402.70001 | E23: 453.35999

Sheet Revenue
A1: Ticker | B1: 2022 | C1: 2023 | D1: 2024 | E1: 2025
A2: AAPL | B2: 394328000000 | C2: 383285000000 | D2: 391035000000 | E2: 416161000000
A3: AMD | B3: 23601000000 | C3: 22680000000 | D3: 25785000000 | E3: 34639000000
A4: AMGN | B4: 26323000000 | C4: 28190000000 | D4: 33424000000 | E4: 36751000000
A5: AMZN | B5: 513983000000 | C5: 574785000000 | D5: 637959000000 | E5: 716924000000
A6: ASML | B6: 21173400000 | C6: 27558500000 | D6: 28262900000 | E6: 32667300000
A7: CCEP | B7: 17320000000 | C7: 18302000000 | D7: 20438000000 | E7: 20901000000
A8: CHTR | B8: 54022000000 | C8: 54607000000 | D8: 55085000000 | E8: 54774000000
A9: COST | B9: 226954000000 | C9: 242290000000 | D9: 254453000000 | E9: 275235000000
A10: GILD | B10: 27281000000 | C10: 27116000000 | D10: 28754000000 | E10: 29442000000
A11: GOOGL | B11: 282836000000 | C11: 307394000000 | D11: 350018000000 | E11: 402836000000
A12: KDP | B12: 14057000000 | C12: 14814000000 | D12: 15351000000 | E12: 16603000000
... A23: VRTX | B23: 8930700000 | C23: 9869200000 | D23: 11020100000 | E23: 12001300000

Sheet Gross Profit
A1: Ticker | B1: 2022 | C1: 2023 | D1: 2024 | E1: 2025
A2: AAPL | B2: 170782000000 | C2: 169148000000 | D2: 180683000000 | E2: 195201000000
A3: AMD | B3: 10603000000 | C3: 10460000000 | D3: 12725000000 | E3: 17152000000
A4: AMGN | B4: 19917000000 | C4: 19739000000 | D4: 20566000000 | E4: 24714000000
A5: AMZN | B5: 225152000000 | C5: 270046000000 | D5: 311671000000 | E5: 360510000000
A6: ASML | B6: 10700100000 | C6: 14136100000 | D6: 14492000000 | E6: 17258000000
A7: CCEP | B7: 6224000000 | C7: 6720000000 | D7: 7211000000 | E7: 7440000000
A8: CHTR | B8: 29511000000 | C8: 29907000000 | D8: 30736000000 | E8: 30968000000
A9: COST | B9: 27572000000 | C9: 29704000000 | D9: 32095000000 | E9: 35349000000
A10: GILD | B10: 21624000000 | C10: 20618000000 | D10: 22503000000 | E10: 23208000000
A11: GOOGL | B11: 156633000000 | C11: 174062000000 | D11: 203712000000 | E11: 240301000000
A12: KDP | B12: 7323000000 | C12: 8080000000 | D12: 8529000000 | E12: 8999000000
... A23: VRTX | B23: 7850400000 | C23: 8607000000 | D23: 9489600000 | E23: 10350000000

Sheet Net Income
A1: Ticker | B1: 2022 | C1: 2023 | D1: 2024 | E1: 2025
A2: AAPL | B2: 99803000000 | C2: 96995000000 | D2: 93736000000 | E2: 112010000000
A3: AMD | B3: 1320000000 | C3: 854000000 | D3: 1641000000 | E3: 4335000000
A4: AMGN | B4: 6552000000 | C4: 6717000000 | D4: 4090000000 | E4: 7711000000
A5: AMZN | B5: -2722000000 | C5: 30425000000 | D5: 59248000000 | E5: 77670000000
A6: ASML | B6: 5624200000 | C6: 7839000000 | D6: 7571600000 | E6: 9609400000
A7: CCEP | B7: 1508000000 | C7: 1669000000 | D7: 1418000000 | E7: 1942000000
A8: CHTR | B8: 5055000000 | C8: 4557000000 | D8: 5083000000 | E8: 4987000000
A9: COST | B9: 5844000000 | C9: 6292000000 | D9: 7367000000 | E9: 8099000000
A10: GILD | B10: 4592000000 | C10: 5665000000 | D10: 480000000 | E10: 8510000000
A11: GOOGL | B11: 59972000000 | C11: 73795000000 | D11: 100118000000 | E11: 132170000000
A12: KDP | B12: 1436000000 | C12: 2181000000 | D12: 1441000000 | E12: 2079000000
... A23: VRTX | B23: 3322000000 | C23: 3619600000 | D23: -535600000 | E23: 3953200000

Sheet EPS
A1: Ticker | B1: 2022 | C1: 2023 | D1: 2024 | E1: 2025
A2: AAPL | B2: 6.11 | C2: 6.13 | D2: 6.08 | E2: 7.46
A3: AMD | B3: 0.84 | C3: 0.53 | D3: 1 | E3: 2.65
A4: AMGN | B4: 12.11 | C4: 12.49 | D4: 7.56 | E4: 14.23
A5: AMZN | B5: -0.27 | C5: 2.9 | D5: 5.53 | E5: 7.17
A6: ASML | B6: 16.07 | C6: 20.59 | D6: 19.24 | E6: 26.26
A7: CCEP | B7: 3.29 | C7: 3.63 | D7: 3.08 | E7: 4.26
A8: CHTR | B8: 30.74 | C8: 29.99 | D8: 34.97 | E8: 36.21
A9: COST | B9: 13.14 | C9: 14.16 | D9: 16.56 | E9: 18.21
A10: GILD | B10: 3.64 | C10: 4.5 | D10: 0.38 | E10: 6.78
A11: GOOGL | B11: 4.56 | C11: 5.8 | D11: 8.04 | E11: 10.81
A12: KDP | B12: 1.01 | C12: 1.55 | D12: 1.05 | E12: 1.53
... A23: VRTX | B23: 12.82 | C23: 13.89 | D23: -2.08 | E23: 15.32

Sheet DPS
A1: Ticker | B1: 2022 | C1: 2023 | D1: 2024 | E1: 2025
A2: AAPL | B2: 0.91 | C2: 0.95 | D2: 0.99 | E2: 1.03
A3: AMGN | B3: 7.76 | C3: 8.52 | D3: 9 | E3: 9.52
A4: ASML | B4: 6.634 | C4: 6.453 | D4: 6.713 | E4: 7.372
A5: CCEP | B5: 1.7 | C5: 1.97 | D5: 2.13 | E5: 2.33
A6: COST | B6: 3.49 | C6: 18.96 | D6: 4.5 | E6: 5.06
A7: GILD | B7: 2.92 | C7: 3 | D7: 3.08 | E7: 3.16
A8: GOOGL | B8: 0 | C8: 0 | D8: 0.6 | E8: 0.83
A9: KDP | B9: 0.764 | C9: 0.815 | D9: 0.875 | E9: 0.92
A10: MDLZ | B10: 1.47 | C10: 1.62 | D10: 1.79 | E10: 1.94
A11: MELI | B11: 0 | C11: 0 | D11: 0 | E11: 0
A12: META | B12: 0 | C12: 0 | D12: 2 | E12: 2.1
... A14: PEP | B14: 4.525 | C14: 4.945 | D14: 5.33 | E14: 5.624
A15: REGN | C15: 0 | D15: 0 | E15: 3.52
A16: TMUS | B16: 0 | C16: 0.65 | D16: 2.83 | E16: 3.66

Sheet FCF
A1: Ticker | B1: 2022 | C1: 2023 | D1: 2024 | E1: 2025
A2: AAPL | B2: 111443000000 | C2: 99584000000 | D2: 108807000000 | E2: 98767000000
A3: AMD | B3: 3115000000 | C3: 1121000000 | D3: 2405000000 | E3: 6735000000
A4: AMGN | B4: 8785000000 | C4: 7359000000 | D4: 10394000000 | E4: 8100000000
A5: AMZN | B5: -16893000000 | C5: 32217000000 | D5: 32878000000 | E5: 7695000000
A6: ASML | B6: 7167500000 | C6: 3247200000 | D6: 9083100000 | E6: 11027300000
A7: CCEP | B7: 2329000000 | C7: 1994000000 | D7: 2122000000 | E7: 2003000000
A8: CHTR | B8: 5549000000 | C8: 3318000000 | D8: 3161000000 | E8: 4418000000
A9: COST | B9: 3501000000 | C9: 6745000000 | D9: 6629000000 | E9: 7837000000
A10: GILD | B10: 8344000000 | C10: 7421000000 | D10: 10305000000 | E10: 9456000000
A11: GOOGL | B11: 60010000000 | C11: 69495000000 | D11: 72764000000 | E11: 73266000000
A12: KDP | B12: 2458000000 | C12: 848000000 | D12: 1597000000 | E12: 1488000000
... A23: VRTX | B23: 3925200000 | C23: 3278900000 | D23: -978000000 | E23: 3193800000

Sheet Pretax Income
A1: Ticker | B1: 2022 | C1: 2023 | D1: 2024 | E1: 2025
A2: AAPL | B2: 119103000000 | C2: 113736000000 | D2: 123485000000 | E2: 132729000000
A3: AMD | B3: 1184000000 | C3: 492000000 | D3: 1989000000 | E3: 4140000000
A4: AMGN | B4: 7346000000 | C4: 7855000000 | D4: 4609000000 | E4: 8976000000
A5: AMZN | B5: -5936000000 | C5: 37557000000 | D5: 68614000000 | E5: 97311000000
A6: ASML | B6: 6456100000 | C6: 9083500000 | D6: 9042400000 | E6: 11406100000
A7: CCEP | B7: 1957000000 | C7: 2203000000 | D7: 1936000000 | E7: 2569000000
A8: CHTR | B8: 7462000000 | C8: 6854000000 | D8: 7502000000 | E8: 7458000000
A9: COST | B9: 7840000000 | C9: 8487000000 | D9: 9740000000 | E9: 10818000000
A10: GILD | B10: 5814000000 | C10: 6859000000 | D10: 690000000 | E10: 9796000000
A11: GOOGL | B11: 71328000000 | C11: 85717000000 | D11: 119815000000 | E11: 158826000000
A12: KDP | B12: 1719000000 | C12: 2757000000 | D12: 1914000000 | E12: 2687000000
... A23: VRTX | B23: 4232400000 | C23: 4379800000 | D23: 248500000 | E23: 4643200000

Sheet Tax Provision
A1: Ticker | B1: 2022 | C1: 2023 | D1: 2024 | E1: 2025
A2: AAPL | B2: 19300000000 | C2: 16741000000 | D2: 29749000000 | E2: 20719000000
A3: AMD | B3: -122000000 | C3: -346000000 | D3: 381000000 | E3: -103000000
A4: AMGN | B4: 794000000 | C4: 1138000000 | D4: 519000000 | E4: 1265000000
A5: ASML | B5: 969900000 | C5: 1435800000 | D5: 1680600000 | E5: 2013400000
A6: CCEP | B6: 436000000 | C6: 534000000 | D6: 492000000 | E6: 590000000
A7: CHTR | B7: 1613000000 | C7: 1593000000 | D7: 1649000000 | E7: 1692000000
A8: COST | B8: 1925000000 | C8: 2195000000 | D8: 2373000000 | E8: 2719000000
A9: GILD | B9: 1248000000 | C9: 1247000000 | D9: 211000000 | E9: 1286000000
A10: GOOGL | B10: 11356000000 | C10: 11922000000 | D10: 19697000000 | E10: 26656000000
A11: KDP | B11: 284000000 | C11: 576000000 | D11: 473000000 | E11: 608000000
A12: MDLZ | B12: 865000000 | C12: 1537000000 | D12: 1469000000 | E12: 782000000
... A22: VRTX | B22: 910400000 | C22: 760200000 | D22: 784100000 | E22: 690000000

Sheet Tax Rate
A1: Ticker | B1: 2022 | C1: 2023 | D1: 2024 | E1: 2025
A2: AAPL | B2: 0.16204462 | C2: 0.14719174 | D2: 0.24091185 | E2: 0.15610002
A3: AMD | B3: -0.10304054 | C3: -0.70325203 | D3: 0.19155354 | E3: -0.024879227
A4: AMGN | B4: 0.10808603 | C4: 0.14487588 | D4: 0.11260577 | E4: 0.14093137
A5: ASML | B5: 0.15023002 | C5: 0.15806682 | D5: 0.18585774 | E5: 0.17651958
A6: CCEP | B6: 0.22278998 | C6: 0.24239673 | D6: 0.25413223 | E6: 0.22966135
A7: CHTR | B7: 0.21616189 | C7: 0.23241903 | D7: 0.21980805 | E7: 0.22687047
A8: COST | B8: 0.24553571 | C8: 0.25863085 | D8: 0.2436345 | E8: 0.25134036
A9: GILD | B9: 0.21465428 | C9: 0.18180493 | D9: 0.3057971 | E9: 0.13127807
A10: GOOGL | B10: 0.15920817 | C10: 0.1390856 | D10: 0.16439511 | E10: 0.16783146
A11: KDP | B11: 0.16521233 | C11: 0.20892274 | D11: 0.24712644 | E11: 0.22627466
A12: MDLZ | B12: 0.26796778 | C12: 0.26139456 | D12: 0.23462706 | E12: 0.25945587
... A22: VRTX | B22: 0.21510254 | C22: 0.17356957 | D22: 3.155332 | E22: 0.14860441

Sheet NOPAT
A1: Ticker | B1: 2022 | C1: 2023 | D1: 2024 | E1: 2025
A2: AAPL | B2: 1.0008288e+11 | C2: 9.7476837e+10 | D2: 9.3531805e+10 | E2: 1.1228089e+11
A3: AMD | B3: 1.4030676e+09 | C3: 1.0185447e+09 | D3: 1.6823771e+09 | E3: 4.3772592e+09
A4: AMGN | B4: 7.806031e+09 | C4: 9.1754819e+09 | D4: 6.8897288e+09 | E4: 1.0077734e+10
A5: AMZN | B5: -2819510000 | C5: 32183810000 | D5: 56105800000 | E5: 78672150000
A6: ASML | B6: 5.537866e+09 | C6: 7.7762632e+09 | D6: 7.4941795e+09 | E6: 9.4901177e+09
A7: CCEP | B7: 1.646908e+09 | C7: 1.7917317e+09 | D7: 1624500000 | E7: 2.1900728e+09
A8: CHTR | B8: 9.4201664e+09 | C8: 9.2432101e+09 | D8: 9.9326237e+09 | E8: 9.6641191e+09
A9: COST | B9: 6.0342054e+09 | C9: 6.4106191e+09 | D9: 7.4948258e+09 | E9: 8.2142936e+09
A10: GILD | B10: 5.3002982e+09 | C10: 6.3843761e+09 | D10: 1.1572362e+09 | E10: 9.3995713e+09
A11: GOOGL | B11: 6.0272163e+10 | C11: 7.4060162e+10 | D11: 1.0034194e+11 | E11: 1.3278248e+11
A12: KDP | B12: 2.0135079e+09 | C12: 2.5733743e+09 | D12: 1.9943621e+09 | E12: 2.6623889e+09
... A23: VRTX | B23: 3.3650124e+09 | C23: 3.6560456e+09 | D23: -6.0155316e+08 | E23: 3.9645236e+09

Sheet Invested Capital
A1: Ticker | B1: 2022 | C1: 2023 | D1: 2024 | E1: 2025
A2: AAPL | B2: 170741000000 | C2: 173234000000 | D2: 163579000000 | E2: 172390000000
A3: AMD | B3: 57217000000 | C3: 58360000000 | D3: 59289000000 | E3: 66221000000
A4: AMGN | B4: 42606000000 | C4: 70845000000 | D4: 65976000000 | E4: 63262000000
A5: AMZN | B5: 213193000000 | C5: 260189000000 | D5: 338593000000 | E5: 476713000000
A6: ASML | B6: 13071200000 | C6: 18084000000 | D6: 23164400000 | E6: 24003100000
A7: CCEP | B7: 18678000000 | C7: 18680000000 | D7: 19112000000 | E7: 17830000000
A8: CHTR | B8: 106722000000 | C8: 109288000000 | D8: 111350000000 | E8: 113175000000
A9: COST | B9: 27199000000 | C9: 31516000000 | D9: 29416000000 | E9: 34877000000
A10: GILD | B10: 46470000000 | C10: 47820000000 | D10: 46041000000 | E10: 47638000000
A11: GOOGL | B11: 269001000000 | C11: 295249000000 | D11: 335967000000 | E11: 461812000000
A12: KDP | B12: 37093000000 | C12: 38867000000 | D12: 39797000000 | E12: 41657000000
... A23: VRTX | B23: 13912700000 | C23: 17580400000 | D23: 16409600000 | E23: 18665800000

Sheet Gross Margin
A1: Ticker | B1: 2022 | C1: 2023 | D1: 2024 | E1: 2025
A2: AAPL | B2: 0.43309631 | C2: 0.4413113 | D2: 0.4620635 | E2: 0.46905164
A3: AMD | B3: 0.44926062 | C3: 0.46119929 | D3: 0.49350398 | E3: 0.49516441
A4: AMGN | B4: 0.75663868 | C4: 0.70021284 | D4: 0.61530637 | E4: 0.6724715
A5: AMZN | B5: 0.4380534 | C5: 0.46982089 | D5: 0.48854393 | E5: 0.50285665
A6: ASML | B6: 0.50535578 | C6: 0.51294882 | D6: 0.51275701 | E6: 0.52829588
A7: CCEP | B7: 0.35935335 | C7: 0.36717299 | D7: 0.35282317 | E7: 0.35596383
A8: CHTR | B8: 0.54627744 | C8: 0.54767704 | D8: 0.55797404 | E8: 0.56537773
A9: COST | B9: 0.12148717 | C9: 0.12259689 | D9: 0.12613331 | E9: 0.12843207
A10: GILD | B10: 0.79263957 | C10: 0.76036289 | D10: 0.78260416 | E10: 0.78826167
A11: GOOGL | B11: 0.55379443 | C11: 0.56625048 | D11: 0.58200435 | E11: 0.59652315
A12: KDP | B12: 0.52095042 | C12: 0.54543 | D12: 0.55559898 | E12: 0.54201048
... A23: VRTX | B23: 0.87903524 | C23: 0.87210716 | D23: 0.86111741 | E23: 0.86240657

Sheet Operating Margin
A1: Ticker | B1: 2022 | C1: 2023 | D1: 2024 | E1: 2025
A2: AAPL | B2: 0.30288744 | C2: 0.29821412 | D2: 0.31510223 | E2: 0.319708
A3: AMD | B3: 0.053896021 | C3: 0.026366843 | D3: 0.080705837 | E3: 0.12330033
A4: AMGN | B4: 0.3324849 | C4: 0.38063143 | D4: 0.23228818 | E4: 0.3192022
A5: AMZN | B5: -0.0069438094 | C5: 0.070876937 | D5: 0.11132377 | E5: 0.13890594
A6: ASML | B6: 0.30778713 | C6: 0.33514887 | D6: 0.32569198 | E6: 0.35278092
A7: CCEP | B7: 0.12234411 | C7: 0.12922085 | D7: 0.1065662 | E7: 0.1360222
A8: CHTR | B8: 0.22246492 | C8: 0.22052118 | D8: 0.23111555 | E8: 0.22821046
A9: COST | B9: 0.035240621 | C9: 0.035688638 | D9: 0.038942359 | E9: 0.039864116
A10: GILD | B10: 0.24738829 | C10: 0.28776368 | D10: 0.057974543 | E10: 0.36750221
A11: GOOGL | B11: 0.25345076 | C11: 0.27985257 | D11: 0.34307664 | E11: 0.39609667
A12: KDP | B12: 0.17158711 | C12: 0.21958958 | D12: 0.17256205 | E12: 0.2072517
... A23: VRTX | B23: 0.48005196 | C23: 0.44825315 | D23: 0.025326449 | E23: 0.38799963

Sheet Net Profit Margin
A1: Ticker | B1: 2022 | C1: 2023 | D1: 2024 | E1: 2025
A2: AAPL | B2: 0.25309641 | C2: 0.25306234 | D2: 0.23971256 | E2: 0.26915064
A3: AMD | B3: 0.055929833 | C3: 0.037654321 | D3: 0.063641652 | E3: 0.12514795
A4: AMGN | B4: 0.2489078 | C4: 0.23827598 | D4: 0.12236716 | E4: 0.20981742
A5: AMZN | B5: -0.005295895 | C5: 0.052932836 | D5: 0.092871172 | E5: 0.10833784
A6: ASML | B6: 0.26562574 | C6: 0.28444944 | D6: 0.26789891 | E6: 0.2941596
A7: CCEP | B7: 0.087066975 | C7: 0.091192219 | D7: 0.069380566 | E7: 0.092914215
A8: CHTR | B8: 0.093572989 | C8: 0.08345084 | D8: 0.092275574 | E8: 0.091046847
A9: COST | B9: 0.025749711 | C9: 0.02596888 | D9: 0.028952302 | E9: 0.029425763
A10: GILD | B10: 0.16832228 | C10: 0.20891724 | D10: 0.01669333 | E10: 0.28904286
A11: GOOGL | B11: 0.21203807 | C11: 0.24006649 | D11: 0.28603672 | E11: 0.32809878
A12: KDP | B12: 0.10215551 | C12: 0.1472256 | D12: 0.093870106 | E12: 0.12521833
... A23: VRTX | B23: 0.37197532 | C23: 0.36675718 | D23: -0.0486021 | E23: 0.32939765

Sheet ROE
A1: Ticker | B1: 2022 | C1: 2023 | D1: 2024 | E1: 2025
A2: AAPL | B2: 1.9695887 | C2: 1.7194951 | D2: 1.5741251 | E2: 1.7142245
A3: AMD | B3: 0.024109589 | C3: 0.015437176 | D3: 0.028926494 | E3: 0.071910224
A4: AMGN | B4: 1.789675 | C4: 1.3579298 | D4: 0.6755306 | E4: 1.0610251
A5: AMZN | B5: -0.018638346 | C5: 0.17489753 | D5: 0.24289682 | E5: 0.22285825
A6: ASML | B6: 0.63833023 | C6: 0.70421143 | D6: 0.47427433 | E6: 0.50457612
A7: CCEP | B7: 0.20249765 | C7: 0.21643001 | D7: 0.17224415 | E7: 0.23793188
A8: CHTR | B8: 0.5543371 | C8: 0.45107647 | D8: 0.38113448 | E8: 0.31522392
A9: COST | B9: 0.2831121 | C9: 0.27536105 | D9: 0.3026705 | E9: 0.30686167
A10: GILD | B10: 0.21619586 | C10: 0.25707349 | D10: 0.022768778 | E10: 0.40492958
A11: GOOGL | B11: 0.23413392 | C11: 0.27355646 | D11: 0.32908492 | E11: 0.35704782
A12: KDP | B12: 0.057151954 | C12: 0.085862761 | D12: 0.057733528 | E12: 0.083562773
... A23: VRTX | B23: 0.23877464 | C23: 0.22986622 | D23: -0.031515152 | E23: 0.22541154

Sheet ROA
A1: Ticker | B1: 2022 | C1: 2023 | D1: 2024 | E1: 2025
A2: AAPL | B2: 0.28292441 | C2: 0.27503126 | D2: 0.26126208 | E2: 0.30932547
A3: AMD | B3: 0.019532406 | C3: 0.012608423 | D3: 0.02393681 | E3: 0.059321802
A4: AMGN | B4: 0.10061271 | C4: 0.082785395 | D4: 0.043282026 | E4: 0.084538852
A5: AMZN | B5: -0.0058831793 | C5: 0.061431821 | D5: 0.10279437 | E5: 0.1076555
A6: ASML | B6: 0.15493493 | C6: 0.20559181 | D6: 0.17101859 | E6: 0.19382348
A7: CCEP | B7: 0.051444751 | C7: 0.056994553 | D7: 0.046989429 | E7: 0.063701371
A8: CHTR | B8: 0.034977132 | C8: 0.031242716 | D8: 0.034204426 | E8: 0.032784083
A9: COST | B9: 0.091076271 | C9: 0.094502854 | D9: 0.10613362 | E9: 0.11024297
A10: GILD | B10: 0.072691583 | C10: 0.090425872 | D10: 0.0079260238 | E10: 0.14421529
A11: GOOGL | B11: 0.16418809 | C11: 0.1922606 | D11: 0.23484017 | E11: 0.25282702
A12: KDP | B12: 0.02770222 | C12: 0.041955621 | D12: 0.027302008 | E12: 0.038185675
... A23: VRTX | B23: 0.18302123 | C23: 0.17707938 | D23: -0.02366592 | E23: 0.16411423

Sheet ROIC
A1: Ticker | B1: 2022 | C1: 2023 | D1: 2024 | E1: 2025
A2: AAPL | B2: 0.5861678 | C2: 0.56268883 | D2: 0.5717837 | E2: 0.65131906
A3: AMD | B3: 0.024521865 | C3: 0.017452788 | D3: 0.028375872 | E3: 0.066100771
A4: AMGN | B4: 0.18321436 | C4: 0.12951488 | D4: 0.1044278 | E4: 0.15930154
A5: AMZN | B5: -0.013225153 | C5: 0.12369397 | D5: 0.16570278 | E5: 0.16503043
A6: ASML | B6: 0.42366929 | C6: 0.43000792 | D6: 0.32352142 | E6: 0.3953705
A7: CCEP | B7: 0.088173681 | C7: 0.095917116 | D7: 0.084998954 | E7: 0.12283078
A8: CHTR | B8: 0.088268271 | C8: 0.084576624 | D8: 0.089201829 | E8: 0.085390935
A9: COST | B9: 0.22185394 | C9: 0.2034084 | D9: 0.25478739 | E9: 0.23552179
A10: GILD | B10: 0.11405849 | C10: 0.13350849 | D10: 0.025134907 | E10: 0.19731247
A11: GOOGL | B11: 0.22405925 | C11: 0.25083967 | D11: 0.29866607 | E11: 0.28752496
A12: KDP | B12: 0.054282691 | C12: 0.066209749 | D12: 0.050113377 | E12: 0.063912161
... A23: VRTX | B23: 0.24186624 | C23: 0.20796146 | D23: -0.036658612 | E23: 0.21239505

Sheet Payout Ratio based on FCF
A1: Ticker | B1: 2022 | C1: 2023 | D1: 2024 | E1: 2025
A2: AAPL | B2: 0.13317122 | C2: 0.15087765 | D2: 0.14000937 | E2: 0.15613515
A3: AMGN | B3: 0.47763233 | C3: 0.61910586 | D3: 0.46488359 | E3: 0.63259259
A4: ASML | B4: 0.35713987 | C4: 0.72317689 | D4: 0.27005097 | E4: 0.23127148
A5: CCEP | B5: 0.32760842 | C5: 0.4217653 | D5: 0.42884072 | E5: 0.46280579
A6: COST | B6: 0.42787775 | C6: 0.18547072 | D6: 0.18871625 | E6: 0.15962741
A7: GILD | B7: 0.44451103 | C7: 0.51327314 | D7: 0.38020378 | E7: 0.4233291
A8: GOOGL | B8: 0 | C8: 0 | D8: 0.10119015 | E8: 0.13715775
A9: KDP | B9: 0.43938161 | C9: 1.3466981 | D9: 0.7150908 | E9: 0.76747312
A10: MDLZ | B10: 0.66122585 | C10: 0.59966685 | D10: 0.66676128 | E10: 0.76877898
A11: MELI | B11: 0 | C11: 0 | D11: 0 | E11: 0
A12: META | B12: 0 | C12: 0 | D12: 0.093800858 | E12: 0.11546553
... A14: PEP | B14: 1.1013562 | C14: 0.84326098 | D14: 1.0055641 | E14: 0.9955683
A15: REGN | C15: 0 | D15: 0 | E15: 0.098348029
A16: TMUS | B16: 0 | C16: 0.096411977 | D16: 0.33059507 | E16: 0.26712906

Sheet Payout Ratio based on NI
A1: Ticker | B1: 2022 | C1: 2023 | D1: 2024 | E1: 2025
A2: AAPL | B2: 0.14870294 | C2: 0.15490489 | D2: 0.16252027 | E2: 0.13767521
A3: AMGN | B3: 0.64041514 | C3: 0.67827899 | D3: 1.1814181 | E3: 0.66450525
A4: ASML | B4: 0.45514029 | C4: 0.29956627 | D4: 0.32396059 | E4: 0.26539638
A5: CCEP | B5: 0.50596817 | C5: 0.50389455 | D5: 0.64174894 | E5: 0.47734295
A6: COST | B6: 0.25633128 | C6: 0.1988239 | D6: 0.16981132 | E6: 0.15446351
A7: GILD | B7: 0.80770906 | C7: 0.67237423 | D7: 8.1625 | E7: 0.47038778
A8: GOOGL | B8: 0 | C8: 0 | D8: 0.073543219 | E8: 0.076030869
A9: KDP | B9: 0.75208914 | C9: 0.52361302 | D9: 0.7925052 | E9: 0.54930255
A10: MDLZ | B10: 0.7305852 | C10: 0.43557169 | D10: 0.50943396 | E10: 1.0146879
A11: MELI | B11: 0 | C11: 0 | D11: 0 | E11: 0
A12: META | B12: 0 | C12: 0 | D12: 0.081334189 | E12: 0.088061133
... A14: PEP | B14: 0.69270483 | C14: 0.73638968 | D14: 0.75475047 | E14: 0.92694175
A15: REGN | C15: 0 | D15: 0 | E15: 0.082199383
A16: TMUS | B16: 0 | C16: 0.089816039 | D16: 0.29103096 | E16: 0.37490902

Sheet D E
A1: Ticker | B1: 2022 | C1: 2023 | D1: 2024 | E1: 2025
A2: AAPL | B2: 2.6144616 | C2: 1.7875326 | D2: 1.8723266 | E2: 1.3380305
A3: AMD | B3: 0.052292237 | C3: 0.053728619 | D3: 0.038424125 | E3: 0.061064461
A4: AMGN | B4: 10.637804 | C4: 10.36794 | D4: 10.226136 | E4: 6.3067683
A5: AMZN | B5: 0.95942976 | C5: 0.67175728 | D5: 0.45774032 | E5: 0.37217228
A6: ASML | B6: 0.48354292 | C6: 0.34429544 | D6: 0.25370194 | E6: 0.22388615
A7: CCEP | B7: 1.5988989 | C7: 1.4287864 | D7: 1.3347862 | E7: 1.3649011
A8: CHTR | B8: 10.703257 | C8: 8.8581995 | D8: 6.1437737 | E8: 6.0496449
A9: COST | B9: 0.43789361 | C9: 0.35453747 | D9: 0.34582169 | E9: 0.28024277
